E5TP1/decoderBCD.v
//This BCD Decoder supports numbers of up to 5-bits
//I'm not sure if Decoder is the proper name

module decoderBCD (
  in,   //5-bit Input Value
  out0, //4-bit Output BCD Digit 0
  out1  //4-bit Output BCD Digit 1
);

//Input Declaration
input [4:0] in;

//Output Declaration
output [3:0] out0;
output [3:0] out1;

//Resources Definition
wire [4:0] in;
reg [3:0] out0;
reg [3:0] out1;

initial begin
  out0 = 0;
  out1 = 0;
end

always @(in) begin
out1 = in/10;
out0 = in%10;
end

endmodule

E5TP1/sum4bit.v
module sum4bit(
    x0, //Sumando 0 (4-bit)
    x1, //Sumando 1 (4-bit)
    o   //Resultado (5-bit)
);

//Definiendo Inputs
input [3:0] x0, x1; //Sumandos

//Definiendo Outputs
output [4:0] o;   //Resultado

//Definiendo los tipos de dato
wire [3:0] x0, x1;
wire [4:0] o;

assign o = x0 + x1;

endmodule

E5TP1/adderBCD.v
`include "decoderBCD.v"
`include "sum4bit.v"

module adderBCD(
    in0,    //BCD Input 0
    in1,    //BCD Input 1
    out0,   //BCD Output 0
    out1    //BCD Output 1
);

//Defining Inputs
input [3:0] in0; //BCD Input 0
input [3:0] in1; //BCD Input 1

//Defining Outputs
output [3:0] out0;  //BCD Output digit 0
output [3:0] out1;  //BCD Output digit 1

//Defining data types
wire [3:0] in0, in1;
wire [4:0] sum;
wire [3:0] out0,out1;

//Declaring included modules
sum4bit adder(.x0(in0),.x1(in1),.o(sum));
decoderBCD decoder (.in(sum),.out0(out0),.out1(out1));


//Code
/*
Get whatever is going to do the sum of the 2 4-bit numbers here
*/

endmodule

E5TP1/adderBCD_tb.v
`include "adderBCD.v"

module adderBCD_tb;

//Test Data Types
reg [3:0] in0, in1;
wire [3:0] out0, out1;

//Test Indexes
reg [3:0] i,j;

//Connecting the ports adderBCD
adderBCD adder_udt(.in0(in0), .in1(in1), .out0(out0), .out1(out1));


//Code
initial begin
  $dumpfile( "adderBCD.vcd");
  $dumpvars;
end

initial begin
  in0 = 0;
  in1 = 0;
  $display("In0\tIn1\tOut");
  $monitor("%d\t%d\t%d,%d", in0, in1, out1, out0);
end


always begin
for (i = 0; i<15 ; i = i+1) begin
    #1 in0 = i;
    for (j=0; j<15; j = j+1) begin
      #1in1 = j;
    end
end
#20$finish;
end



endmodule

E5TP1/adderBCD.vcd
$date
	Wed Aug 22 01:33:00 2018
$end
$version
	Icarus Verilog
$end
$timescale
	1s
$end
$scope module adderBCD_tb $end
$var wire 4 ! out0 [3:0] $end
$var wire 4 " out1 [3:0] $end
$var reg 4 # i [3:0] $end
$var reg 4 $ in0 [3:0] $end
$var reg 4 % in1 [3:0] $end
$var reg 4 & j [3:0] $end
$scope module adder_udt $end
$var wire 4 ' in0 [3:0] $end
$var wire 4 ( in1 [3:0] $end
$var wire 4 ) out0 [3:0] $end
$var wire 4 * out1 [3:0] $end
$var wire 5 + sum [4:0] $end
$scope module adder $end
$var wire 5 , o [4:0] $end
$var wire 4 - x0 [3:0] $end
$var wire 4 . x1 [3:0] $end
$upscope $end
$scope module decoder $end
$var wire 5 / in [4:0] $end
$var wire 4 0 out0 [3:0] $end
$var wire 4 1 out1 [3:0] $end
$upscope $end
$upscope $end
$upscope $end
$enddefinitions $end
#0
$dumpvars
b0 1
b0 0
b0 /
b0 .
b0 -
b0 ,
b0 +
b0 *
b0 )
b0 (
b0 '
bx &
b0 %
b0 $
b0 #
b0 "
b0 !
$end
#1
b0 &
#2
b1 &
#3
b1 !
b1 )
b1 0
b10 &
b1 %
b1 (
b1 .
b1 +
b1 ,
b1 /
#4
b10 !
b10 )
b10 0
b11 &
b10 %
b10 (
b10 .
b10 +
b10 ,
b10 /
#5
b11 !
b11 )
b11 0
b100 &
b11 %
b11 (
b11 .
b11 +
b11 ,
b11 /
#6
b100 !
b100 )
b100 0
b101 &
b100 %
b100 (
b100 .
b100 +
b100 ,
b100 /
#7
b101 !
b101 )
b101 0
b110 &
b101 %
b101 (
b101 .
b101 +
b101 ,
b101 /
#8
b110 !
b110 )
b110 0
b111 &
b110 %
b110 (
b110 .
b110 +
b110 ,
b110 /
#9
b111 !
b111 )
b111 0
b1000 &
b111 %
b111 (
b111 .
b111 +
b111 ,
b111 /
#10
b1000 !
b1000 )
b1000 0
b1001 &
b1000 %
b1000 (
b1000 .
b1000 +
b1000 ,
b1000 /
#11
b1001 !
b1001 )
b1001 0
b1010 &
b1001 %
b1001 (
b1001 .
b1001 +
b1001 ,
b1001 /
#12
b0 !
b0 )
b0 0
b1 "
b1 *
b1 1
b1011 &
b1010 %
b1010 (
b1010 .
b1010 +
b1010 ,
b1010 /
#13
b1 !
b1 )
b1 0
b1100 &
b1011 %
b1011 (
b1011 .
b1011 +
b1011 ,
b1011 /
#14
b10 !
b10 )
b10 0
b1101 &
b1100 %
b1100 (
b1100 .
b1100 +
b1100 ,
b1100 /
#15
b11 !
b11 )
b11 0
b1110 &
b1101 %
b1101 (
b1101 .
b1101 +
b1101 ,
b1101 /
#16
b100 !
b100 )
b100 0
b1 #
b1111 &
b1110 %
b1110 (
b1110 .
b1110 +
b1110 ,
b1110 /
#17
b101 !
b101 )
b101 0
b0 &
b1 $
b1 '
b1 -
b1111 +
b1111 ,
b1111 /
#18
b1 !
b1 )
b1 0
b0 "
b0 *
b0 1
b1 &
b0 %
b0 (
b0 .
b1 +
b1 ,
b1 /
#19
b10 !
b10 )
b10 0
b10 &
b1 %
b1 (
b1 .
b10 +
b10 ,
b10 /
#20
b11 !
b11 )
b11 0
b11 &
b10 %
b10 (
b10 .
b11 +
b11 ,
b11 /
#21
b100 !
b100 )
b100 0
b100 &
b11 %
b11 (
b11 .
b100 +
b100 ,
b100 /
#22
b101 !
b101 )
b101 0
b101 &
b100 %
b100 (
b100 .
b101 +
b101 ,
b101 /
#23
b110 !
b110 )
b110 0
b110 &
b101 %
b101 (
b101 .
b110 +
b110 ,
b110 /
#24
b111 !
b111 )
b111 0
b111 &
b110 %
b110 (
b110 .
b111 +
b111 ,
b111 /
#25
b1000 !
b1000 )
b1000 0
b1000 &
b111 %
b111 (
b111 .
b1000 +
b1000 ,
b1000 /
#26
b1001 !
b1001 )
b1001 0
b1001 &
b1000 %
b1000 (
b1000 .
b1001 +
b1001 ,
b1001 /
#27
b0 !
b0 )
b0 0
b1 "
b1 *
b1 1
b1010 &
b1001 %
b1001 (
b1001 .
b1010 +
b1010 ,
b1010 /
#28
b1 !
b1 )
b1 0
b1011 &
b1010 %
b1010 (
b1010 .
b1011 +
b1011 ,
b1011 /
#29
b10 !
b10 )
b10 0
b1100 &
b1011 %
b1011 (
b1011 .
b1100 +
b1100 ,
b1100 /
#30
b11 !
b11 )
b11 0
b1101 &
b1100 %
b1100 (
b1100 .
b1101 +
b1101 ,
b1101 /
#31
b100 !
b100 )
b100 0
b1110 &
b1101 %
b1101 (
b1101 .
b1110 +
b1110 ,
b1110 /
#32
b101 !
b101 )
b101 0
b10 #
b1111 &
b1110 %
b1110 (
b1110 .
b1111 +
b1111 ,
b1111 /
#33
b110 !
b110 )
b110 0
b0 &
b10 $
b10 '
b10 -
b10000 +
b10000 ,
b10000 /
#34
b10 !
b10 )
b10 0
b0 "
b0 *
b0 1
b1 &
b0 %
b0 (
b0 .
b10 +
b10 ,
b10 /
#35
b11 !
b11 )
b11 0
b10 &
b1 %
b1 (
b1 .
b11 +
b11 ,
b11 /
#36
b100 !
b100 )
b100 0
b11 &
b10 %
b10 (
b10 .
b100 +
b100 ,
b100 /
#37
b101 !
b101 )
b101 0
b100 &
b11 %
b11 (
b11 .
b101 +
b101 ,
b101 /
#38
b110 !
b110 )
b110 0
b101 &
b100 %
b100 (
b100 .
b110 +
b110 ,
b110 /
#39
b111 !
b111 )
b111 0
b110 &
b101 %
b101 (
b101 .
b111 +
b111 ,
b111 /
#40
b1000 !
b1000 )
b1000 0
b111 &
b110 %
b110 (
b110 .
b1000 +
b1000 ,
b1000 /
#41
b1001 !
b1001 )
b1001 0
b1000 &
b111 %
b111 (
b111 .
b1001 +
b1001 ,
b1001 /
#42
b0 !
b0 )
b0 0
b1 "
b1 *
b1 1
b1001 &
b1000 %
b1000 (
b1000 .
b1010 +
b1010 ,
b1010 /
#43
b1 !
b1 )
b1 0
b1010 &
b1001 %
b1001 (
b1001 .
b1011 +
b1011 ,
b1011 /
#44
b10 !
b10 )
b10 0
b1011 &
b1010 %
b1010 (
b1010 .
b1100 +
b1100 ,
b1100 /
#45
b11 !
b11 )
b11 0
b1100 &
b1011 %
b1011 (
b1011 .
b1101 +
b1101 ,
b1101 /
#46
b100 !
b100 )
b100 0
b1101 &
b1100 %
b1100 (
b1100 .
b1110 +
b1110 ,
b1110 /
#47
b101 !
b101 )
b101 0
b1110 &
b1101 %
b1101 (
b1101 .
b1111 +
b1111 ,
b1111 /
#48
b110 !
b110 )
b110 0
b11 #
b1111 &
b1110 %
b1110 (
b1110 .
b10000 +
b10000 ,
b10000 /
#49
b111 !
b111 )
b111 0
b0 &
b11 $
b11 '
b11 -
b10001 +
b10001 ,
b10001 /
#50
b11 !
b11 )
b11 0
b0 "
b0 *
b0 1
b1 &
b0 %
b0 (
b0 .
b11 +
b11 ,
b11 /
#51
b100 !
b100 )
b100 0
b10 &
b1 %
b1 (
b1 .
b100 +
b100 ,
b100 /
#52
b101 !
b101 )
b101 0
b11 &
b10 %
b10 (
b10 .
b101 +
b101 ,
b101 /
#53
b110 !
b110 )
b110 0
b100 &
b11 %
b11 (
b11 .
b110 +
b110 ,
b110 /
#54
b111 !
b111 )
b111 0
b101 &
b100 %
b100 (
b100 .
b111 +
b111 ,
b111 /
#55
b1000 !
b1000 )
b1000 0
b110 &
b101 %
b101 (
b101 .
b1000 +
b1000 ,
b1000 /
#56
b1001 !
b1001 )
b1001 0
b111 &
b110 %
b110 (
b110 .
b1001 +
b1001 ,
b1001 /
#57
b0 !
b0 )
b0 0
b1 "
b1 *
b1 1
b1000 &
b111 %
b111 (
b111 .
b1010 +
b1010 ,
b1010 /
#58
b1 !
b1 )
b1 0
b1001 &
b1000 %
b1000 (
b1000 .
b1011 +
b1011 ,
b1011 /
#59
b10 !
b10 )
b10 0
b1010 &
b1001 %
b1001 (
b1001 .
b1100 +
b1100 ,
b1100 /
#60
b11 !
b11 )
b11 0
b1011 &
b1010 %
b1010 (
b1010 .
b1101 +
b1101 ,
b1101 /
#61
b100 !
b100 )
b100 0
b1100 &
b1011 %
b1011 (
b1011 .
b1110 +
b1110 ,
b1110 /
#62
b101 !
b101 )
b101 0
b1101 &
b1100 %
b1100 (
b1100 .
b1111 +
b1111 ,
b1111 /
#63
b110 !
b110 )
b110 0
b1110 &
b1101 %
b1101 (
b1101 .
b10000 +
b10000 ,
b10000 /
#64
b111 !
b111 )
b111 0
b100 #
b1111 &
b1110 %
b1110 (
b1110 .
b10001 +
b10001 ,
b10001 /
#65
b1000 !
b1000 )
b1000 0
b0 &
b100 $
b100 '
b100 -
b10010 +
b10010 ,
b10010 /
#66
b100 !
b100 )
b100 0
b0 "
b0 *
b0 1
b1 &
b0 %
b0 (
b0 .
b100 +
b100 ,
b100 /
#67
b101 !
b101 )
b101 0
b10 &
b1 %
b1 (
b1 .
b101 +
b101 ,
b101 /
#68
b110 !
b110 )
b110 0
b11 &
b10 %
b10 (
b10 .
b110 +
b110 ,
b110 /
#69
b111 !
b111 )
b111 0
b100 &
b11 %
b11 (
b11 .
b111 +
b111 ,
b111 /
#70
b1000 !
b1000 )
b1000 0
b101 &
b100 %
b100 (
b100 .
b1000 +
b1000 ,
b1000 /
#71
b1001 !
b1001 )
b1001 0
b110 &
b101 %
b101 (
b101 .
b1001 +
b1001 ,
b1001 /
#72
b0 !
b0 )
b0 0
b1 "
b1 *
b1 1
b111 &
b110 %
b110 (
b110 .
b1010 +
b1010 ,
b1010 /
#73
b1 !
b1 )
b1 0
b1000 &
b111 %
b111 (
b111 .
b1011 +
b1011 ,
b1011 /
#74
b10 !
b10 )
b10 0
b1001 &
b1000 %
b1000 (
b1000 .
b1100 +
b1100 ,
b1100 /
#75
b11 !
b11 )
b11 0
b1010 &
b1001 %
b1001 (
b1001 .
b1101 +
b1101 ,
b1101 /
#76
b100 !
b100 )
b100 0
b1011 &
b1010 %
b1010 (
b1010 .
b1110 +
b1110 ,
b1110 /
#77
b101 !
b101 )
b101 0
b1100 &
b1011 %
b1011 (
b1011 .
b1111 +
b1111 ,
b1111 /
#78
b110 !
b110 )
b110 0
b1101 &
b1100 %
b1100 (
b1100 .
b10000 +
b10000 ,
b10000 /
#79
b111 !
b111 )
b111 0
b1110 &
b1101 %
b1101 (
b1101 .
b10001 +
b10001 ,
b10001 /
#80
b1000 !
b1000 )
b1000 0
b101 #
b1111 &
b1110 %
b1110 (
b1110 .
b10010 +
b10010 ,
b10010 /
#81
b1001 !
b1001 )
b1001 0
b0 &
b101 $
b101 '
b101 -
b10011 +
b10011 ,
b10011 /
#82
b101 !
b101 )
b101 0
b0 "
b0 *
b0 1
b1 &
b0 %
b0 (
b0 .
b101 +
b101 ,
b101 /
#83
b110 !
b110 )
b110 0
b10 &
b1 %
b1 (
b1 .
b110 +
b110 ,
b110 /
#84
b111 !
b111 )
b111 0
b11 &
b10 %
b10 (
b10 .
b111 +
b111 ,
b111 /
#85
b1000 !
b1000 )
b1000 0
b100 &
b11 %
b11 (
b11 .
b1000 +
b1000 ,
b1000 /
#86
b1001 !
b1001 )
b1001 0
b101 &
b100 %
b100 (
b100 .
b1001 +
b1001 ,
b1001 /
#87
b0 !
b0 )
b0 0
b1 "
b1 *
b1 1
b110 &
b101 %
b101 (
b101 .
b1010 +
b1010 ,
b1010 /
#88
b1 !
b1 )
b1 0
b111 &
b110 %
b110 (
b110 .
b1011 +
b1011 ,
b1011 /
#89
b10 !
b10 )
b10 0
b1000 &
b111 %
b111 (
b111 .
b1100 +
b1100 ,
b1100 /
#90
b11 !
b11 )
b11 0
b1001 &
b1000 %
b1000 (
b1000 .
b1101 +
b1101 ,
b1101 /
#91
b100 !
b100 )
b100 0
b1010 &
b1001 %
b1001 (
b1001 .
b1110 +
b1110 ,
b1110 /
#92
b101 !
b101 )
b101 0
b1011 &
b1010 %
b1010 (
b1010 .
b1111 +
b1111 ,
b1111 /
#93
b110 !
b110 )
b110 0
b1100 &
b1011 %
b1011 (
b1011 .
b10000 +
b10000 ,
b10000 /
#94
b111 !
b111 )
b111 0
b1101 &
b1100 %
b1100 (
b1100 .
b10001 +
b10001 ,
b10001 /
#95
b1000 !
b1000 )
b1000 0
b1110 &
b1101 %
b1101 (
b1101 .
b10010 +
b10010 ,
b10010 /
#96
b1001 !
b1001 )
b1001 0
b110 #
b1111 &
b1110 %
b1110 (
b1110 .
b10011 +
b10011 ,
b10011 /
#97
b0 !
b0 )
b0 0
b10 "
b10 *
b10 1
b0 &
b110 $
b110 '
b110 -
b10100 +
b10100 ,
b10100 /
#98
b110 !
b110 )
b110 0
b0 "
b0 *
b0 1
b1 &
b0 %
b0 (
b0 .
b110 +
b110 ,
b110 /
#99
b111 !
b111 )
b111 0
b10 &
b1 %
b1 (
b1 .
b111 +
b111 ,
b111 /
#100
b1000 !
b1000 )
b1000 0
b11 &
b10 %
b10 (
b10 .
b1000 +
b1000 ,
b1000 /
#101
b1001 !
b1001 )
b1001 0
b100 &
b11 %
b11 (
b11 .
b1001 +
b1001 ,
b1001 /
#102
b0 !
b0 )
b0 0
b1 "
b1 *
b1 1
b101 &
b100 %
b100 (
b100 .
b1010 +
b1010 ,
b1010 /
#103
b1 !
b1 )
b1 0
b110 &
b101 %
b101 (
b101 .
b1011 +
b1011 ,
b1011 /
#104
b10 !
b10 )
b10 0
b111 &
b110 %
b110 (
b110 .
b1100 +
b1100 ,
b1100 /
#105
b11 !
b11 )
b11 0
b1000 &
b111 %
b111 (
b111 .
b1101 +
b1101 ,
b1101 /
#106
b100 !
b100 )
b100 0
b1001 &
b1000 %
b1000 (
b1000 .
b1110 +
b1110 ,
b1110 /
#107
b101 !
b101 )
b101 0
b1010 &
b1001 %
b1001 (
b1001 .
b1111 +
b1111 ,
b1111 /
#108
b110 !
b110 )
b110 0
b1011 &
b1010 %
b1010 (
b1010 .
b10000 +
b10000 ,
b10000 /
#109
b111 !
b111 )
b111 0
b1100 &
b1011 %
b1011 (
b1011 .
b10001 +
b10001 ,
b10001 /
#110
b1000 !
b1000 )
b1000 0
b1101 &
b1100 %
b1100 (
b1100 .
b10010 +
b10010 ,
b10010 /
#111
b1001 !
b1001 )
b1001 0
b1110 &
b1101 %
b1101 (
b1101 .
b10011 +
b10011 ,
b10011 /
#112
b0 !
b0 )
b0 0
b10 "
b10 *
b10 1
b111 #
b1111 &
b1110 %
b1110 (
b1110 .
b10100 +
b10100 ,
b10100 /
#113
b1 !
b1 )
b1 0
b0 &
b111 $
b111 '
b111 -
b10101 +
b10101 ,
b10101 /
#114
b111 !
b111 )
b111 0
b0 "
b0 *
b0 1
b1 &
b0 %
b0 (
b0 .
b111 +
b111 ,
b111 /
#115
b1000 !
b1000 )
b1000 0
b10 &
b1 %
b1 (
b1 .
b1000 +
b1000 ,
b1000 /
#116
b1001 !
b1001 )
b1001 0
b11 &
b10 %
b10 (
b10 .
b1001 +
b1001 ,
b1001 /
#117
b0 !
b0 )
b0 0
b1 "
b1 *
b1 1
b100 &
b11 %
b11 (
b11 .
b1010 +
b1010 ,
b1010 /
#118
b1 !
b1 )
b1 0
b101 &
b100 %
b100 (
b100 .
b1011 +
b1011 ,
b1011 /
#119
b10 !
b10 )
b10 0
b110 &
b101 %
b101 (
b101 .
b1100 +
b1100 ,
b1100 /
#120
b11 !
b11 )
b11 0
b111 &
b110 %
b110 (
b110 .
b1101 +
b1101 ,
b1101 /
#121
b100 !
b100 )
b100 0
b1000 &
b111 %
b111 (
b111 .
b1110 +
b1110 ,
b1110 /
#122
b101 !
b101 )
b101 0
b1001 &
b1000 %
b1000 (
b1000 .
b1111 +
b1111 ,
b1111 /
#123
b110 !
b110 )
b110 0
b1010 &
b1001 %
b1001 (
b1001 .
b10000 +
b10000 ,
b10000 /
#124
b111 !
b111 )
b111 0
b1011 &
b1010 %
b1010 (
b1010 .
b10001 +
b10001 ,
b10001 /
#125
b1000 !
b1000 )
b1000 0
b1100 &
b1011 %
b1011 (
b1011 .
b10010 +
b10010 ,
b10010 /
#126
b1001 !
b1001 )
b1001 0
b1101 &
b1100 %
b1100 (
b1100 .
b10011 +
b10011 ,
b10011 /
#127
b0 !
b0 )
b0 0
b10 "
b10 *
b10 1
b1110 &
b1101 %
b1101 (
b1101 .
b10100 +
b10100 ,
b10100 /
#128
b1 !
b1 )
b1 0
b1000 #
b1111 &
b1110 %
b1110 (
b1110 .
b10101 +
b10101 ,
b10101 /
#129
b10 !
b10 )
b10 0
b0 &
b1000 $
b1000 '
b1000 -
b10110 +
b10110 ,
b10110 /
#130
b1000 !
b1000 )
b1000 0
b0 "
b0 *
b0 1
b1 &
b0 %
b0 (
b0 .
b1000 +
b1000 ,
b1000 /
#131
b1001 !
b1001 )
b1001 0
b10 &
b1 %
b1 (
b1 .
b1001 +
b1001 ,
b1001 /
#132
b0 !
b0 )
b0 0
b1 "
b1 *
b1 1
b11 &
b10 %
b10 (
b10 .
b1010 +
b1010 ,
b1010 /
#133
b1 !
b1 )
b1 0
b100 &
b11 %
b11 (
b11 .
b1011 +
b1011 ,
b1011 /
#134
b10 !
b10 )
b10 0
b101 &
b100 %
b100 (
b100 .
b1100 +
b1100 ,
b1100 /
#135
b11 !
b11 )
b11 0
b110 &
b101 %
b101 (
b101 .
b1101 +
b1101 ,
b1101 /
#136
b100 !
b100 )
b100 0
b111 &
b110 %
b110 (
b110 .
b1110 +
b1110 ,
b1110 /
#137
b101 !
b101 )
b101 0
b1000 &
b111 %
b111 (
b111 .
b1111 +
b1111 ,
b1111 /
#138
b110 !
b110 )
b110 0
b1001 &
b1000 %
b1000 (
b1000 .
b10000 +
b10000 ,
b10000 /
#139
b111 !
b111 )
b111 0
b1010 &
b1001 %
b1001 (
b1001 .
b10001 +
b10001 ,
b10001 /
#140
b1000 !
b1000 )
b1000 0
b1011 &
b1010 %
b1010 (
b1010 .
b10010 +
b10010 ,
b10010 /
#141
b1001 !
b1001 )
b1001 0
b1100 &
b1011 %
b1011 (
b1011 .
b10011 +
b10011 ,
b10011 /
#142
b0 !
b0 )
b0 0
b10 "
b10 *
b10 1
b1101 &
b1100 %
b1100 (
b1100 .
b10100 +
b10100 ,
b10100 /
#143
b1 !
b1 )
b1 0
b1110 &
b1101 %
b1101 (
b1101 .
b10101 +
b10101 ,
b10101 /
#144
b10 !
b10 )
b10 0
b1001 #
b1111 &
b1110 %
b1110 (
b1110 .
b10110 +
b10110 ,
b10110 /
#145
b11 !
b11 )
b11 0
b0 &
b1001 $
b1001 '
b1001 -
b10111 +
b10111 ,
b10111 /
#146
b1001 !
b1001 )
b1001 0
b0 "
b0 *
b0 1
b1 &
b0 %
b0 (
b0 .
b1001 +
b1001 ,
b1001 /
#147
b0 !
b0 )
b0 0
b1 "
b1 *
b1 1
b10 &
b1 %
b1 (
b1 .
b1010 +
b1010 ,
b1010 /
#148
b1 !
b1 )
b1 0
b11 &
b10 %
b10 (
b10 .
b1011 +
b1011 ,
b1011 /
#149
b10 !
b10 )
b10 0
b100 &
b11 %
b11 (
b11 .
b1100 +
b1100 ,
b1100 /
#150
b11 !
b11 )
b11 0
b101 &
b100 %
b100 (
b100 .
b1101 +
b1101 ,
b1101 /
#151
b100 !
b100 )
b100 0
b110 &
b101 %
b101 (
b101 .
b1110 +
b1110 ,
b1110 /
#152
b101 !
b101 )
b101 0
b111 &
b110 %
b110 (
b110 .
b1111 +
b1111 ,
b1111 /
#153
b110 !
b110 )
b110 0
b1000 &
b111 %
b111 (
b111 .
b10000 +
b10000 ,
b10000 /
#154
b111 !
b111 )
b111 0
b1001 &
b1000 %
b1000 (
b1000 .
b10001 +
b10001 ,
b10001 /
#155
b1000 !
b1000 )
b1000 0
b1010 &
b1001 %
b1001 (
b1001 .
b10010 +
b10010 ,
b10010 /
#156
b1001 !
b1001 )
b1001 0
b1011 &
b1010 %
b1010 (
b1010 .
b10011 +
b10011 ,
b10011 /
#157
b0 !
b0 )
b0 0
b10 "
b10 *
b10 1
b1100 &
b1011 %
b1011 (
b1011 .
b10100 +
b10100 ,
b10100 /
#158
b1 !
b1 )
b1 0
b1101 &
b1100 %
b1100 (
b1100 .
b10101 +
b10101 ,
b10101 /
#159
b10 !
b10 )
b10 0
b1110 &
b1101 %
b1101 (
b1101 .
b10110 +
b10110 ,
b10110 /
#160
b11 !
b11 )
b11 0
b1010 #
b1111 &
b1110 %
b1110 (
b1110 .
b10111 +
b10111 ,
b10111 /
#161
b100 !
b100 )
b100 0
b0 &
b1010 $
b1010 '
b1010 -
b11000 +
b11000 ,
b11000 /
#162
b0 !
b0 )
b0 0
b1 "
b1 *
b1 1
b1 &
b0 %
b0 (
b0 .
b1010 +
b1010 ,
b1010 /
#163
b1 !
b1 )
b1 0
b10 &
b1 %
b1 (
b1 .
b1011 +
b1011 ,
b1011 /
#164
b10 !
b10 )
b10 0
b11 &
b10 %
b10 (
b10 .
b1100 +
b1100 ,
b1100 /
#165
b11 !
b11 )
b11 0
b100 &
b11 %
b11 (
b11 .
b1101 +
b1101 ,
b1101 /
#166
b100 !
b100 )
b100 0
b101 &
b100 %
b100 (
b100 .
b1110 +
b1110 ,
b1110 /
#167
b101 !
b101 )
b101 0
b110 &
b101 %
b101 (
b101 .
b1111 +
b1111 ,
b1111 /
#168
b110 !
b110 )
b110 0
b111 &
b110 %
b110 (
b110 .
b10000 +
b10000 ,
b10000 /
#169
b111 !
b111 )
b111 0
b1000 &
b111 %
b111 (
b111 .
b10001 +
b10001 ,
b10001 /
#170
b1000 !
b1000 )
b1000 0
b1001 &
b1000 %
b1000 (
b1000 .
b10010 +
b10010 ,
b10010 /
#171
b1001 !
b1001 )
b1001 0
b1010 &
b1001 %
b1001 (
b1001 .
b10011 +
b10011 ,
b10011 /
#172
b0 !
b0 )
b0 0
b10 "
b10 *
b10 1
b1011 &
b1010 %
b1010 (
b1010 .
b10100 +
b10100 ,
b10100 /
#173
b1 !
b1 )
b1 0
b1100 &
b1011 %
b1011 (
b1011 .
b10101 +
b10101 ,
b10101 /
#174
b10 !
b10 )
b10 0
b1101 &
b1100 %
b1100 (
b1100 .
b10110 +
b10110 ,
b10110 /
#175
b11 !
b11 )
b11 0
b1110 &
b1101 %
b1101 (
b1101 .
b10111 +
b10111 ,
b10111 /
#176
b100 !
b100 )
b100 0
b1011 #
b1111 &
b1110 %
b1110 (
b1110 .
b11000 +
b11000 ,
b11000 /
#177
b101 !
b101 )
b101 0
b0 &
b1011 $
b1011 '
b1011 -
b11001 +
b11001 ,
b11001 /
#178
b1 !
b1 )
b1 0
b1 "
b1 *
b1 1
b1 &
b0 %
b0 (
b0 .
b1011 +
b1011 ,
b1011 /
#179
b10 !
b10 )
b10 0
b10 &
b1 %
b1 (
b1 .
b1100 +
b1100 ,
b1100 /
#180
b11 !
b11 )
b11 0
b11 &
b10 %
b10 (
b10 .
b1101 +
b1101 ,
b1101 /
#181
b100 !
b100 )
b100 0
b100 &
b11 %
b11 (
b11 .
b1110 +
b1110 ,
b1110 /
#182
b101 !
b101 )
b101 0
b101 &
b100 %
b100 (
b100 .
b1111 +
b1111 ,
b1111 /
#183
b110 !
b110 )
b110 0
b110 &
b101 %
b101 (
b101 .
b10000 +
b10000 ,
b10000 /
#184
b111 !
b111 )
b111 0
b111 &
b110 %
b110 (
b110 .
b10001 +
b10001 ,
b10001 /
#185
b1000 !
b1000 )
b1000 0
b1000 &
b111 %
b111 (
b111 .
b10010 +
b10010 ,
b10010 /
#186
b1001 !
b1001 )
b1001 0
b1001 &
b1000 %
b1000 (
b1000 .
b10011 +
b10011 ,
b10011 /
#187
b0 !
b0 )
b0 0
b10 "
b10 *
b10 1
b1010 &
b1001 %
b1001 (
b1001 .
b10100 +
b10100 ,
b10100 /
#188
b1 !
b1 )
b1 0
b1011 &
b1010 %
b1010 (
b1010 .
b10101 +
b10101 ,
b10101 /
#189
b10 !
b10 )
b10 0
b1100 &
b1011 %
b1011 (
b1011 .
b10110 +
b10110 ,
b10110 /
#190
b11 !
b11 )
b11 0
b1101 &
b1100 %
b1100 (
b1100 .
b10111 +
b10111 ,
b10111 /
#191
b100 !
b100 )
b100 0
b1110 &
b1101 %
b1101 (
b1101 .
b11000 +
b11000 ,
b11000 /
#192
b101 !
b101 )
b101 0
b1100 #
b1111 &
b1110 %
b1110 (
b1110 .
b11001 +
b11001 ,
b11001 /
#193
b110 !
b110 )
b110 0
b0 &
b1100 $
b1100 '
b1100 -
b11010 +
b11010 ,
b11010 /
#194
b10 !
b10 )
b10 0
b1 "
b1 *
b1 1
b1 &
b0 %
b0 (
b0 .
b1100 +
b1100 ,
b1100 /
#195
b11 !
b11 )
b11 0
b10 &
b1 %
b1 (
b1 .
b1101 +
b1101 ,
b1101 /
#196
b100 !
b100 )
b100 0
b11 &
b10 %
b10 (
b10 .
b1110 +
b1110 ,
b1110 /
#197
b101 !
b101 )
b101 0
b100 &
b11 %
b11 (
b11 .
b1111 +
b1111 ,
b1111 /
#198
b110 !
b110 )
b110 0
b101 &
b100 %
b100 (
b100 .
b10000 +
b10000 ,
b10000 /
#199
b111 !
b111 )
b111 0
b110 &
b101 %
b101 (
b101 .
b10001 +
b10001 ,
b10001 /
#200
b1000 !
b1000 )
b1000 0
b111 &
b110 %
b110 (
b110 .
b10010 +
b10010 ,
b10010 /
#201
b1001 !
b1001 )
b1001 0
b1000 &
b111 %
b111 (
b111 .
b10011 +
b10011 ,
b10011 /
#202
b0 !
b0 )
b0 0
b10 "
b10 *
b10 1
b1001 &
b1000 %
b1000 (
b1000 .
b10100 +
b10100 ,
b10100 /
#203
b1 !
b1 )
b1 0
b1010 &
b1001 %
b1001 (
b1001 .
b10101 +
b10101 ,
b10101 /
#204
b10 !
b10 )
b10 0
b1011 &
b1010 %
b1010 (
b1010 .
b10110 +
b10110 ,
b10110 /
#205
b11 !
b11 )
b11 0
b1100 &
b1011 %
b1011 (
b1011 .
b10111 +
b10111 ,
b10111 /
#206
b100 !
b100 )
b100 0
b1101 &
b1100 %
b1100 (
b1100 .
b11000 +
b11000 ,
b11000 /
#207
b101 !
b101 )
b101 0
b1110 &
b1101 %
b1101 (
b1101 .
b11001 +
b11001 ,
b11001 /
#208
b110 !
b110 )
b110 0
b1101 #
b1111 &
b1110 %
b1110 (
b1110 .
b11010 +
b11010 ,
b11010 /
#209
b111 !
b111 )
b111 0
b0 &
b1101 $
b1101 '
b1101 -
b11011 +
b11011 ,
b11011 /
#210
b11 !
b11 )
b11 0
b1 "
b1 *
b1 1
b1 &
b0 %
b0 (
b0 .
b1101 +
b1101 ,
b1101 /
#211
b100 !
b100 )
b100 0
b10 &
b1 %
b1 (
b1 .
b1110 +
b1110 ,
b1110 /
#212
b101 !
b101 )
b101 0
b11 &
b10 %
b10 (
b10 .
b1111 +
b1111 ,
b1111 /
#213
b110 !
b110 )
b110 0
b100 &
b11 %
b11 (
b11 .
b10000 +
b10000 ,
b10000 /
#214
b111 !
b111 )
b111 0
b101 &
b100 %
b100 (
b100 .
b10001 +
b10001 ,
b10001 /
#215
b1000 !
b1000 )
b1000 0
b110 &
b101 %
b101 (
b101 .
b10010 +
b10010 ,
b10010 /
#216
b1001 !
b1001 )
b1001 0
b111 &
b110 %
b110 (
b110 .
b10011 +
b10011 ,
b10011 /
#217
b0 !
b0 )
b0 0
b10 "
b10 *
b10 1
b1000 &
b111 %
b111 (
b111 .
b10100 +
b10100 ,
b10100 /
