E5TP1/decoderBCD.v
//This BCD Decoder supports numbers of up to 5-bits
//I'm not sure if Decoder is the proper name

module decoderBCD (
  in,   //5-bit Input Value
  out0, //4-bit Output BCD Digit 0
  out1  //4-bit Output BCD Digit 1
);

//Input Declaration
input [4:0] in;

//Output Declaration
output [3:0] out0;
output [3:0] out1;

//Resources Definition
wire [4:0] in;
reg [3:0] out0;
reg [3:0] out1;

initial begin
  out0 = 0;
  out1 = 0;
end

always @(in) begin
out1 = in/10;
out0 = in%10;
end

endmodule

E5TP1/sum4bit.v
module sum4bit(
    x0, //Sumando 0 (4-bit)
    x1, //Sumando 1 (4-bit)
    o   //Resultado (5-bit)
);

input wire [3:0] x0, x1;
output reg [4:0] o;

initial begin
  o = 0;
end

always @(x0 or x1) begin
  o = x0 + x1;
end


endmodule

E5TP1/filterBCD.v
module filterBCD
(
    in,     //Entrada de datos
    out,    //Salida de datos
    error   //Flag de error o invalido
);

input [3:0] in;

output[3:0] out;
output error;

wire [3:0] in;
reg [3:0] out;
reg error;

initial begin
  error = 0;
  out = 0;
end

always @ (in) begin
  if (in>9) begin
    error = 1;
    out = 0;
  end
  else begin
    error = 0;
    out = in;
  end
end



endmodule

E5TP1/adderBCD.v
`include "decoderBCD.v"
`include "sum4bit.v"
`include "filterBCD.v"

module adderBCD(
    in0,    //BCD Input 0
    in1,    //BCD Input 1
    out0,   //BCD Output 0
    out1,   //BCD Output 1
    flag
);

//Defining Inputs
input [3:0] in0; //BCD Input 0
input [3:0] in1; //BCD Input 1

//Defining Outputs
output [3:0] out0;  //BCD Output digit 0
output [3:0] out1;  //BCD Output digit 1
output flag;

//Defining data types
wire [3:0] in0, in1;
wire [4:0] sum;
wire [3:0] out0,out1;
wire [3:0] f0, f1;
wire e0, e1;

//Declaring included modules
filterBCD filter0(.in(in0), .out(f0), .error(e0));
filterBCD filter1(.in(in1), .out(f1), .error(e1));
sum4bit adder(.x0(f0),.x1(f1),.o(sum));
decoderBCD decoder (.in(sum),.out0(out0),.out1(out1));

assign flag = e0 || e1;

//Code
/*
Get whatever is going to do the sum of the 2 4-bit numbers here
*/

endmodule

E5TP1/src/adderBCD/adderBCD_tb.v
`include "src/adderBCD/adderBCD.v"

module adderBCD_tb;

//Test Data Types
reg [3:0] in0, in1;
wire [3:0] out0, out1;
wire flag;

//Test Indexes
reg [4:0] i,j;

//Connecting the ports adderBCD
adderBCD adder_udt(
  .in0(in0),
  .in1(in1),
  .out0(out0),
  .out1(out1),
  .flag(flag)
  );

//Code
initial begin
  $dumpfile( "adderBCD.vcd");
  $dumpvars;
end

initial begin
  in0 = 0;
  in1 = 0;
  $display("In1\tIn0\t\tOut\t\tError");
  $monitor("%d\t%d\t\t%d,%d\t%b", in1, in0, out1, out0, flag);
end

always begin
for (i = 0; i<16 ; i = i+1) begin
    for (j=0; j<16; j = j+1) begin
      in1 = i[3:0];
      in0 = j[3:0];
      #1;
    end
end
#20$finish;
end

endmodule

E5TP1/adderBCD.vcd
$date
	Mon Sep  3 22:06:04 2018
$end
$version
	Icarus Verilog
$end
$timescale
	1s
$end
$scope module adderBCD_tb $end
$var wire 1 ! flag $end
$var wire 4 " out0 [3:0] $end
$var wire 4 # out1 [3:0] $end
$var reg 5 $ i [4:0] $end
$var reg 4 % in0 [3:0] $end
$var reg 4 & in1 [3:0] $end
$var reg 5 ' j [4:0] $end
$scope module adder_udt $end
$var wire 1 ( e0 $end
$var wire 1 ) e1 $end
$var wire 4 * f0 [3:0] $end
$var wire 4 + f1 [3:0] $end
$var wire 1 ! flag $end
$var wire 4 , in0 [3:0] $end
$var wire 4 - in1 [3:0] $end
$var wire 4 . out0 [3:0] $end
$var wire 4 / out1 [3:0] $end
$var wire 5 0 sum [4:0] $end
$scope module filter0 $end
$var wire 4 1 in [3:0] $end
$var reg 1 2 error $end
$var reg 4 3 out [3:0] $end
$upscope $end
$scope module filter1 $end
$var wire 4 4 in [3:0] $end
$var reg 1 5 error $end
$var reg 4 6 out [3:0] $end
$upscope $end
$scope module adder $end
$var wire 5 7 o [4:0] $end
$var wire 4 8 x0 [3:0] $end
$var wire 4 9 x1 [3:0] $end
$upscope $end
$scope module decoder $end
$var wire 5 : in [4:0] $end
$var wire 4 ; out0 [3:0] $end
$var wire 4 < out1 [3:0] $end
$upscope $end
$upscope $end
$upscope $end
$enddefinitions $end
#0
$dumpvars
b0 <
b0 ;
b0 :
b0 9
b0 8
b0 7
b0 6
05
b0 4
b0 3
02
b0 1
b0 0
b0 /
b0 .
b0 -
b0 ,
b0 +
b0 *
0)
0(
b0 '
b0 &
b0 %
b0 $
b0 #
b0 "
0!
$end
#1
b1 "
b1 .
b1 ;
b1 %
b1 ,
b1 1
b1 3
b1 0
b1 7
b1 :
b1 *
b1 8
b1 '
#2
b10 "
b10 .
b10 ;
b10 %
b10 ,
b10 1
b10 3
b10 0
b10 7
b10 :
b10 *
b10 8
b10 '
#3
b11 "
b11 .
b11 ;
b11 %
b11 ,
b11 1
b11 3
b11 0
b11 7
b11 :
b11 *
b11 8
b11 '
#4
b100 "
b100 .
b100 ;
b100 %
b100 ,
b100 1
b100 3
b100 0
b100 7
b100 :
b100 *
b100 8
b100 '
#5
b101 "
b101 .
b101 ;
b101 %
b101 ,
b101 1
b101 3
b101 0
b101 7
b101 :
b101 *
b101 8
b101 '
#6
b110 "
b110 .
b110 ;
b110 %
b110 ,
b110 1
b110 3
b110 0
b110 7
b110 :
b110 *
b110 8
b110 '
#7
b111 "
b111 .
b111 ;
b111 %
b111 ,
b111 1
b111 3
b111 0
b111 7
b111 :
b111 *
b111 8
b111 '
#8
b1000 "
b1000 .
b1000 ;
b1000 %
b1000 ,
b1000 1
b1000 3
b1000 0
b1000 7
b1000 :
b1000 *
b1000 8
b1000 '
#9
b1001 "
b1001 .
b1001 ;
b1001 %
b1001 ,
b1001 1
b1001 3
b1001 0
b1001 7
b1001 :
b1001 *
b1001 8
b1001 '
#10
1!
12
1(
b0 "
b0 .
b0 ;
b1 #
b1 /
b1 <
b1010 %
b1010 ,
b1010 1
b1010 3
b1010 0
b1010 7
b1010 :
b1010 *
b1010 8
b1010 '
#11
b1 "
b1 .
b1 ;
b1011 %
b1011 ,
b1011 1
b1011 3
b1011 0
b1011 7
b1011 :
b1011 *
b1011 8
b1011 '
#12
b10 "
b10 .
b10 ;
b1100 %
b1100 ,
b1100 1
b1100 3
b1100 0
b1100 7
b1100 :
b1100 *
b1100 8
b1100 '
#13
b11 "
b11 .
b11 ;
b1101 %
b1101 ,
b1101 1
b1101 3
b1101 0
b1101 7
b1101 :
b1101 *
b1101 8
b1101 '
#14
b100 "
b100 .
b100 ;
b1110 %
b1110 ,
b1110 1
b1110 3
b1110 0
b1110 7
b1110 :
b1110 *
b1110 8
b1110 '
#15
b101 "
b101 .
b101 ;
b1111 %
b1111 ,
b1111 1
b1111 3
b1111 0
b1111 7
b1111 :
b1111 *
b1111 8
b1111 '
#16
0!
02
0(
b0 #
b0 /
b0 <
b1 "
b1 .
b1 ;
b0 %
b0 ,
b0 1
b0 3
b0 *
b0 8
b1 &
b1 -
b1 4
b1 6
b1 0
b1 7
b1 :
b1 +
b1 9
b1 $
b0 '
#17
b10 "
b10 .
b10 ;
b1 %
b1 ,
b1 1
b1 3
b10 0
b10 7
b10 :
b1 *
b1 8
b1 '
#18
b11 "
b11 .
b11 ;
b10 %
b10 ,
b10 1
b10 3
b11 0
b11 7
b11 :
b10 *
b10 8
b10 '
#19
b100 "
b100 .
b100 ;
b11 %
b11 ,
b11 1
b11 3
b100 0
b100 7
b100 :
b11 *
b11 8
b11 '
#20
b101 "
b101 .
b101 ;
b100 %
b100 ,
b100 1
b100 3
b101 0
b101 7
b101 :
b100 *
b100 8
b100 '
#21
b110 "
b110 .
b110 ;
b101 %
b101 ,
b101 1
b101 3
b110 0
b110 7
b110 :
b101 *
b101 8
b101 '
#22
b111 "
b111 .
b111 ;
b110 %
b110 ,
b110 1
b110 3
b111 0
b111 7
b111 :
b110 *
b110 8
b110 '
#23
b1000 "
b1000 .
b1000 ;
b111 %
b111 ,
b111 1
b111 3
b1000 0
b1000 7
b1000 :
b111 *
b111 8
b111 '
#24
b1001 "
b1001 .
b1001 ;
b1000 %
b1000 ,
b1000 1
b1000 3
b1001 0
b1001 7
b1001 :
b1000 *
b1000 8
b1000 '
#25
b0 "
b0 .
b0 ;
b1 #
b1 /
b1 <
b1001 %
b1001 ,
b1001 1
b1001 3
b1010 0
b1010 7
b1010 :
b1001 *
b1001 8
b1001 '
#26
1!
12
1(
b1 "
b1 .
b1 ;
b1010 %
b1010 ,
b1010 1
b1010 3
b1011 0
b1011 7
b1011 :
b1010 *
b1010 8
b1010 '
#27
b10 "
b10 .
b10 ;
b1011 %
b1011 ,
b1011 1
b1011 3
b1100 0
b1100 7
b1100 :
b1011 *
b1011 8
b1011 '
#28
b11 "
b11 .
b11 ;
b1100 %
b1100 ,
b1100 1
b1100 3
b1101 0
b1101 7
b1101 :
b1100 *
b1100 8
b1100 '
#29
b100 "
b100 .
b100 ;
b1101 %
b1101 ,
b1101 1
b1101 3
b1110 0
b1110 7
b1110 :
b1101 *
b1101 8
b1101 '
#30
b101 "
b101 .
b101 ;
b1110 %
b1110 ,
b1110 1
b1110 3
b1111 0
b1111 7
b1111 :
b1110 *
b1110 8
b1110 '
#31
b110 "
b110 .
b110 ;
b1111 %
b1111 ,
b1111 1
b1111 3
b10000 0
b10000 7
b10000 :
b1111 *
b1111 8
b1111 '
#32
0!
02
0(
b0 #
b0 /
b0 <
b10 "
b10 .
b10 ;
b0 %
b0 ,
b0 1
b0 3
b0 *
b0 8
b10 &
b10 -
b10 4
b10 6
b10 0
b10 7
b10 :
b10 +
b10 9
b10 $
b0 '
#33
b11 "
b11 .
b11 ;
b1 %
b1 ,
b1 1
b1 3
b11 0
b11 7
b11 :
b1 *
b1 8
b1 '
#34
b100 "
b100 .
b100 ;
b10 %
b10 ,
b10 1
b10 3
b100 0
b100 7
b100 :
b10 *
b10 8
b10 '
#35
b101 "
b101 .
b101 ;
b11 %
b11 ,
b11 1
b11 3
b101 0
b101 7
b101 :
b11 *
b11 8
b11 '
#36
b110 "
b110 .
b110 ;
b100 %
b100 ,
b100 1
b100 3
b110 0
b110 7
b110 :
b100 *
b100 8
b100 '
#37
b111 "
b111 .
b111 ;
b101 %
b101 ,
b101 1
b101 3
b111 0
b111 7
b111 :
b101 *
b101 8
b101 '
#38
b1000 "
b1000 .
b1000 ;
b110 %
b110 ,
b110 1
b110 3
b1000 0
b1000 7
b1000 :
b110 *
b110 8
b110 '
#39
b1001 "
b1001 .
b1001 ;
b111 %
b111 ,
b111 1
b111 3
b1001 0
b1001 7
b1001 :
b111 *
b111 8
b111 '
#40
b0 "
b0 .
b0 ;
b1 #
b1 /
b1 <
b1000 %
b1000 ,
b1000 1
b1000 3
b1010 0
b1010 7
b1010 :
b1000 *
b1000 8
b1000 '
#41
b1 "
b1 .
b1 ;
b1001 %
b1001 ,
b1001 1
b1001 3
b1011 0
b1011 7
b1011 :
b1001 *
b1001 8
b1001 '
#42
1!
12
1(
b10 "
b10 .
b10 ;
b1010 %
b1010 ,
b1010 1
b1010 3
b1100 0
b1100 7
b1100 :
b1010 *
b1010 8
b1010 '
#43
b11 "
b11 .
b11 ;
b1011 %
b1011 ,
b1011 1
b1011 3
b1101 0
b1101 7
b1101 :
b1011 *
b1011 8
b1011 '
#44
b100 "
b100 .
b100 ;
b1100 %
b1100 ,
b1100 1
b1100 3
b1110 0
b1110 7
b1110 :
b1100 *
b1100 8
b1100 '
#45
b101 "
b101 .
b101 ;
b1101 %
b1101 ,
b1101 1
b1101 3
b1111 0
b1111 7
b1111 :
b1101 *
b1101 8
b1101 '
#46
b110 "
b110 .
b110 ;
b1110 %
b1110 ,
b1110 1
b1110 3
b10000 0
b10000 7
b10000 :
b1110 *
b1110 8
b1110 '
#47
b111 "
b111 .
b111 ;
b1111 %
b1111 ,
b1111 1
b1111 3
b10001 0
b10001 7
b10001 :
b1111 *
b1111 8
b1111 '
#48
0!
02
0(
b0 #
b0 /
b0 <
b11 "
b11 .
b11 ;
b0 %
b0 ,
b0 1
b0 3
b0 *
b0 8
b11 &
b11 -
b11 4
b11 6
b11 0
b11 7
b11 :
b11 +
b11 9
b11 $
b0 '
#49
b100 "
b100 .
b100 ;
b1 %
b1 ,
b1 1
b1 3
b100 0
b100 7
b100 :
b1 *
b1 8
b1 '
#50
b101 "
b101 .
b101 ;
b10 %
b10 ,
b10 1
b10 3
b101 0
b101 7
b101 :
b10 *
b10 8
b10 '
#51
b110 "
b110 .
b110 ;
b11 %
b11 ,
b11 1
b11 3
b110 0
b110 7
b110 :
b11 *
b11 8
b11 '
#52
b111 "
b111 .
b111 ;
b100 %
b100 ,
b100 1
b100 3
b111 0
b111 7
b111 :
b100 *
b100 8
b100 '
#53
b1000 "
b1000 .
b1000 ;
b101 %
b101 ,
b101 1
b101 3
b1000 0
b1000 7
b1000 :
b101 *
b101 8
b101 '
#54
b1001 "
b1001 .
b1001 ;
b110 %
b110 ,
b110 1
b110 3
b1001 0
b1001 7
b1001 :
b110 *
b110 8
b110 '
#55
b0 "
b0 .
b0 ;
b1 #
b1 /
b1 <
b111 %
b111 ,
b111 1
b111 3
b1010 0
b1010 7
b1010 :
b111 *
b111 8
b111 '
#56
b1 "
b1 .
b1 ;
b1000 %
b1000 ,
b1000 1
b1000 3
b1011 0
b1011 7
b1011 :
b1000 *
b1000 8
b1000 '
#57
b10 "
b10 .
b10 ;
b1001 %
b1001 ,
b1001 1
b1001 3
b1100 0
b1100 7
b1100 :
b1001 *
b1001 8
b1001 '
#58
1!
12
1(
b11 "
b11 .
b11 ;
b1010 %
b1010 ,
b1010 1
b1010 3
b1101 0
b1101 7
b1101 :
b1010 *
b1010 8
b1010 '
#59
b100 "
b100 .
b100 ;
b1011 %
b1011 ,
b1011 1
b1011 3
b1110 0
b1110 7
b1110 :
b1011 *
b1011 8
b1011 '
#60
b101 "
b101 .
b101 ;
b1100 %
b1100 ,
b1100 1
b1100 3
b1111 0
b1111 7
b1111 :
b1100 *
b1100 8
b1100 '
#61
b110 "
b110 .
b110 ;
b1101 %
b1101 ,
b1101 1
b1101 3
b10000 0
b10000 7
b10000 :
b1101 *
b1101 8
b1101 '
#62
b111 "
b111 .
b111 ;
b1110 %
b1110 ,
b1110 1
b1110 3
b10001 0
b10001 7
b10001 :
b1110 *
b1110 8
b1110 '
#63
b1000 "
b1000 .
b1000 ;
b1111 %
b1111 ,
b1111 1
b1111 3
b10010 0
b10010 7
b10010 :
b1111 *
b1111 8
b1111 '
#64
0!
02
0(
b0 #
b0 /
b0 <
b100 "
b100 .
b100 ;
b0 %
b0 ,
b0 1
b0 3
b0 *
b0 8
b100 &
b100 -
b100 4
b100 6
b100 0
b100 7
b100 :
b100 +
b100 9
b100 $
b0 '
#65
b101 "
b101 .
b101 ;
b1 %
b1 ,
b1 1
b1 3
b101 0
b101 7
b101 :
b1 *
b1 8
b1 '
#66
b110 "
b110 .
b110 ;
b10 %
b10 ,
b10 1
b10 3
b110 0
b110 7
b110 :
b10 *
b10 8
b10 '
#67
b111 "
b111 .
b111 ;
b11 %
b11 ,
b11 1
b11 3
b111 0
b111 7
b111 :
b11 *
b11 8
b11 '
#68
b1000 "
b1000 .
b1000 ;
b100 %
b100 ,
b100 1
b100 3
b1000 0
b1000 7
b1000 :
b100 *
b100 8
b100 '
#69
b1001 "
b1001 .
b1001 ;
b101 %
b101 ,
b101 1
b101 3
b1001 0
b1001 7
b1001 :
b101 *
b101 8
b101 '
#70
b0 "
b0 .
b0 ;
b1 #
b1 /
b1 <
b110 %
b110 ,
b110 1
b110 3
b1010 0
b1010 7
b1010 :
b110 *
b110 8
b110 '
#71
b1 "
b1 .
b1 ;
b111 %
b111 ,
b111 1
b111 3
b1011 0
b1011 7
b1011 :
b111 *
b111 8
b111 '
#72
b10 "
b10 .
b10 ;
b1000 %
b1000 ,
b1000 1
b1000 3
b1100 0
b1100 7
b1100 :
b1000 *
b1000 8
b1000 '
#73
b11 "
b11 .
b11 ;
b1001 %
b1001 ,
b1001 1
b1001 3
b1101 0
b1101 7
b1101 :
b1001 *
b1001 8
b1001 '
#74
1!
12
1(
b100 "
b100 .
b100 ;
b1010 %
b1010 ,
b1010 1
b1010 3
b1110 0
b1110 7
b1110 :
b1010 *
b1010 8
b1010 '
#75
b101 "
b101 .
b101 ;
b1011 %
b1011 ,
b1011 1
b1011 3
b1111 0
b1111 7
b1111 :
b1011 *
b1011 8
b1011 '
#76
b110 "
b110 .
b110 ;
b1100 %
b1100 ,
b1100 1
b1100 3
b10000 0
b10000 7
b10000 :
b1100 *
b1100 8
b1100 '
#77
b111 "
b111 .
b111 ;
b1101 %
b1101 ,
b1101 1
b1101 3
b10001 0
b10001 7
b10001 :
b1101 *
b1101 8
b1101 '
#78
b1000 "
b1000 .
b1000 ;
b1110 %
b1110 ,
b1110 1
b1110 3
b10010 0
b10010 7
b10010 :
b1110 *
b1110 8
b1110 '
#79
b1001 "
b1001 .
b1001 ;
b1111 %
b1111 ,
b1111 1
b1111 3
b10011 0
b10011 7
b10011 :
b1111 *
b1111 8
b1111 '
#80
0!
02
0(
b101 "
b101 .
b101 ;
b0 #
b0 /
b0 <
b0 %
b0 ,
b0 1
b0 3
b0 *
b0 8
b101 &
b101 -
b101 4
b101 6
b101 0
b101 7
b101 :
b101 +
b101 9
b101 $
b0 '
#81
b110 "
b110 .
b110 ;
b1 %
b1 ,
b1 1
b1 3
b110 0
b110 7
b110 :
b1 *
b1 8
b1 '
#82
b111 "
b111 .
b111 ;
b10 %
b10 ,
b10 1
b10 3
b111 0
b111 7
b111 :
b10 *
b10 8
b10 '
#83
b1000 "
b1000 .
b1000 ;
b11 %
b11 ,
b11 1
b11 3
b1000 0
b1000 7
b1000 :
b11 *
b11 8
b11 '
#84
b1001 "
b1001 .
b1001 ;
b100 %
b100 ,
b100 1
b100 3
b1001 0
b1001 7
b1001 :
b100 *
b100 8
b100 '
#85
b0 "
b0 .
b0 ;
b1 #
b1 /
b1 <
b101 %
b101 ,
b101 1
b101 3
b1010 0
b1010 7
b1010 :
b101 *
b101 8
b101 '
#86
b1 "
b1 .
b1 ;
b110 %
b110 ,
b110 1
b110 3
b1011 0
b1011 7
b1011 :
b110 *
b110 8
b110 '
#87
b10 "
b10 .
b10 ;
b111 %
b111 ,
b111 1
b111 3
b1100 0
b1100 7
b1100 :
b111 *
b111 8
b111 '
#88
b11 "
b11 .
b11 ;
b1000 %
b1000 ,
b1000 1
b1000 3
b1101 0
b1101 7
b1101 :
b1000 *
b1000 8
b1000 '
#89
b100 "
b100 .
b100 ;
b1001 %
b1001 ,
b1001 1
b1001 3
b1110 0
b1110 7
b1110 :
b1001 *
b1001 8
b1001 '
#90
1!
12
1(
b101 "
b101 .
b101 ;
b1010 %
b1010 ,
b1010 1
b1010 3
b1111 0
b1111 7
b1111 :
b1010 *
b1010 8
b1010 '
#91
b110 "
b110 .
b110 ;
b1011 %
b1011 ,
b1011 1
b1011 3
b10000 0
b10000 7
b10000 :
b1011 *
b1011 8
b1011 '
#92
b111 "
b111 .
b111 ;
b1100 %
b1100 ,
b1100 1
b1100 3
b10001 0
b10001 7
b10001 :
b1100 *
b1100 8
b1100 '
#93
b1000 "
b1000 .
b1000 ;
b1101 %
b1101 ,
b1101 1
b1101 3
b10010 0
b10010 7
b10010 :
b1101 *
b1101 8
b1101 '
#94
b1001 "
b1001 .
b1001 ;
b1110 %
b1110 ,
b1110 1
b1110 3
b10011 0
b10011 7
b10011 :
b1110 *
b1110 8
b1110 '
#95
b0 "
b0 .
b0 ;
b10 #
b10 /
b10 <
b1111 %
b1111 ,
b1111 1
b1111 3
b10100 0
b10100 7
b10100 :
b1111 *
b1111 8
b1111 '
#96
0!
02
0(
b0 #
b0 /
b0 <
b110 "
b110 .
b110 ;
b0 %
b0 ,
b0 1
b0 3
b0 *
b0 8
b110 &
b110 -
b110 4
b110 6
b110 0
b110 7
b110 :
b110 +
b110 9
b110 $
b0 '
#97
b111 "
b111 .
b111 ;
b1 %
b1 ,
b1 1
b1 3
b111 0
b111 7
b111 :
b1 *
b1 8
b1 '
#98
b1000 "
b1000 .
b1000 ;
b10 %
b10 ,
b10 1
b10 3
b1000 0
b1000 7
b1000 :
b10 *
b10 8
b10 '
#99
b1001 "
b1001 .
b1001 ;
b11 %
b11 ,
b11 1
b11 3
b1001 0
b1001 7
b1001 :
b11 *
b11 8
b11 '
#100
b0 "
b0 .
b0 ;
b1 #
b1 /
b1 <
b100 %
b100 ,
b100 1
b100 3
b1010 0
b1010 7
b1010 :
b100 *
b100 8
b100 '
#101
b1 "
b1 .
b1 ;
b101 %
b101 ,
b101 1
b101 3
b1011 0
b1011 7
b1011 :
b101 *
b101 8
b101 '
#102
b10 "
b10 .
b10 ;
b110 %
b110 ,
b110 1
b110 3
b1100 0
b1100 7
b1100 :
b110 *
b110 8
b110 '
#103
b11 "
b11 .
b11 ;
b111 %
b111 ,
b111 1
b111 3
b1101 0
b1101 7
b1101 :
b111 *
b111 8
b111 '
#104
b100 "
b100 .
b100 ;
b1000 %
b1000 ,
b1000 1
b1000 3
b1110 0
b1110 7
b1110 :
b1000 *
b1000 8
b1000 '
#105
b101 "
b101 .
b101 ;
b1001 %
b1001 ,
b1001 1
b1001 3
b1111 0
b1111 7
b1111 :
b1001 *
b1001 8
b1001 '
#106
1!
12
1(
b110 "
b110 .
b110 ;
b1010 %
b1010 ,
b1010 1
b1010 3
b10000 0
b10000 7
b10000 :
b1010 *
b1010 8
b1010 '
#107
b111 "
b111 .
b111 ;
b1011 %
b1011 ,
b1011 1
b1011 3
b10001 0
b10001 7
b10001 :
b1011 *
b1011 8
b1011 '
#108
b1000 "
b1000 .
b1000 ;
b1100 %
b1100 ,
b1100 1
b1100 3
b10010 0
b10010 7
b10010 :
b1100 *
b1100 8
b1100 '
#109
b1001 "
b1001 .
b1001 ;
b1101 %
b1101 ,
b1101 1
b1101 3
b10011 0
b10011 7
b10011 :
b1101 *
b1101 8
b1101 '
#110
b0 "
b0 .
b0 ;
b10 #
b10 /
b10 <
b1110 %
b1110 ,
b1110 1
b1110 3
b10100 0
b10100 7
b10100 :
b1110 *
b1110 8
b1110 '
#111
b1 "
b1 .
b1 ;
b1111 %
b1111 ,
b1111 1
b1111 3
b10101 0
b10101 7
b10101 :
b1111 *
b1111 8
b1111 '
#112
0!
02
0(
b0 #
b0 /
b0 <
b111 "
b111 .
b111 ;
b0 %
b0 ,
b0 1
b0 3
b0 *
b0 8
b111 &
b111 -
b111 4
b111 6
b111 0
b111 7
b111 :
b111 +
b111 9
b111 $
b0 '
#113
b1000 "
b1000 .
b1000 ;
b1 %
b1 ,
b1 1
b1 3
b1000 0
b1000 7
b1000 :
b1 *
b1 8
b1 '
#114
b1001 "
b1001 .
b1001 ;
b10 %
b10 ,
b10 1
b10 3
b1001 0
b1001 7
b1001 :
b10 *
b10 8
b10 '
#115
b0 "
b0 .
b0 ;
b1 #
b1 /
b1 <
b11 %
b11 ,
b11 1
b11 3
b1010 0
b1010 7
b1010 :
b11 *
b11 8
b11 '
#116
b1 "
b1 .
b1 ;
b100 %
b100 ,
b100 1
b100 3
b1011 0
b1011 7
b1011 :
b100 *
b100 8
b100 '
#117
b10 "
b10 .
b10 ;
b101 %
b101 ,
b101 1
b101 3
b1100 0
b1100 7
b1100 :
b101 *
b101 8
b101 '
#118
b11 "
b11 .
b11 ;
b110 %
b110 ,
b110 1
b110 3
b1101 0
b1101 7
b1101 :
b110 *
b110 8
b110 '
#119
b100 "
b100 .
b100 ;
b111 %
b111 ,
b111 1
b111 3
b1110 0
b1110 7
b1110 :
b111 *
b111 8
b111 '
#120
b101 "
b101 .
b101 ;
b1000 %
b1000 ,
b1000 1
b1000 3
b1111 0
b1111 7
b1111 :
b1000 *
b1000 8
b1000 '
#121
b110 "
b110 .
b110 ;
b1001 %
b1001 ,
b1001 1
b1001 3
b10000 0
b10000 7
b10000 :
b1001 *
b1001 8
b1001 '
#122
1!
12
1(
b111 "
b111 .
b111 ;
b1010 %
b1010 ,
b1010 1
b1010 3
b10001 0
b10001 7
b10001 :
b1010 *
b1010 8
b1010 '
#123
b1000 "
b1000 .
b1000 ;
b1011 %
b1011 ,
b1011 1
b1011 3
b10010 0
b10010 7
b10010 :
b1011 *
b1011 8
b1011 '
#124
b1001 "
b1001 .
b1001 ;
b1100 %
b1100 ,
b1100 1
b1100 3
b10011 0
b10011 7
b10011 :
b1100 *
b1100 8
b1100 '
#125
b0 "
b0 .
b0 ;
b10 #
b10 /
b10 <
b1101 %
b1101 ,
b1101 1
b1101 3
b10100 0
b10100 7
b10100 :
b1101 *
b1101 8
b1101 '
#126
b1 "
b1 .
b1 ;
b1110 %
b1110 ,
b1110 1
b1110 3
b10101 0
b10101 7
b10101 :
b1110 *
b1110 8
b1110 '
#127
b10 "
b10 .
b10 ;
b1111 %
b1111 ,
b1111 1
b1111 3
b10110 0
b10110 7
b10110 :
b1111 *
b1111 8
b1111 '
#128
0!
02
0(
b0 #
b0 /
b0 <
b1000 "
b1000 .
b1000 ;
b0 %
b0 ,
b0 1
b0 3
b0 *
b0 8
b1000 &
b1000 -
b1000 4
b1000 6
b1000 0
b1000 7
b1000 :
b1000 +
b1000 9
b1000 $
b0 '
#129
b1001 "
b1001 .
b1001 ;
b1 %
b1 ,
b1 1
b1 3
b1001 0
b1001 7
b1001 :
b1 *
b1 8
b1 '
#130
b0 "
b0 .
b0 ;
b1 #
b1 /
b1 <
b10 %
b10 ,
b10 1
b10 3
b1010 0
b1010 7
b1010 :
b10 *
b10 8
b10 '
#131
b1 "
b1 .
b1 ;
b11 %
b11 ,
b11 1
b11 3
b1011 0
b1011 7
b1011 :
b11 *
b11 8
b11 '
#132
b10 "
b10 .
b10 ;
b100 %
b100 ,
b100 1
b100 3
b1100 0
b1100 7
b1100 :
b100 *
b100 8
b100 '
#133
b11 "
b11 .
b11 ;
b101 %
b101 ,
b101 1
b101 3
b1101 0
b1101 7
b1101 :
b101 *
b101 8
b101 '
#134
b100 "
b100 .
b100 ;
b110 %
b110 ,
b110 1
b110 3
b1110 0
b1110 7
b1110 :
b110 *
b110 8
b110 '
#135
b101 "
b101 .
b101 ;
b111 %
b111 ,
b111 1
b111 3
b1111 0
b1111 7
b1111 :
b111 *
b111 8
b111 '
#136
b110 "
b110 .
b110 ;
b1000 %
b1000 ,
b1000 1
b1000 3
b10000 0
b10000 7
b10000 :
b1000 *
b1000 8
b1000 '
#137
b111 "
b111 .
b111 ;
b1001 %
b1001 ,
b1001 1
b1001 3
b10001 0
b10001 7
b10001 :
b1001 *
b1001 8
b1001 '
#138
1!
12
1(
b1000 "
b1000 .
b1000 ;
b1010 %
b1010 ,
b1010 1
b1010 3
b10010 0
b10010 7
b10010 :
b1010 *
b1010 8
b1010 '
#139
b1001 "
b1001 .
b1001 ;
b1011 %
b1011 ,
b1011 1
b1011 3
b10011 0
b10011 7
b10011 :
b1011 *
b1011 8
b1011 '
#140
b0 "
b0 .
b0 ;
b10 #
b10 /
b10 <
b1100 %
b1100 ,
b1100 1
b1100 3
b10100 0
b10100 7
b10100 :
b1100 *
b1100 8
b1100 '
#141
b1 "
b1 .
b1 ;
b1101 %
b1101 ,
b1101 1
b1101 3
b10101 0
b10101 7
b10101 :
b1101 *
b1101 8
b1101 '
#142
b10 "
b10 .
b10 ;
b1110 %
b1110 ,
b1110 1
b1110 3
b10110 0
b10110 7
b10110 :
b1110 *
b1110 8
b1110 '
#143
b11 "
b11 .
b11 ;
b1111 %
b1111 ,
b1111 1
b1111 3
b10111 0
b10111 7
b10111 :
b1111 *
b1111 8
b1111 '
#144
0!
02
0(
b0 #
b0 /
b0 <
b1001 "
b1001 .
b1001 ;
b0 %
b0 ,
b0 1
b0 3
b0 *
b0 8
b1001 &
b1001 -
b1001 4
b1001 6
b1001 0
b1001 7
b1001 :
b1001 +
b1001 9
b1001 $
b0 '
#145
b0 "
b0 .
b0 ;
b1 #
b1 /
b1 <
b1 %
b1 ,
b1 1
b1 3
b1010 0
b1010 7
b1010 :
b1 *
b1 8
b1 '
#146
b1 "
b1 .
b1 ;
b10 %
b10 ,
b10 1
b10 3
b1011 0
b1011 7
b1011 :
b10 *
b10 8
b10 '
#147
b10 "
b10 .
b10 ;
b11 %
b11 ,
b11 1
b11 3
b1100 0
b1100 7
b1100 :
b11 *
b11 8
b11 '
#148
b11 "
b11 .
b11 ;
b100 %
b100 ,
b100 1
b100 3
b1101 0
b1101 7
b1101 :
b100 *
b100 8
b100 '
#149
b100 "
b100 .
b100 ;
b101 %
b101 ,
b101 1
b101 3
b1110 0
b1110 7
b1110 :
b101 *
b101 8
b101 '
#150
b101 "
b101 .
b101 ;
b110 %
b110 ,
b110 1
b110 3
b1111 0
b1111 7
b1111 :
b110 *
b110 8
b110 '
#151
b110 "
b110 .
b110 ;
b111 %
b111 ,
b111 1
b111 3
b10000 0
b10000 7
b10000 :
b111 *
b111 8
b111 '
#152
b111 "
b111 .
b111 ;
b1000 %
b1000 ,
b1000 1
b1000 3
b10001 0
b10001 7
b10001 :
b1000 *
b1000 8
b1000 '
#153
b1000 "
b1000 .
b1000 ;
b1001 %
b1001 ,
b1001 1
b1001 3
b10010 0
b10010 7
b10010 :
b1001 *
b1001 8
b1001 '
#154
1!
12
1(
b1001 "
b1001 .
b1001 ;
b1010 %
b1010 ,
b1010 1
b1010 3
b10011 0
b10011 7
b10011 :
b1010 *
b1010 8
b1010 '
