E5TP1/decoderBCD.v
//This BCD Decoder supports numbers of up to 5-bits
//I'm not sure if Decoder is the proper name

module decoderBCD (
  in,   //5-bit Input Value
  out0, //4-bit Output BCD Digit 0
  out1  //4-bit Output BCD Digit 1
);

//Input Declaration
input [4:0] in;

//Output Declaration
output [3:0] out0;
output [3:0] out1;

//Resources Definition
wire [4:0] in;
reg [3:0] out0;
reg [3:0] out1;

initial begin
  out0 = 0;
  out1 = 0;
end

always @(in) begin
out1 = in/10;
out0 = in%10;
end

endmodule

E5TP1/sum4bit.v
module sum4bit(
    x0, //Sumando 0 (4-bit)
    x1, //Sumando 1 (4-bit)
    o   //Resultado (5-bit)
);

input wire [3:0] x0, x1;
output reg [4:0] o;

initial begin
  o = 0;
end

always @(x0 or x1) begin
  o = x0 + x1;
end


endmodule

E5TP1/filterBCD.v
module filterBCD
(
    in,     //Entrada de datos
    out,    //Salida de datos
    error   //Flag de error o invalido
);

input [3:0] in;

output[3:0] out;
output error;

wire [3:0] in;
reg [3:0] out;
reg error;

initial begin
  error = 0;
  out = 0;
end

always @ (in) begin
  if (in>9) begin
    error = 1;
    out = 0;
  end
  else begin
    error = 0;
    out = in;
  end
end



endmodule

E5TP1/adderBCD.v
`include "decoderBCD.v"
`include "sum4bit.v"
`include "filterBCD.v"

module adderBCD(
    in0,    //BCD Input 0
    in1,    //BCD Input 1
    out0,   //BCD Output 0
    out1,   //BCD Output 1
    flag
);

//Defining Inputs
input [3:0] in0; //BCD Input 0
input [3:0] in1; //BCD Input 1

//Defining Outputs
output [3:0] out0;  //BCD Output digit 0
output [3:0] out1;  //BCD Output digit 1
output flag;

//Defining data types
wire [3:0] in0, in1;
wire [4:0] sum;
wire [3:0] out0,out1;
wire [3:0] f0, f1;
wire e0, e1;

//Declaring included modules
filterBCD filter0(.in(in0), .out(f0), .error(e0));
filterBCD filter1(.in(in1), .out(f1), .error(e1));
sum4bit adder(.x0(f0),.x1(f1),.o(sum));
decoderBCD decoder (.in(sum),.out0(out0),.out1(out1));

assign flag = e0 || e1;

//Code
/*
Get whatever is going to do the sum of the 2 4-bit numbers here
*/

endmodule

E5TP1/src/adderBCD/adderBCD_tb.v
`include "src/adderBCD/adderBCD.v"

module adderBCD_tb;

//Test Data Types
reg [3:0] in0, in1;
wire [3:0] out0, out1;
wire flag;

//Test Indexes
reg [4:0] i,j;

//Connecting the ports adderBCD
adderBCD adder_udt(
  .in0(in0),
  .in1(in1),
  .out0(out0),
  .out1(out1),
  .flag(flag)
  );


//Code
initial begin
  $dumpfile( "adderBCD.vcd");
  $dumpvars;
end

initial begin
  in0 = 0;
  in1 = 0;
  $display("In1\tIn0\t\tOut\t\tError");
  $monitor("%d\t%d\t\t%d,%d\t%b", in1, in0, out1, out0, flag);
end


always begin
for (i = 0; i<16 ; i = i+1) begin
    for (j=0; j<16; j = j+1) begin
      #1 in1 = i[3:0];
      in0 = j[3:0];
      
    end
end
#20$finish;
end



endmodule

E5TP1/adderBCD.vcd
$date
	Mon Sep  3 21:34:05 2018
$end
$version
	Icarus Verilog
$end
$timescale
	1s
$end
$scope module adderBCD_tb $end
$var wire 1 ! flag $end
$var wire 4 " out0 [3:0] $end
$var wire 4 # out1 [3:0] $end
$var reg 5 $ i [4:0] $end
$var reg 4 % in0 [3:0] $end
$var reg 4 & in1 [3:0] $end
$var reg 5 ' j [4:0] $end
$scope module adder_udt $end
$var wire 1 ( e0 $end
$var wire 1 ) e1 $end
$var wire 4 * f0 [3:0] $end
$var wire 4 + f1 [3:0] $end
$var wire 1 ! flag $end
$var wire 4 , in0 [3:0] $end
$var wire 4 - in1 [3:0] $end
$var wire 4 . out0 [3:0] $end
$var wire 4 / out1 [3:0] $end
$var wire 5 0 sum [4:0] $end
$scope module filter0 $end
$var wire 4 1 in [3:0] $end
$var reg 1 2 error $end
$var reg 4 3 out [3:0] $end
$upscope $end
$scope module filter1 $end
$var wire 4 4 in [3:0] $end
$var reg 1 5 error $end
$var reg 4 6 out [3:0] $end
$upscope $end
$scope module adder $end
$var wire 5 7 o [4:0] $end
$var wire 4 8 x0 [3:0] $end
$var wire 4 9 x1 [3:0] $end
$upscope $end
$scope module decoder $end
$var wire 5 : in [4:0] $end
$var wire 4 ; out0 [3:0] $end
$var wire 4 < out1 [3:0] $end
$upscope $end
$upscope $end
$upscope $end
$enddefinitions $end
#0
$dumpvars
b0 <
b0 ;
b0 :
b0 9
b0 8
b0 7
b0 6
05
b0 4
b0 3
02
b0 1
b0 0
b0 /
b0 .
b0 -
b0 ,
b0 +
b0 *
0)
0(
b0 '
b0 &
b0 %
b0 $
b0 #
b0 "
0!
$end
#1
b1 '
#2
b1 "
b1 .
b1 ;
b10 '
b1 %
b1 ,
b1 1
b1 3
b1 0
b1 7
b1 :
b1 *
b1 8
#3
b10 "
b10 .
b10 ;
b11 '
b10 %
b10 ,
b10 1
b10 3
b10 0
b10 7
b10 :
b10 *
b10 8
#4
b11 "
b11 .
b11 ;
b100 '
b11 %
b11 ,
b11 1
b11 3
b11 0
b11 7
b11 :
b11 *
b11 8
#5
b100 "
b100 .
b100 ;
b101 '
b100 %
b100 ,
b100 1
b100 3
b100 0
b100 7
b100 :
b100 *
b100 8
#6
b101 "
b101 .
b101 ;
b110 '
b101 %
b101 ,
b101 1
b101 3
b101 0
b101 7
b101 :
b101 *
b101 8
#7
b110 "
b110 .
b110 ;
b111 '
b110 %
b110 ,
b110 1
b110 3
b110 0
b110 7
b110 :
b110 *
b110 8
#8
b111 "
b111 .
b111 ;
b1000 '
b111 %
b111 ,
b111 1
b111 3
b111 0
b111 7
b111 :
b111 *
b111 8
#9
b1000 "
b1000 .
b1000 ;
b1001 '
b1000 %
b1000 ,
b1000 1
b1000 3
b1000 0
b1000 7
b1000 :
b1000 *
b1000 8
#10
b1001 "
b1001 .
b1001 ;
b1010 '
b1001 %
b1001 ,
b1001 1
b1001 3
b1001 0
b1001 7
b1001 :
b1001 *
b1001 8
#11
1!
12
1(
b0 "
b0 .
b0 ;
b1 #
b1 /
b1 <
b1011 '
b1010 %
b1010 ,
b1010 1
b1010 3
b1010 0
b1010 7
b1010 :
b1010 *
b1010 8
#12
b1 "
b1 .
b1 ;
b1100 '
b1011 %
b1011 ,
b1011 1
b1011 3
b1011 0
b1011 7
b1011 :
b1011 *
b1011 8
#13
b10 "
b10 .
b10 ;
b1101 '
b1100 %
b1100 ,
b1100 1
b1100 3
b1100 0
b1100 7
b1100 :
b1100 *
b1100 8
#14
b11 "
b11 .
b11 ;
b1110 '
b1101 %
b1101 ,
b1101 1
b1101 3
b1101 0
b1101 7
b1101 :
b1101 *
b1101 8
#15
b100 "
b100 .
b100 ;
b1111 '
b1110 %
b1110 ,
b1110 1
b1110 3
b1110 0
b1110 7
b1110 :
b1110 *
b1110 8
#16
b101 "
b101 .
b101 ;
b1 $
b0 '
b1111 %
b1111 ,
b1111 1
b1111 3
b1111 0
b1111 7
b1111 :
b1111 *
b1111 8
#17
0!
02
0(
b0 #
b0 /
b0 <
b1 "
b1 .
b1 ;
b1 '
b0 %
b0 ,
b0 1
b0 3
b0 *
b0 8
b1 &
b1 -
b1 4
b1 6
b1 0
b1 7
b1 :
b1 +
b1 9
#18
b10 "
b10 .
b10 ;
b10 '
b1 %
b1 ,
b1 1
b1 3
b10 0
b10 7
b10 :
b1 *
b1 8
#19
b11 "
b11 .
b11 ;
b11 '
b10 %
b10 ,
b10 1
b10 3
b11 0
b11 7
b11 :
b10 *
b10 8
#20
b100 "
b100 .
b100 ;
b100 '
b11 %
b11 ,
b11 1
b11 3
b100 0
b100 7
b100 :
b11 *
b11 8
#21
b101 "
b101 .
b101 ;
b101 '
b100 %
b100 ,
b100 1
b100 3
b101 0
b101 7
b101 :
b100 *
b100 8
#22
b110 "
b110 .
b110 ;
b110 '
b101 %
b101 ,
b101 1
b101 3
b110 0
b110 7
b110 :
b101 *
b101 8
#23
b111 "
b111 .
b111 ;
b111 '
b110 %
b110 ,
b110 1
b110 3
b111 0
b111 7
b111 :
b110 *
b110 8
#24
b1000 "
b1000 .
b1000 ;
b1000 '
b111 %
b111 ,
b111 1
b111 3
b1000 0
b1000 7
b1000 :
b111 *
b111 8
#25
b1001 "
b1001 .
b1001 ;
b1001 '
b1000 %
b1000 ,
b1000 1
b1000 3
b1001 0
b1001 7
b1001 :
b1000 *
b1000 8
#26
b0 "
b0 .
b0 ;
b1 #
b1 /
b1 <
b1010 '
b1001 %
b1001 ,
b1001 1
b1001 3
b1010 0
b1010 7
b1010 :
b1001 *
b1001 8
#27
1!
12
1(
b1 "
b1 .
b1 ;
b1011 '
b1010 %
b1010 ,
b1010 1
b1010 3
b1011 0
b1011 7
b1011 :
b1010 *
b1010 8
#28
b10 "
b10 .
b10 ;
b1100 '
b1011 %
b1011 ,
b1011 1
b1011 3
b1100 0
b1100 7
b1100 :
b1011 *
b1011 8
#29
b11 "
b11 .
b11 ;
b1101 '
b1100 %
b1100 ,
b1100 1
b1100 3
b1101 0
b1101 7
b1101 :
b1100 *
b1100 8
#30
b100 "
b100 .
b100 ;
b1110 '
b1101 %
b1101 ,
b1101 1
b1101 3
b1110 0
b1110 7
b1110 :
b1101 *
b1101 8
#31
b101 "
b101 .
b101 ;
b1111 '
b1110 %
b1110 ,
b1110 1
b1110 3
b1111 0
b1111 7
b1111 :
b1110 *
b1110 8
#32
b110 "
b110 .
b110 ;
b10 $
b0 '
b1111 %
b1111 ,
b1111 1
b1111 3
b10000 0
b10000 7
b10000 :
b1111 *
b1111 8
#33
0!
02
0(
b0 #
b0 /
b0 <
b10 "
b10 .
b10 ;
b1 '
b0 %
b0 ,
b0 1
b0 3
b0 *
b0 8
b10 &
b10 -
b10 4
b10 6
b10 0
b10 7
b10 :
b10 +
b10 9
#34
b11 "
b11 .
b11 ;
b10 '
b1 %
b1 ,
b1 1
b1 3
b11 0
b11 7
b11 :
b1 *
b1 8
#35
b100 "
b100 .
b100 ;
b11 '
b10 %
b10 ,
b10 1
b10 3
b100 0
b100 7
b100 :
b10 *
b10 8
#36
b101 "
b101 .
b101 ;
b100 '
b11 %
b11 ,
b11 1
b11 3
b101 0
b101 7
b101 :
b11 *
b11 8
#37
b110 "
b110 .
b110 ;
b101 '
b100 %
b100 ,
b100 1
b100 3
b110 0
b110 7
b110 :
b100 *
b100 8
#38
b111 "
b111 .
b111 ;
b110 '
b101 %
b101 ,
b101 1
b101 3
b111 0
b111 7
b111 :
b101 *
b101 8
#39
b1000 "
b1000 .
b1000 ;
b111 '
b110 %
b110 ,
b110 1
b110 3
b1000 0
b1000 7
b1000 :
b110 *
b110 8
#40
b1001 "
b1001 .
b1001 ;
b1000 '
b111 %
b111 ,
b111 1
b111 3
b1001 0
b1001 7
b1001 :
b111 *
b111 8
#41
b0 "
b0 .
b0 ;
b1 #
b1 /
b1 <
b1001 '
b1000 %
b1000 ,
b1000 1
b1000 3
b1010 0
b1010 7
b1010 :
b1000 *
b1000 8
#42
b1 "
b1 .
b1 ;
b1010 '
b1001 %
b1001 ,
b1001 1
b1001 3
b1011 0
b1011 7
b1011 :
b1001 *
b1001 8
#43
1!
12
1(
b10 "
b10 .
b10 ;
b1011 '
b1010 %
b1010 ,
b1010 1
b1010 3
b1100 0
b1100 7
b1100 :
b1010 *
b1010 8
#44
b11 "
b11 .
b11 ;
b1100 '
b1011 %
b1011 ,
b1011 1
b1011 3
b1101 0
b1101 7
b1101 :
b1011 *
b1011 8
#45
b100 "
b100 .
b100 ;
b1101 '
b1100 %
b1100 ,
b1100 1
b1100 3
b1110 0
b1110 7
b1110 :
b1100 *
b1100 8
#46
b101 "
b101 .
b101 ;
b1110 '
b1101 %
b1101 ,
b1101 1
b1101 3
b1111 0
b1111 7
b1111 :
b1101 *
b1101 8
#47
b110 "
b110 .
b110 ;
b1111 '
b1110 %
b1110 ,
b1110 1
b1110 3
b10000 0
b10000 7
b10000 :
b1110 *
b1110 8
#48
b111 "
b111 .
b111 ;
b11 $
b0 '
b1111 %
b1111 ,
b1111 1
b1111 3
b10001 0
b10001 7
b10001 :
b1111 *
b1111 8
#49
0!
02
0(
b0 #
b0 /
b0 <
b11 "
b11 .
b11 ;
b1 '
b0 %
b0 ,
b0 1
b0 3
b0 *
b0 8
b11 &
b11 -
b11 4
b11 6
b11 0
b11 7
b11 :
b11 +
b11 9
#50
b100 "
b100 .
b100 ;
b10 '
b1 %
b1 ,
b1 1
b1 3
b100 0
b100 7
b100 :
b1 *
b1 8
#51
b101 "
b101 .
b101 ;
b11 '
b10 %
b10 ,
b10 1
b10 3
b101 0
b101 7
b101 :
b10 *
b10 8
#52
b110 "
b110 .
b110 ;
b100 '
b11 %
b11 ,
b11 1
b11 3
b110 0
b110 7
b110 :
b11 *
b11 8
#53
b111 "
b111 .
b111 ;
b101 '
b100 %
b100 ,
b100 1
b100 3
b111 0
b111 7
b111 :
b100 *
b100 8
#54
b1000 "
b1000 .
b1000 ;
b110 '
b101 %
b101 ,
b101 1
b101 3
b1000 0
b1000 7
b1000 :
b101 *
b101 8
#55
b1001 "
b1001 .
b1001 ;
b111 '
b110 %
b110 ,
b110 1
b110 3
b1001 0
b1001 7
b1001 :
b110 *
b110 8
#56
b0 "
b0 .
b0 ;
b1 #
b1 /
b1 <
b1000 '
b111 %
b111 ,
b111 1
b111 3
b1010 0
b1010 7
b1010 :
b111 *
b111 8
#57
b1 "
b1 .
b1 ;
b1001 '
b1000 %
b1000 ,
b1000 1
b1000 3
b1011 0
b1011 7
b1011 :
b1000 *
b1000 8
#58
b10 "
b10 .
b10 ;
b1010 '
b1001 %
b1001 ,
b1001 1
b1001 3
b1100 0
b1100 7
b1100 :
b1001 *
b1001 8
#59
1!
12
1(
b11 "
b11 .
b11 ;
b1011 '
b1010 %
b1010 ,
b1010 1
b1010 3
b1101 0
b1101 7
b1101 :
b1010 *
b1010 8
#60
b100 "
b100 .
b100 ;
b1100 '
b1011 %
b1011 ,
b1011 1
b1011 3
b1110 0
b1110 7
b1110 :
b1011 *
b1011 8
#61
b101 "
b101 .
b101 ;
b1101 '
b1100 %
b1100 ,
b1100 1
b1100 3
b1111 0
b1111 7
b1111 :
b1100 *
b1100 8
#62
b110 "
b110 .
b110 ;
b1110 '
b1101 %
b1101 ,
b1101 1
b1101 3
b10000 0
b10000 7
b10000 :
b1101 *
b1101 8
#63
b111 "
b111 .
b111 ;
b1111 '
b1110 %
b1110 ,
b1110 1
b1110 3
b10001 0
b10001 7
b10001 :
b1110 *
b1110 8
#64
b1000 "
b1000 .
b1000 ;
b100 $
b0 '
b1111 %
b1111 ,
b1111 1
b1111 3
b10010 0
b10010 7
b10010 :
b1111 *
b1111 8
#65
0!
02
0(
b0 #
b0 /
b0 <
b100 "
b100 .
b100 ;
b1 '
b0 %
b0 ,
b0 1
b0 3
b0 *
b0 8
b100 &
b100 -
b100 4
b100 6
b100 0
b100 7
b100 :
b100 +
b100 9
#66
b101 "
b101 .
b101 ;
b10 '
b1 %
b1 ,
b1 1
b1 3
b101 0
b101 7
b101 :
b1 *
b1 8
#67
b110 "
b110 .
b110 ;
b11 '
b10 %
b10 ,
b10 1
b10 3
b110 0
b110 7
b110 :
b10 *
b10 8
#68
b111 "
b111 .
b111 ;
b100 '
b11 %
b11 ,
b11 1
b11 3
b111 0
b111 7
b111 :
b11 *
b11 8
#69
b1000 "
b1000 .
b1000 ;
b101 '
b100 %
b100 ,
b100 1
b100 3
b1000 0
b1000 7
b1000 :
b100 *
b100 8
#70
b1001 "
b1001 .
b1001 ;
b110 '
b101 %
b101 ,
b101 1
b101 3
b1001 0
b1001 7
b1001 :
b101 *
b101 8
#71
b0 "
b0 .
b0 ;
b1 #
b1 /
b1 <
b111 '
b110 %
b110 ,
b110 1
b110 3
b1010 0
b1010 7
b1010 :
b110 *
b110 8
#72
b1 "
b1 .
b1 ;
b1000 '
b111 %
b111 ,
b111 1
b111 3
b1011 0
b1011 7
b1011 :
b111 *
b111 8
#73
b10 "
b10 .
b10 ;
b1001 '
b1000 %
b1000 ,
b1000 1
b1000 3
b1100 0
b1100 7
b1100 :
b1000 *
b1000 8
#74
b11 "
b11 .
b11 ;
b1010 '
b1001 %
b1001 ,
b1001 1
b1001 3
b1101 0
b1101 7
b1101 :
b1001 *
b1001 8
#75
1!
12
1(
b100 "
b100 .
b100 ;
b1011 '
b1010 %
b1010 ,
b1010 1
b1010 3
b1110 0
b1110 7
b1110 :
b1010 *
b1010 8
#76
b101 "
b101 .
b101 ;
b1100 '
b1011 %
b1011 ,
b1011 1
b1011 3
b1111 0
b1111 7
b1111 :
b1011 *
b1011 8
#77
b110 "
b110 .
b110 ;
b1101 '
b1100 %
b1100 ,
b1100 1
b1100 3
b10000 0
b10000 7
b10000 :
b1100 *
b1100 8
#78
b111 "
b111 .
b111 ;
b1110 '
b1101 %
b1101 ,
b1101 1
b1101 3
b10001 0
b10001 7
b10001 :
b1101 *
b1101 8
#79
b1000 "
b1000 .
b1000 ;
b1111 '
b1110 %
b1110 ,
b1110 1
b1110 3
b10010 0
b10010 7
b10010 :
b1110 *
b1110 8
#80
b1001 "
b1001 .
b1001 ;
b101 $
b0 '
b1111 %
b1111 ,
b1111 1
b1111 3
b10011 0
b10011 7
b10011 :
b1111 *
b1111 8
#81
0!
02
0(
b101 "
b101 .
b101 ;
b0 #
b0 /
b0 <
b1 '
b0 %
b0 ,
b0 1
b0 3
b0 *
b0 8
b101 &
b101 -
b101 4
b101 6
b101 0
b101 7
b101 :
b101 +
b101 9
#82
b110 "
b110 .
b110 ;
b10 '
b1 %
b1 ,
b1 1
b1 3
b110 0
b110 7
b110 :
b1 *
b1 8
#83
b111 "
b111 .
b111 ;
b11 '
b10 %
b10 ,
b10 1
b10 3
b111 0
b111 7
b111 :
b10 *
b10 8
#84
b1000 "
b1000 .
b1000 ;
b100 '
b11 %
b11 ,
b11 1
b11 3
b1000 0
b1000 7
b1000 :
b11 *
b11 8
#85
b1001 "
b1001 .
b1001 ;
b101 '
b100 %
b100 ,
b100 1
b100 3
b1001 0
b1001 7
b1001 :
b100 *
b100 8
#86
b0 "
b0 .
b0 ;
b1 #
b1 /
b1 <
b110 '
b101 %
b101 ,
b101 1
b101 3
b1010 0
b1010 7
b1010 :
b101 *
b101 8
#87
b1 "
b1 .
b1 ;
b111 '
b110 %
b110 ,
b110 1
b110 3
b1011 0
b1011 7
b1011 :
b110 *
b110 8
#88
b10 "
b10 .
b10 ;
b1000 '
b111 %
b111 ,
b111 1
b111 3
b1100 0
b1100 7
b1100 :
b111 *
b111 8
#89
b11 "
b11 .
b11 ;
b1001 '
b1000 %
b1000 ,
b1000 1
b1000 3
b1101 0
b1101 7
b1101 :
b1000 *
b1000 8
#90
b100 "
b100 .
b100 ;
b1010 '
b1001 %
b1001 ,
b1001 1
b1001 3
b1110 0
b1110 7
b1110 :
b1001 *
b1001 8
#91
1!
12
1(
b101 "
b101 .
b101 ;
b1011 '
b1010 %
b1010 ,
b1010 1
b1010 3
b1111 0
b1111 7
b1111 :
b1010 *
b1010 8
#92
b110 "
b110 .
b110 ;
b1100 '
b1011 %
b1011 ,
b1011 1
b1011 3
b10000 0
b10000 7
b10000 :
b1011 *
b1011 8
#93
b111 "
b111 .
b111 ;
b1101 '
b1100 %
b1100 ,
b1100 1
b1100 3
b10001 0
b10001 7
b10001 :
b1100 *
b1100 8
#94
b1000 "
b1000 .
b1000 ;
b1110 '
b1101 %
b1101 ,
b1101 1
b1101 3
b10010 0
b10010 7
b10010 :
b1101 *
b1101 8
#95
b1001 "
b1001 .
b1001 ;
b1111 '
b1110 %
b1110 ,
b1110 1
b1110 3
b10011 0
b10011 7
b10011 :
b1110 *
b1110 8
#96
b0 "
b0 .
b0 ;
b10 #
b10 /
b10 <
b110 $
b0 '
b1111 %
b1111 ,
b1111 1
b1111 3
b10100 0
b10100 7
b10100 :
b1111 *
b1111 8
#97
0!
02
0(
b0 #
b0 /
b0 <
b110 "
b110 .
b110 ;
b1 '
b0 %
b0 ,
b0 1
b0 3
b0 *
b0 8
b110 &
b110 -
b110 4
b110 6
b110 0
b110 7
b110 :
b110 +
b110 9
#98
b111 "
b111 .
b111 ;
b10 '
b1 %
b1 ,
b1 1
b1 3
b111 0
b111 7
b111 :
b1 *
b1 8
#99
b1000 "
b1000 .
b1000 ;
b11 '
b10 %
b10 ,
b10 1
b10 3
b1000 0
b1000 7
b1000 :
b10 *
b10 8
#100
b1001 "
b1001 .
b1001 ;
b100 '
b11 %
b11 ,
b11 1
b11 3
b1001 0
b1001 7
b1001 :
b11 *
b11 8
#101
b0 "
b0 .
b0 ;
b1 #
b1 /
b1 <
b101 '
b100 %
b100 ,
b100 1
b100 3
b1010 0
b1010 7
b1010 :
b100 *
b100 8
#102
b1 "
b1 .
b1 ;
b110 '
b101 %
b101 ,
b101 1
b101 3
b1011 0
b1011 7
b1011 :
b101 *
b101 8
#103
b10 "
b10 .
b10 ;
b111 '
b110 %
b110 ,
b110 1
b110 3
b1100 0
b1100 7
b1100 :
b110 *
b110 8
#104
b11 "
b11 .
b11 ;
b1000 '
b111 %
b111 ,
b111 1
b111 3
b1101 0
b1101 7
b1101 :
b111 *
b111 8
#105
b100 "
b100 .
b100 ;
b1001 '
b1000 %
b1000 ,
b1000 1
b1000 3
b1110 0
b1110 7
b1110 :
b1000 *
b1000 8
#106
b101 "
b101 .
b101 ;
b1010 '
b1001 %
b1001 ,
b1001 1
b1001 3
b1111 0
b1111 7
b1111 :
b1001 *
b1001 8
#107
1!
12
1(
b110 "
b110 .
b110 ;
b1011 '
b1010 %
b1010 ,
b1010 1
b1010 3
b10000 0
b10000 7
b10000 :
b1010 *
b1010 8
#108
b111 "
b111 .
b111 ;
b1100 '
b1011 %
b1011 ,
b1011 1
b1011 3
b10001 0
b10001 7
b10001 :
b1011 *
b1011 8
#109
b1000 "
b1000 .
b1000 ;
b1101 '
b1100 %
b1100 ,
b1100 1
b1100 3
b10010 0
b10010 7
b10010 :
b1100 *
b1100 8
#110
b1001 "
b1001 .
b1001 ;
b1110 '
b1101 %
b1101 ,
b1101 1
b1101 3
b10011 0
b10011 7
b10011 :
b1101 *
b1101 8
#111
b0 "
b0 .
b0 ;
b10 #
b10 /
b10 <
b1111 '
b1110 %
b1110 ,
b1110 1
b1110 3
b10100 0
b10100 7
b10100 :
b1110 *
b1110 8
#112
b1 "
b1 .
b1 ;
b111 $
b0 '
b1111 %
b1111 ,
b1111 1
b1111 3
b10101 0
b10101 7
b10101 :
b1111 *
b1111 8
#113
0!
02
0(
b0 #
b0 /
b0 <
b111 "
b111 .
b111 ;
b1 '
b0 %
b0 ,
b0 1
b0 3
b0 *
b0 8
b111 &
b111 -
b111 4
b111 6
b111 0
b111 7
b111 :
b111 +
b111 9
#114
b1000 "
b1000 .
b1000 ;
b10 '
b1 %
b1 ,
b1 1
b1 3
b1000 0
b1000 7
b1000 :
b1 *
b1 8
#115
b1001 "
b1001 .
b1001 ;
b11 '
b10 %
b10 ,
b10 1
b10 3
b1001 0
b1001 7
b1001 :
b10 *
b10 8
#116
b0 "
b0 .
b0 ;
b1 #
b1 /
b1 <
b100 '
b11 %
b11 ,
b11 1
b11 3
b1010 0
b1010 7
b1010 :
b11 *
b11 8
#117
b1 "
b1 .
b1 ;
b101 '
b100 %
b100 ,
b100 1
b100 3
b1011 0
b1011 7
b1011 :
b100 *
b100 8
#118
b10 "
b10 .
b10 ;
b110 '
b101 %
b101 ,
b101 1
b101 3
b1100 0
b1100 7
b1100 :
b101 *
b101 8
#119
b11 "
b11 .
b11 ;
b111 '
b110 %
b110 ,
b110 1
b110 3
b1101 0
b1101 7
b1101 :
b110 *
b110 8
#120
b100 "
b100 .
b100 ;
b1000 '
b111 %
b111 ,
b111 1
b111 3
b1110 0
b1110 7
b1110 :
b111 *
b111 8
#121
b101 "
b101 .
b101 ;
b1001 '
b1000 %
b1000 ,
b1000 1
b1000 3
b1111 0
b1111 7
b1111 :
b1000 *
b1000 8
#122
b110 "
b110 .
b110 ;
b1010 '
b1001 %
b1001 ,
b1001 1
b1001 3
b10000 0
b10000 7
b10000 :
b1001 *
b1001 8
#123
1!
12
1(
b111 "
b111 .
b111 ;
b1011 '
b1010 %
b1010 ,
b1010 1
b1010 3
b10001 0
b10001 7
b10001 :
b1010 *
b1010 8
#124
b1000 "
b1000 .
b1000 ;
b1100 '
b1011 %
b1011 ,
b1011 1
b1011 3
b10010 0
b10010 7
b10010 :
b1011 *
b1011 8
#125
b1001 "
b1001 .
b1001 ;
b1101 '
b1100 %
b1100 ,
b1100 1
b1100 3
b10011 0
b10011 7
b10011 :
b1100 *
b1100 8
#126
b0 "
b0 .
b0 ;
b10 #
b10 /
b10 <
b1110 '
b1101 %
b1101 ,
b1101 1
b1101 3
b10100 0
b10100 7
b10100 :
b1101 *
b1101 8
#127
b1 "
b1 .
b1 ;
b1111 '
b1110 %
b1110 ,
b1110 1
b1110 3
b10101 0
b10101 7
b10101 :
b1110 *
b1110 8
#128
b10 "
b10 .
b10 ;
b1000 $
b0 '
b1111 %
b1111 ,
b1111 1
b1111 3
b10110 0
b10110 7
b10110 :
b1111 *
b1111 8
#129
0!
02
0(
b0 #
b0 /
b0 <
b1000 "
b1000 .
b1000 ;
b1 '
b0 %
b0 ,
b0 1
b0 3
b0 *
b0 8
b1000 &
b1000 -
b1000 4
b1000 6
b1000 0
b1000 7
b1000 :
b1000 +
b1000 9
#130
b1001 "
b1001 .
b1001 ;
b10 '
b1 %
b1 ,
b1 1
b1 3
b1001 0
b1001 7
b1001 :
b1 *
b1 8
#131
b0 "
b0 .
b0 ;
b1 #
b1 /
b1 <
b11 '
b10 %
b10 ,
b10 1
b10 3
b1010 0
b1010 7
b1010 :
b10 *
b10 8
#132
b1 "
b1 .
b1 ;
b100 '
b11 %
b11 ,
b11 1
b11 3
b1011 0
b1011 7
b1011 :
b11 *
b11 8
#133
b10 "
b10 .
b10 ;
b101 '
b100 %
b100 ,
b100 1
b100 3
b1100 0
b1100 7
b1100 :
b100 *
b100 8
#134
b11 "
b11 .
b11 ;
b110 '
b101 %
b101 ,
b101 1
b101 3
b1101 0
b1101 7
b1101 :
b101 *
b101 8
#135
b100 "
b100 .
b100 ;
b111 '
b110 %
b110 ,
b110 1
b110 3
b1110 0
b1110 7
b1110 :
b110 *
b110 8
#136
b101 "
b101 .
b101 ;
b1000 '
b111 %
b111 ,
b111 1
b111 3
b1111 0
b1111 7
b1111 :
b111 *
b111 8
#137
b110 "
b110 .
b110 ;
b1001 '
b1000 %
b1000 ,
b1000 1
b1000 3
b10000 0
b10000 7
b10000 :
b1000 *
b1000 8
#138
b111 "
b111 .
b111 ;
b1010 '
b1001 %
b1001 ,
b1001 1
b1001 3
b10001 0
b10001 7
b10001 :
b1001 *
b1001 8
#139
1!
12
1(
b1000 "
b1000 .
b1000 ;
b1011 '
b1010 %
b1010 ,
b1010 1
b1010 3
b10010 0
b10010 7
b10010 :
b1010 *
b1010 8
#140
b1001 "
b1001 .
b1001 ;
b1100 '
b1011 %
b1011 ,
b1011 1
b1011 3
b10011 0
b10011 7
b10011 :
b1011 *
b1011 8
#141
b0 "
b0 .
b0 ;
b10 #
b10 /
b10 <
b1101 '
b1100 %
b1100 ,
b1100 1
b1100 3
b10100 0
b10100 7
b10100 :
b1100 *
b1100 8
#142
b1 "
b1 .
b1 ;
b1110 '
b1101 %
b1101 ,
b1101 1
b1101 3
b10101 0
b10101 7
b10101 :
b1101 *
b1101 8
#143
b10 "
b10 .
b10 ;
b1111 '
b1110 %
b1110 ,
b1110 1
b1110 3
b10110 0
b10110 7
b10110 :
b1110 *
b1110 8
#144
b11 "
b11 .
b11 ;
b1001 $
b0 '
b1111 %
b1111 ,
b1111 1
b1111 3
b10111 0
b10111 7
b10111 :
b1111 *
b1111 8
#145
0!
02
0(
b0 #
b0 /
b0 <
b1001 "
b1001 .
b1001 ;
b1 '
b0 %
b0 ,
b0 1
b0 3
b0 *
b0 8
b1001 &
b1001 -
b1001 4
b1001 6
b1001 0
b1001 7
b1001 :
b1001 +
b1001 9
#146
b0 "
b0 .
b0 ;
b1 #
b1 /
b1 <
b10 '
b1 %
b1 ,
b1 1
b1 3
b1010 0
b1010 7
b1010 :
b1 *
b1 8
#147
b1 "
b1 .
b1 ;
b11 '
b10 %
b10 ,
b10 1
b10 3
b1011 0
b1011 7
b1011 :
b10 *
b10 8
#148
b10 "
b10 .
b10 ;
b100 '
b11 %
b11 ,
b11 1
b11 3
b1100 0
b1100 7
b1100 :
b11 *
b11 8
#149
b11 "
b11 .
b11 ;
b101 '
b100 %
b100 ,
b100 1
b100 3
b1101 0
b1101 7
b1101 :
b100 *
b100 8
#150
b100 "
b100 .
b100 ;
b110 '
b101 %
b101 ,
b101 1
b101 3
b1110 0
b1110 7
b1110 :
b101 *
b101 8
#151
b101 "
b101 .
b101 ;
b111 '
b110 %
b110 ,
b110 1
b110 3
b1111 0
b1111 7
b1111 :
b110 *
b110 8
#152
b110 "
b110 .
b110 ;
b1000 '
b111 %
b111 ,
b111 1
b111 3
b10000 0
b10000 7
b10000 :
b111 *
b111 8
#153
b111 "
b111 .
b111 ;
b1001 '
b1000 %
b1000 ,
b1000 1
b1000 3
b10001 0
b10001 7
b10001 :
b1000 *
b1000 8
#154
b1000 "
b1000 .
b1000 ;
b1010 '
b1001 %
b1001 ,
b1001 1
b1001 3
b10010 0
b10010 7
b10010 :
b1001 *
b1001 8
#155
1!
12
1(
b1001 "
b1001 .
b1001 ;
b1011 '
b1010 %
b1010 ,
b1010 1
b1010 3
b10011 0
b10011 7
b10011 :
b1010 *
b1010 8
