E5TP1/decoderBCD.v
//This BCD Decoder supports numbers of up to 5-bits
//I'm not sure if Decoder is the proper name

module decoderBCD (
  in,   //5-bit Input Value
  out0, //4-bit Output BCD Digit 0
  out1  //4-bit Output BCD Digit 1
);

//Input Declaration
input [4:0] in;

//Output Declaration
output [3:0] out0;
output [3:0] out1;

//Resources Definition
wire [4:0] in;
reg [3:0] out0;
reg [3:0] out1;

initial begin
  out0 = 0;
  out1 = 0;
end

always @(in) begin
out1 = in/10;
out0 = in%10;
end

endmodule

E5TP1/sum4bit.v
module sum4bit(
    x0, //Sumando 0 (4-bit)
    x1, //Sumando 1 (4-bit)
    o   //Resultado (5-bit)
);

input wire [3:0] x0, x1;
output reg [4:0] o;

initial begin
  o = 0;
end

always @(x0 or x1) begin
  o = x0 + x1;
end


endmodule

E5TP1/filterBCD.v
module filterBCD
(
    in,     //Entrada de datos
    out,    //Salida de datos
    error   //Flag de error o invalido
);

input [3:0] in;

output[3:0] out;
output error;

wire [3:0] in;
reg [3:0] out;
reg error;

initial begin
  error = 0;
  out = 0;
end

always @ (in) begin
  if (in>9) begin
    error = 1;
    out = 0;
  end
  else begin
    error = 0;
    out = in;
  end
end



endmodule

E5TP1/adderBCD.v
`include "decoderBCD.v"
`include "sum4bit.v"
`include "filterBCD.v"

module adderBCD(
    in0,    //BCD Input 0
    in1,    //BCD Input 1
    out0,   //BCD Output 0
    out1,   //BCD Output 1
    flag
);

//Defining Inputs
input [3:0] in0; //BCD Input 0
input [3:0] in1; //BCD Input 1

//Defining Outputs
output [3:0] out0;  //BCD Output digit 0
output [3:0] out1;  //BCD Output digit 1
output flag;

//Defining data types
wire [3:0] in0, in1;
wire [4:0] sum;
wire [3:0] out0,out1;
wire [3:0] f0, f1;
wire e0, e1;

//Declaring included modules
filterBCD filter0(.in(in0), .out(f0), .error(e0));
filterBCD filter1(.in(in1), .out(f1), .error(e1));
sum4bit adder(.x0(f0),.x1(f1),.o(sum));
decoderBCD decoder (.in(sum),.out0(out0),.out1(out1));

assign flag = e0 || e1;

//Code
/*
Get whatever is going to do the sum of the 2 4-bit numbers here
*/

endmodule

E5TP1/adderBCD_tb.v
`include "adderBCD.v"

module adderBCD_tb;

//Test Data Types
reg [3:0] in0, in1;
wire [3:0] out0, out1;
wire flag;

//Test Indexes
reg [3:0] i,j;

//Connecting the ports adderBCD
adderBCD adder_udt(.in0(in0), .in1(in1), .out0(out0), .out1(out1), .flag(flag));


//Code
initial begin
  $dumpfile( "adderBCD.vcd");
  $dumpvars;
end

initial begin
  in0 = 0;
  in1 = 0;
  $display("In0\tIn1\tOut\tError");
  $monitor("%d\t%d\t%d,%d\t%b", in0, in1, out1, out0, flag);
end


always begin
for (i = 0; i<15 ; i = i+1) begin
    #1 in0 = i;
    for (j=0; j<15; j = j+1) begin
      #1in1 = j;
    end
end
#20$finish;
end



endmodule

E5TP1/adderBCD.vcd
$date
	Fri Aug 24 16:15:44 2018
$end
$version
	Icarus Verilog
$end
$timescale
	1s
$end
$scope module adderBCD_tb $end
$var wire 1 ! flag $end
$var wire 4 " out0 [3:0] $end
$var wire 4 # out1 [3:0] $end
$var reg 4 $ i [3:0] $end
$var reg 4 % in0 [3:0] $end
$var reg 4 & in1 [3:0] $end
$var reg 4 ' j [3:0] $end
$scope module adder_udt $end
$var wire 1 ( e0 $end
$var wire 1 ) e1 $end
$var wire 4 * f0 [3:0] $end
$var wire 4 + f1 [3:0] $end
$var wire 1 ! flag $end
$var wire 4 , in0 [3:0] $end
$var wire 4 - in1 [3:0] $end
$var wire 4 . out0 [3:0] $end
$var wire 4 / out1 [3:0] $end
$var wire 5 0 sum [4:0] $end
$scope module filter0 $end
$var wire 4 1 in [3:0] $end
$var reg 1 2 error $end
$var reg 4 3 out [3:0] $end
$upscope $end
$scope module filter1 $end
$var wire 4 4 in [3:0] $end
$var reg 1 5 error $end
$var reg 4 6 out [3:0] $end
$upscope $end
$scope module adder $end
$var wire 5 7 o [4:0] $end
$var wire 4 8 x0 [3:0] $end
$var wire 4 9 x1 [3:0] $end
$upscope $end
$scope module decoder $end
$var wire 5 : in [4:0] $end
$var wire 4 ; out0 [3:0] $end
$var wire 4 < out1 [3:0] $end
$upscope $end
$upscope $end
$upscope $end
$enddefinitions $end
#0
$dumpvars
b0 <
b0 ;
b0 :
b0 9
b0 8
b0 7
b0 6
05
b0 4
b0 3
02
b0 1
b0 0
b0 /
b0 .
b0 -
b0 ,
b0 +
b0 *
0)
0(
bx '
b0 &
b0 %
b0 $
b0 #
b0 "
0!
$end
#1
b0 '
#2
b1 '
#3
b1 "
b1 .
b1 ;
b10 '
b1 &
b1 -
b1 4
b1 6
b1 0
b1 7
b1 :
b1 +
b1 9
#4
b10 "
b10 .
b10 ;
b11 '
b10 &
b10 -
b10 4
b10 6
b10 0
b10 7
b10 :
b10 +
b10 9
#5
b11 "
b11 .
b11 ;
b100 '
b11 &
b11 -
b11 4
b11 6
b11 0
b11 7
b11 :
b11 +
b11 9
#6
b100 "
b100 .
b100 ;
b101 '
b100 &
b100 -
b100 4
b100 6
b100 0
b100 7
b100 :
b100 +
b100 9
#7
b101 "
b101 .
b101 ;
b110 '
b101 &
b101 -
b101 4
b101 6
b101 0
b101 7
b101 :
b101 +
b101 9
#8
b110 "
b110 .
b110 ;
b111 '
b110 &
b110 -
b110 4
b110 6
b110 0
b110 7
b110 :
b110 +
b110 9
#9
b111 "
b111 .
b111 ;
b1000 '
b111 &
b111 -
b111 4
b111 6
b111 0
b111 7
b111 :
b111 +
b111 9
#10
b1000 "
b1000 .
b1000 ;
b1001 '
b1000 &
b1000 -
b1000 4
b1000 6
b1000 0
b1000 7
b1000 :
b1000 +
b1000 9
#11
b1001 "
b1001 .
b1001 ;
b1010 '
b1001 &
b1001 -
b1001 4
b1001 6
b1001 0
b1001 7
b1001 :
b1001 +
b1001 9
#12
1!
15
1)
b0 "
b0 .
b0 ;
b1 #
b1 /
b1 <
b1011 '
b1010 &
b1010 -
b1010 4
b1010 6
b1010 0
b1010 7
b1010 :
b1010 +
b1010 9
#13
b1 "
b1 .
b1 ;
b1100 '
b1011 &
b1011 -
b1011 4
b1011 6
b1011 0
b1011 7
b1011 :
b1011 +
b1011 9
#14
b10 "
b10 .
b10 ;
b1101 '
b1100 &
b1100 -
b1100 4
b1100 6
b1100 0
b1100 7
b1100 :
b1100 +
b1100 9
#15
b11 "
b11 .
b11 ;
b1110 '
b1101 &
b1101 -
b1101 4
b1101 6
b1101 0
b1101 7
b1101 :
b1101 +
b1101 9
#16
b100 "
b100 .
b100 ;
b1 $
b1111 '
b1110 &
b1110 -
b1110 4
b1110 6
b1110 0
b1110 7
b1110 :
b1110 +
b1110 9
#17
b101 "
b101 .
b101 ;
b0 '
b1 %
b1 ,
b1 1
b1 3
b1111 0
b1111 7
b1111 :
b1 *
b1 8
#18
0!
05
0)
b1 "
b1 .
b1 ;
b0 #
b0 /
b0 <
b1 '
b0 &
b0 -
b0 4
b0 6
b1 0
b1 7
b1 :
b0 +
b0 9
#19
b10 "
b10 .
b10 ;
b10 '
b1 &
b1 -
b1 4
b1 6
b10 0
b10 7
b10 :
b1 +
b1 9
#20
b11 "
b11 .
b11 ;
b11 '
b10 &
b10 -
b10 4
b10 6
b11 0
b11 7
b11 :
b10 +
b10 9
#21
b100 "
b100 .
b100 ;
b100 '
b11 &
b11 -
b11 4
b11 6
b100 0
b100 7
b100 :
b11 +
b11 9
#22
b101 "
b101 .
b101 ;
b101 '
b100 &
b100 -
b100 4
b100 6
b101 0
b101 7
b101 :
b100 +
b100 9
#23
b110 "
b110 .
b110 ;
b110 '
b101 &
b101 -
b101 4
b101 6
b110 0
b110 7
b110 :
b101 +
b101 9
#24
b111 "
b111 .
b111 ;
b111 '
b110 &
b110 -
b110 4
b110 6
b111 0
b111 7
b111 :
b110 +
b110 9
#25
b1000 "
b1000 .
b1000 ;
b1000 '
b111 &
b111 -
b111 4
b111 6
b1000 0
b1000 7
b1000 :
b111 +
b111 9
#26
b1001 "
b1001 .
b1001 ;
b1001 '
b1000 &
b1000 -
b1000 4
b1000 6
b1001 0
b1001 7
b1001 :
b1000 +
b1000 9
#27
b0 "
b0 .
b0 ;
b1 #
b1 /
b1 <
b1010 '
b1001 &
b1001 -
b1001 4
b1001 6
b1010 0
b1010 7
b1010 :
b1001 +
b1001 9
#28
1!
15
1)
b1 "
b1 .
b1 ;
b1011 '
b1010 &
b1010 -
b1010 4
b1010 6
b1011 0
b1011 7
b1011 :
b1010 +
b1010 9
#29
b10 "
b10 .
b10 ;
b1100 '
b1011 &
b1011 -
b1011 4
b1011 6
b1100 0
b1100 7
b1100 :
b1011 +
b1011 9
#30
b11 "
b11 .
b11 ;
b1101 '
b1100 &
b1100 -
b1100 4
b1100 6
b1101 0
b1101 7
b1101 :
b1100 +
b1100 9
#31
b100 "
b100 .
b100 ;
b1110 '
b1101 &
b1101 -
b1101 4
b1101 6
b1110 0
b1110 7
b1110 :
b1101 +
b1101 9
#32
b101 "
b101 .
b101 ;
b10 $
b1111 '
b1110 &
b1110 -
b1110 4
b1110 6
b1111 0
b1111 7
b1111 :
b1110 +
b1110 9
#33
b110 "
b110 .
b110 ;
b0 '
b10 %
b10 ,
b10 1
b10 3
b10000 0
b10000 7
b10000 :
b10 *
b10 8
#34
0!
05
0)
b10 "
b10 .
b10 ;
b0 #
b0 /
b0 <
b1 '
b0 &
b0 -
b0 4
b0 6
b10 0
b10 7
b10 :
b0 +
b0 9
#35
b11 "
b11 .
b11 ;
b10 '
b1 &
b1 -
b1 4
b1 6
b11 0
b11 7
b11 :
b1 +
b1 9
#36
b100 "
b100 .
b100 ;
b11 '
b10 &
b10 -
b10 4
b10 6
b100 0
b100 7
b100 :
b10 +
b10 9
#37
b101 "
b101 .
b101 ;
b100 '
b11 &
b11 -
b11 4
b11 6
b101 0
b101 7
b101 :
b11 +
b11 9
#38
b110 "
b110 .
b110 ;
b101 '
b100 &
b100 -
b100 4
b100 6
b110 0
b110 7
b110 :
b100 +
b100 9
#39
b111 "
b111 .
b111 ;
b110 '
b101 &
b101 -
b101 4
b101 6
b111 0
b111 7
b111 :
b101 +
b101 9
#40
b1000 "
b1000 .
b1000 ;
b111 '
b110 &
b110 -
b110 4
b110 6
b1000 0
b1000 7
b1000 :
b110 +
b110 9
#41
b1001 "
b1001 .
b1001 ;
b1000 '
b111 &
b111 -
b111 4
b111 6
b1001 0
b1001 7
b1001 :
b111 +
b111 9
#42
b0 "
b0 .
b0 ;
b1 #
b1 /
b1 <
b1001 '
b1000 &
b1000 -
b1000 4
b1000 6
b1010 0
b1010 7
b1010 :
b1000 +
b1000 9
#43
b1 "
b1 .
b1 ;
b1010 '
b1001 &
b1001 -
b1001 4
b1001 6
b1011 0
b1011 7
b1011 :
b1001 +
b1001 9
#44
1!
15
1)
b10 "
b10 .
b10 ;
b1011 '
b1010 &
b1010 -
b1010 4
b1010 6
b1100 0
b1100 7
b1100 :
b1010 +
b1010 9
#45
b11 "
b11 .
b11 ;
b1100 '
b1011 &
b1011 -
b1011 4
b1011 6
b1101 0
b1101 7
b1101 :
b1011 +
b1011 9
#46
b100 "
b100 .
b100 ;
b1101 '
b1100 &
b1100 -
b1100 4
b1100 6
b1110 0
b1110 7
b1110 :
b1100 +
b1100 9
#47
b101 "
b101 .
b101 ;
b1110 '
b1101 &
b1101 -
b1101 4
b1101 6
b1111 0
b1111 7
b1111 :
b1101 +
b1101 9
#48
b110 "
b110 .
b110 ;
b11 $
b1111 '
b1110 &
b1110 -
b1110 4
b1110 6
b10000 0
b10000 7
b10000 :
b1110 +
b1110 9
#49
b111 "
b111 .
b111 ;
b0 '
b11 %
b11 ,
b11 1
b11 3
b10001 0
b10001 7
b10001 :
b11 *
b11 8
#50
0!
05
0)
b11 "
b11 .
b11 ;
b0 #
b0 /
b0 <
b1 '
b0 &
b0 -
b0 4
b0 6
b11 0
b11 7
b11 :
b0 +
b0 9
#51
b100 "
b100 .
b100 ;
b10 '
b1 &
b1 -
b1 4
b1 6
b100 0
b100 7
b100 :
b1 +
b1 9
#52
b101 "
b101 .
b101 ;
b11 '
b10 &
b10 -
b10 4
b10 6
b101 0
b101 7
b101 :
b10 +
b10 9
#53
b110 "
b110 .
b110 ;
b100 '
b11 &
b11 -
b11 4
b11 6
b110 0
b110 7
b110 :
b11 +
b11 9
#54
b111 "
b111 .
b111 ;
b101 '
b100 &
b100 -
b100 4
b100 6
b111 0
b111 7
b111 :
b100 +
b100 9
#55
b1000 "
b1000 .
b1000 ;
b110 '
b101 &
b101 -
b101 4
b101 6
b1000 0
b1000 7
b1000 :
b101 +
b101 9
#56
b1001 "
b1001 .
b1001 ;
b111 '
b110 &
b110 -
b110 4
b110 6
b1001 0
b1001 7
b1001 :
b110 +
b110 9
#57
b0 "
b0 .
b0 ;
b1 #
b1 /
b1 <
b1000 '
b111 &
b111 -
b111 4
b111 6
b1010 0
b1010 7
b1010 :
b111 +
b111 9
#58
b1 "
b1 .
b1 ;
b1001 '
b1000 &
b1000 -
b1000 4
b1000 6
b1011 0
b1011 7
b1011 :
b1000 +
b1000 9
#59
b10 "
b10 .
b10 ;
b1010 '
b1001 &
b1001 -
b1001 4
b1001 6
b1100 0
b1100 7
b1100 :
b1001 +
b1001 9
#60
1!
15
1)
b11 "
b11 .
b11 ;
b1011 '
b1010 &
b1010 -
b1010 4
b1010 6
b1101 0
b1101 7
b1101 :
b1010 +
b1010 9
#61
b100 "
b100 .
b100 ;
b1100 '
b1011 &
b1011 -
b1011 4
b1011 6
b1110 0
b1110 7
b1110 :
b1011 +
b1011 9
#62
b101 "
b101 .
b101 ;
b1101 '
b1100 &
b1100 -
b1100 4
b1100 6
b1111 0
b1111 7
b1111 :
b1100 +
b1100 9
#63
b110 "
b110 .
b110 ;
b1110 '
b1101 &
b1101 -
b1101 4
b1101 6
b10000 0
b10000 7
b10000 :
b1101 +
b1101 9
#64
b111 "
b111 .
b111 ;
b100 $
b1111 '
b1110 &
b1110 -
b1110 4
b1110 6
b10001 0
b10001 7
b10001 :
b1110 +
b1110 9
#65
b1000 "
b1000 .
b1000 ;
b0 '
b100 %
b100 ,
b100 1
b100 3
b10010 0
b10010 7
b10010 :
b100 *
b100 8
#66
0!
05
0)
b100 "
b100 .
b100 ;
b0 #
b0 /
b0 <
b1 '
b0 &
b0 -
b0 4
b0 6
b100 0
b100 7
b100 :
b0 +
b0 9
#67
b101 "
b101 .
b101 ;
b10 '
b1 &
b1 -
b1 4
b1 6
b101 0
b101 7
b101 :
b1 +
b1 9
#68
b110 "
b110 .
b110 ;
b11 '
b10 &
b10 -
b10 4
b10 6
b110 0
b110 7
b110 :
b10 +
b10 9
#69
b111 "
b111 .
b111 ;
b100 '
b11 &
b11 -
b11 4
b11 6
b111 0
b111 7
b111 :
b11 +
b11 9
#70
b1000 "
b1000 .
b1000 ;
b101 '
b100 &
b100 -
b100 4
b100 6
b1000 0
b1000 7
b1000 :
b100 +
b100 9
#71
b1001 "
b1001 .
b1001 ;
b110 '
b101 &
b101 -
b101 4
b101 6
b1001 0
b1001 7
b1001 :
b101 +
b101 9
#72
b0 "
b0 .
b0 ;
b1 #
b1 /
b1 <
b111 '
b110 &
b110 -
b110 4
b110 6
b1010 0
b1010 7
b1010 :
b110 +
b110 9
#73
b1 "
b1 .
b1 ;
b1000 '
b111 &
b111 -
b111 4
b111 6
b1011 0
b1011 7
b1011 :
b111 +
b111 9
#74
b10 "
b10 .
b10 ;
b1001 '
b1000 &
b1000 -
b1000 4
b1000 6
b1100 0
b1100 7
b1100 :
b1000 +
b1000 9
#75
b11 "
b11 .
b11 ;
b1010 '
b1001 &
b1001 -
b1001 4
b1001 6
b1101 0
b1101 7
b1101 :
b1001 +
b1001 9
#76
1!
15
1)
b100 "
b100 .
b100 ;
b1011 '
b1010 &
b1010 -
b1010 4
b1010 6
b1110 0
b1110 7
b1110 :
b1010 +
b1010 9
#77
b101 "
b101 .
b101 ;
b1100 '
b1011 &
b1011 -
b1011 4
b1011 6
b1111 0
b1111 7
b1111 :
b1011 +
b1011 9
#78
b110 "
b110 .
b110 ;
b1101 '
b1100 &
b1100 -
b1100 4
b1100 6
b10000 0
b10000 7
b10000 :
b1100 +
b1100 9
#79
b111 "
b111 .
b111 ;
b1110 '
b1101 &
b1101 -
b1101 4
b1101 6
b10001 0
b10001 7
b10001 :
b1101 +
b1101 9
#80
b1000 "
b1000 .
b1000 ;
b101 $
b1111 '
b1110 &
b1110 -
b1110 4
b1110 6
b10010 0
b10010 7
b10010 :
b1110 +
b1110 9
#81
b1001 "
b1001 .
b1001 ;
b0 '
b101 %
b101 ,
b101 1
b101 3
b10011 0
b10011 7
b10011 :
b101 *
b101 8
#82
0!
05
0)
b101 "
b101 .
b101 ;
b0 #
b0 /
b0 <
b1 '
b0 &
b0 -
b0 4
b0 6
b101 0
b101 7
b101 :
b0 +
b0 9
#83
b110 "
b110 .
b110 ;
b10 '
b1 &
b1 -
b1 4
b1 6
b110 0
b110 7
b110 :
b1 +
b1 9
#84
b111 "
b111 .
b111 ;
b11 '
b10 &
b10 -
b10 4
b10 6
b111 0
b111 7
b111 :
b10 +
b10 9
#85
b1000 "
b1000 .
b1000 ;
b100 '
b11 &
b11 -
b11 4
b11 6
b1000 0
b1000 7
b1000 :
b11 +
b11 9
#86
b1001 "
b1001 .
b1001 ;
b101 '
b100 &
b100 -
b100 4
b100 6
b1001 0
b1001 7
b1001 :
b100 +
b100 9
#87
b0 "
b0 .
b0 ;
b1 #
b1 /
b1 <
b110 '
b101 &
b101 -
b101 4
b101 6
b1010 0
b1010 7
b1010 :
b101 +
b101 9
#88
b1 "
b1 .
b1 ;
b111 '
b110 &
b110 -
b110 4
b110 6
b1011 0
b1011 7
b1011 :
b110 +
b110 9
#89
b10 "
b10 .
b10 ;
b1000 '
b111 &
b111 -
b111 4
b111 6
b1100 0
b1100 7
b1100 :
b111 +
b111 9
#90
b11 "
b11 .
b11 ;
b1001 '
b1000 &
b1000 -
b1000 4
b1000 6
b1101 0
b1101 7
b1101 :
b1000 +
b1000 9
#91
b100 "
b100 .
b100 ;
b1010 '
b1001 &
b1001 -
b1001 4
b1001 6
b1110 0
b1110 7
b1110 :
b1001 +
b1001 9
#92
1!
15
1)
b101 "
b101 .
b101 ;
b1011 '
b1010 &
b1010 -
b1010 4
b1010 6
b1111 0
b1111 7
b1111 :
b1010 +
b1010 9
#93
b110 "
b110 .
b110 ;
b1100 '
b1011 &
b1011 -
b1011 4
b1011 6
b10000 0
b10000 7
b10000 :
b1011 +
b1011 9
#94
b111 "
b111 .
b111 ;
b1101 '
b1100 &
b1100 -
b1100 4
b1100 6
b10001 0
b10001 7
b10001 :
b1100 +
b1100 9
#95
b1000 "
b1000 .
b1000 ;
b1110 '
b1101 &
b1101 -
b1101 4
b1101 6
b10010 0
b10010 7
b10010 :
b1101 +
b1101 9
#96
b1001 "
b1001 .
b1001 ;
b110 $
b1111 '
b1110 &
b1110 -
b1110 4
b1110 6
b10011 0
b10011 7
b10011 :
b1110 +
b1110 9
#97
b0 "
b0 .
b0 ;
b10 #
b10 /
b10 <
b0 '
b110 %
b110 ,
b110 1
b110 3
b10100 0
b10100 7
b10100 :
b110 *
b110 8
#98
0!
05
0)
b110 "
b110 .
b110 ;
b0 #
b0 /
b0 <
b1 '
b0 &
b0 -
b0 4
b0 6
b110 0
b110 7
b110 :
b0 +
b0 9
#99
b111 "
b111 .
b111 ;
b10 '
b1 &
b1 -
b1 4
b1 6
b111 0
b111 7
b111 :
b1 +
b1 9
#100
b1000 "
b1000 .
b1000 ;
b11 '
b10 &
b10 -
b10 4
b10 6
b1000 0
b1000 7
b1000 :
b10 +
b10 9
#101
b1001 "
b1001 .
b1001 ;
b100 '
b11 &
b11 -
b11 4
b11 6
b1001 0
b1001 7
b1001 :
b11 +
b11 9
#102
b0 "
b0 .
b0 ;
b1 #
b1 /
b1 <
b101 '
b100 &
b100 -
b100 4
b100 6
b1010 0
b1010 7
b1010 :
b100 +
b100 9
#103
b1 "
b1 .
b1 ;
b110 '
b101 &
b101 -
b101 4
b101 6
b1011 0
b1011 7
b1011 :
b101 +
b101 9
#104
b10 "
b10 .
b10 ;
b111 '
b110 &
b110 -
b110 4
b110 6
b1100 0
b1100 7
b1100 :
b110 +
b110 9
#105
b11 "
b11 .
b11 ;
b1000 '
b111 &
b111 -
b111 4
b111 6
b1101 0
b1101 7
b1101 :
b111 +
b111 9
#106
b100 "
b100 .
b100 ;
b1001 '
b1000 &
b1000 -
b1000 4
b1000 6
b1110 0
b1110 7
b1110 :
b1000 +
b1000 9
#107
b101 "
b101 .
b101 ;
b1010 '
b1001 &
b1001 -
b1001 4
b1001 6
b1111 0
b1111 7
b1111 :
b1001 +
b1001 9
#108
1!
15
1)
b110 "
b110 .
b110 ;
b1011 '
b1010 &
b1010 -
b1010 4
b1010 6
b10000 0
b10000 7
b10000 :
b1010 +
b1010 9
#109
b111 "
b111 .
b111 ;
b1100 '
b1011 &
b1011 -
b1011 4
b1011 6
b10001 0
b10001 7
b10001 :
b1011 +
b1011 9
#110
b1000 "
b1000 .
b1000 ;
b1101 '
b1100 &
b1100 -
b1100 4
b1100 6
b10010 0
b10010 7
b10010 :
b1100 +
b1100 9
#111
b1001 "
b1001 .
b1001 ;
b1110 '
b1101 &
b1101 -
b1101 4
b1101 6
b10011 0
b10011 7
b10011 :
b1101 +
b1101 9
#112
b0 "
b0 .
b0 ;
b10 #
b10 /
b10 <
b111 $
b1111 '
b1110 &
b1110 -
b1110 4
b1110 6
b10100 0
b10100 7
b10100 :
b1110 +
b1110 9
#113
b1 "
b1 .
b1 ;
b0 '
b111 %
b111 ,
b111 1
b111 3
b10101 0
b10101 7
b10101 :
b111 *
b111 8
#114
0!
05
0)
b111 "
b111 .
b111 ;
b0 #
b0 /
b0 <
b1 '
b0 &
b0 -
b0 4
b0 6
b111 0
b111 7
b111 :
b0 +
b0 9
#115
b1000 "
b1000 .
b1000 ;
b10 '
b1 &
b1 -
b1 4
b1 6
b1000 0
b1000 7
b1000 :
b1 +
b1 9
#116
b1001 "
b1001 .
b1001 ;
b11 '
b10 &
b10 -
b10 4
b10 6
b1001 0
b1001 7
b1001 :
b10 +
b10 9
#117
b0 "
b0 .
b0 ;
b1 #
b1 /
b1 <
b100 '
b11 &
b11 -
b11 4
b11 6
b1010 0
b1010 7
b1010 :
b11 +
b11 9
#118
b1 "
b1 .
b1 ;
b101 '
b100 &
b100 -
b100 4
b100 6
b1011 0
b1011 7
b1011 :
b100 +
b100 9
#119
b10 "
b10 .
b10 ;
b110 '
b101 &
b101 -
b101 4
b101 6
b1100 0
b1100 7
b1100 :
b101 +
b101 9
#120
b11 "
b11 .
b11 ;
b111 '
b110 &
b110 -
b110 4
b110 6
b1101 0
b1101 7
b1101 :
b110 +
b110 9
#121
b100 "
b100 .
b100 ;
b1000 '
b111 &
b111 -
b111 4
b111 6
b1110 0
b1110 7
b1110 :
b111 +
b111 9
#122
b101 "
b101 .
b101 ;
b1001 '
b1000 &
b1000 -
b1000 4
b1000 6
b1111 0
b1111 7
b1111 :
b1000 +
b1000 9
#123
b110 "
b110 .
b110 ;
b1010 '
b1001 &
b1001 -
b1001 4
b1001 6
b10000 0
b10000 7
b10000 :
b1001 +
b1001 9
#124
1!
15
1)
b111 "
b111 .
b111 ;
b1011 '
b1010 &
b1010 -
b1010 4
b1010 6
b10001 0
b10001 7
b10001 :
b1010 +
b1010 9
#125
b1000 "
b1000 .
b1000 ;
b1100 '
b1011 &
b1011 -
b1011 4
b1011 6
b10010 0
b10010 7
b10010 :
b1011 +
b1011 9
#126
b1001 "
b1001 .
b1001 ;
b1101 '
b1100 &
b1100 -
b1100 4
b1100 6
b10011 0
b10011 7
b10011 :
b1100 +
b1100 9
#127
b0 "
b0 .
b0 ;
b10 #
b10 /
b10 <
b1110 '
b1101 &
b1101 -
b1101 4
b1101 6
b10100 0
b10100 7
b10100 :
b1101 +
b1101 9
#128
b1 "
b1 .
b1 ;
b1000 $
b1111 '
b1110 &
b1110 -
b1110 4
b1110 6
b10101 0
b10101 7
b10101 :
b1110 +
b1110 9
#129
b10 "
b10 .
b10 ;
b0 '
b1000 %
b1000 ,
b1000 1
b1000 3
b10110 0
b10110 7
b10110 :
b1000 *
b1000 8
#130
0!
05
0)
b1000 "
b1000 .
b1000 ;
b0 #
b0 /
b0 <
b1 '
b0 &
b0 -
b0 4
b0 6
b1000 0
b1000 7
b1000 :
b0 +
b0 9
#131
b1001 "
b1001 .
b1001 ;
b10 '
b1 &
b1 -
b1 4
b1 6
b1001 0
b1001 7
b1001 :
b1 +
b1 9
#132
b0 "
b0 .
b0 ;
b1 #
b1 /
b1 <
b11 '
b10 &
b10 -
b10 4
b10 6
b1010 0
b1010 7
b1010 :
b10 +
b10 9
#133
b1 "
b1 .
b1 ;
b100 '
b11 &
b11 -
b11 4
b11 6
b1011 0
b1011 7
b1011 :
b11 +
b11 9
#134
b10 "
b10 .
b10 ;
b101 '
b100 &
b100 -
b100 4
b100 6
b1100 0
b1100 7
b1100 :
b100 +
b100 9
#135
b11 "
b11 .
b11 ;
b110 '
b101 &
b101 -
b101 4
b101 6
b1101 0
b1101 7
b1101 :
b101 +
b101 9
#136
b100 "
b100 .
b100 ;
b111 '
b110 &
b110 -
b110 4
b110 6
b1110 0
b1110 7
b1110 :
b110 +
b110 9
#137
b101 "
b101 .
b101 ;
b1000 '
b111 &
b111 -
b111 4
b111 6
b1111 0
b1111 7
b1111 :
b111 +
b111 9
#138
b110 "
b110 .
b110 ;
b1001 '
b1000 &
b1000 -
b1000 4
b1000 6
b10000 0
b10000 7
b10000 :
b1000 +
b1000 9
#139
b111 "
b111 .
b111 ;
b1010 '
b1001 &
b1001 -
b1001 4
b1001 6
b10001 0
b10001 7
b10001 :
b1001 +
b1001 9
#140
1!
15
1)
b1000 "
b1000 .
b1000 ;
b1011 '
b1010 &
b1010 -
b1010 4
b1010 6
b10010 0
b10010 7
b10010 :
b1010 +
b1010 9
#141
b1001 "
b1001 .
b1001 ;
b1100 '
b1011 &
b1011 -
b1011 4
b1011 6
b10011 0
b10011 7
b10011 :
b1011 +
b1011 9
#142
b0 "
b0 .
b0 ;
b10 #
b10 /
b10 <
b1101 '
b1100 &
b1100 -
b1100 4
b1100 6
b10100 0
b10100 7
b10100 :
b1100 +
b1100 9
#143
b1 "
b1 .
b1 ;
b1110 '
b1101 &
b1101 -
b1101 4
b1101 6
b10101 0
b10101 7
b10101 :
b1101 +
b1101 9
#144
b10 "
b10 .
b10 ;
b1001 $
b1111 '
b1110 &
b1110 -
b1110 4
b1110 6
b10110 0
b10110 7
b10110 :
b1110 +
b1110 9
#145
b11 "
b11 .
b11 ;
b0 '
b1001 %
b1001 ,
b1001 1
b1001 3
b10111 0
b10111 7
b10111 :
b1001 *
b1001 8
#146
0!
05
0)
b1001 "
b1001 .
b1001 ;
b0 #
b0 /
b0 <
b1 '
b0 &
b0 -
b0 4
b0 6
b1001 0
b1001 7
b1001 :
b0 +
b0 9
#147
b0 "
b0 .
b0 ;
b1 #
b1 /
b1 <
b10 '
b1 &
b1 -
b1 4
b1 6
b1010 0
b1010 7
b1010 :
b1 +
b1 9
#148
b1 "
b1 .
b1 ;
b11 '
b10 &
b10 -
b10 4
b10 6
b1011 0
b1011 7
b1011 :
b10 +
b10 9
#149
b10 "
b10 .
b10 ;
b100 '
b11 &
b11 -
b11 4
b11 6
b1100 0
b1100 7
b1100 :
b11 +
b11 9
#150
b11 "
b11 .
b11 ;
b101 '
b100 &
b100 -
b100 4
b100 6
b1101 0
b1101 7
b1101 :
b100 +
b100 9
#151
b100 "
b100 .
b100 ;
b110 '
b101 &
b101 -
b101 4
b101 6
b1110 0
b1110 7
b1110 :
b101 +
b101 9
#152
b101 "
b101 .
b101 ;
b111 '
b110 &
b110 -
b110 4
b110 6
b1111 0
b1111 7
b1111 :
b110 +
b110 9
#153
b110 "
b110 .
b110 ;
b1000 '
b111 &
b111 -
b111 4
b111 6
b10000 0
b10000 7
b10000 :
b111 +
b111 9
#154
b111 "
b111 .
b111 ;
b1001 '
b1000 &
b1000 -
b1000 4
b1000 6
b10001 0
b10001 7
b10001 :
b1000 +
b1000 9
#155
b1000 "
b1000 .
b1000 ;
b1010 '
b1001 &
b1001 -
b1001 4
b1001 6
b10010 0
b10010 7
b10010 :
b1001 +
b1001 9
#156
1!
15
1)
b1001 "
b1001 .
b1001 ;
b1011 '
b1010 &
b1010 -
b1010 4
b1010 6
b10011 0
b10011 7
b10011 :
b1010 +
b1010 9
#157
b0 "
b0 .
b0 ;
b10 #
b10 /
b10 <
b1100 '
b1011 &
b1011 -
b1011 4
b1011 6
b10100 0
b10100 7
b10100 :
b1011 +
b1011 9
#158
b1 "
b1 .
b1 ;
b1101 '
b1100 &
b1100 -
b1100 4
b1100 6
b10101 0
b10101 7
b10101 :
b1100 +
b1100 9
#159
b10 "
b10 .
b10 ;
b1110 '
b1101 &
b1101 -
b1101 4
b1101 6
b10110 0
b10110 7
b10110 :
b1101 +
b1101 9
#160
b11 "
b11 .
b11 ;
b1010 $
b1111 '
b1110 &
b1110 -
b1110 4
b1110 6
b10111 0
b10111 7
b10111 :
b1110 +
b1110 9
#161
12
1(
b100 "
b100 .
b100 ;
b0 '
b1010 %
b1010 ,
b1010 1
b1010 3
b11000 0
b11000 7
b11000 :
b1010 *
b1010 8
#162
05
0)
b0 "
b0 .
b0 ;
b1 #
b1 /
b1 <
b1 '
b0 &
b0 -
b0 4
b0 6
b1010 0
b1010 7
b1010 :
b0 +
b0 9
