E5TP1/sum4bit.v
module sum4bit(
    x0, //Sumando 0 (4-bit)
    x1, //Sumando 1 (4-bit)
    o   //Resultado (5-bit)
);

//Definiendo Inputs
input [3:0] x0, x1; //Sumandos

//Definiendo Outputs
output [4:0] o;   //Resultado

//Definiendo los tipos de dato
wire [3:0] x0, x1;
wire [4:0] o;

assign o = x0 + x1;

endmodule

E5TP1/sum4bit_tb.v
`include "sum4bit.v"

module sum4bit_tb;

//Defining test variables
reg [3:0] in0, in1, i, j;
wire [4:0] out;

//Connecting the ports
sum4bit sum_udt(.x0(in0), .x1(in1), .o(out));

//Code
initial begin
  $dumpfile("sum4bit.vcd");
  $dumpvars;
end

initial begin
  in0 = 0;
  in1 = 0;
  $display("In0\t+\tIn1\t=\tOut");
  $monitor("%d\t%d\t%d", in0, in1, out);
end


always begin
for (i = 0; i<15 ; i = i+1) begin
    #1 in0 = i;
    for (j=0; j<15; j = j+1) begin
      #1in1 = j;
    end
end
#20$finish;
end



endmodule

E5TP1/sum4bit.vcd
$date
	Wed Aug 22 01:24:07 2018
$end
$version
	Icarus Verilog
$end
$timescale
	1s
$end
$scope module sum4bit_tb $end
$var wire 5 ! out [4:0] $end
$var reg 4 " i [3:0] $end
$var reg 4 # in0 [3:0] $end
$var reg 4 $ in1 [3:0] $end
$var reg 4 % j [3:0] $end
$scope module sum_udt $end
$var wire 5 & o [4:0] $end
$var wire 4 ' x0 [3:0] $end
$var wire 4 ( x1 [3:0] $end
$upscope $end
$upscope $end
$enddefinitions $end
#0
$dumpvars
b0 (
b0 '
b0 &
bx %
b0 $
b0 #
b0 "
b0 !
$end
#1
b0 %
#2
b1 %
#3
b10 %
b1 $
b1 (
b1 !
b1 &
#4
b11 %
b10 $
b10 (
b10 !
b10 &
#5
b100 %
b11 $
b11 (
b11 !
b11 &
#6
b101 %
b100 $
b100 (
b100 !
b100 &
#7
b110 %
b101 $
b101 (
b101 !
b101 &
#8
b111 %
b110 $
b110 (
b110 !
b110 &
#9
b1000 %
b111 $
b111 (
b111 !
b111 &
#10
b1001 %
b1000 $
b1000 (
b1000 !
b1000 &
#11
b1010 %
b1001 $
b1001 (
b1001 !
b1001 &
#12
b1011 %
b1010 $
b1010 (
b1010 !
b1010 &
#13
b1100 %
b1011 $
b1011 (
b1011 !
b1011 &
#14
b1101 %
b1100 $
b1100 (
b1100 !
b1100 &
#15
b1110 %
b1101 $
b1101 (
b1101 !
b1101 &
#16
b1 "
b1111 %
b1110 $
b1110 (
b1110 !
b1110 &
#17
b0 %
b1 #
b1 '
b1111 !
b1111 &
#18
b1 %
b0 $
b0 (
b1 !
b1 &
#19
b10 %
b1 $
b1 (
b10 !
b10 &
#20
b11 %
b10 $
b10 (
b11 !
b11 &
#21
b100 %
b11 $
b11 (
b100 !
b100 &
#22
b101 %
b100 $
b100 (
b101 !
b101 &
#23
b110 %
b101 $
b101 (
b110 !
b110 &
#24
b111 %
b110 $
b110 (
b111 !
b111 &
#25
b1000 %
b111 $
b111 (
b1000 !
b1000 &
#26
b1001 %
b1000 $
b1000 (
b1001 !
b1001 &
#27
b1010 %
b1001 $
b1001 (
b1010 !
b1010 &
#28
b1011 %
b1010 $
b1010 (
b1011 !
b1011 &
#29
b1100 %
b1011 $
b1011 (
b1100 !
b1100 &
#30
b1101 %
b1100 $
b1100 (
b1101 !
b1101 &
#31
b1110 %
b1101 $
b1101 (
b1110 !
b1110 &
#32
b10 "
b1111 %
b1110 $
b1110 (
b1111 !
b1111 &
#33
b0 %
b10 #
b10 '
b10000 !
b10000 &
#34
b1 %
b0 $
b0 (
b10 !
b10 &
#35
b10 %
b1 $
b1 (
b11 !
b11 &
#36
b11 %
b10 $
b10 (
b100 !
b100 &
#37
b100 %
b11 $
b11 (
b101 !
b101 &
#38
b101 %
b100 $
b100 (
b110 !
b110 &
#39
b110 %
b101 $
b101 (
b111 !
b111 &
#40
b111 %
b110 $
b110 (
b1000 !
b1000 &
#41
b1000 %
b111 $
b111 (
b1001 !
b1001 &
#42
b1001 %
b1000 $
b1000 (
b1010 !
b1010 &
#43
b1010 %
b1001 $
b1001 (
b1011 !
b1011 &
#44
b1011 %
b1010 $
b1010 (
b1100 !
b1100 &
#45
b1100 %
b1011 $
b1011 (
b1101 !
b1101 &
#46
b1101 %
b1100 $
b1100 (
b1110 !
b1110 &
#47
b1110 %
b1101 $
b1101 (
b1111 !
b1111 &
#48
b11 "
b1111 %
b1110 $
b1110 (
b10000 !
b10000 &
#49
b0 %
b11 #
b11 '
b10001 !
b10001 &
#50
b1 %
b0 $
b0 (
b11 !
b11 &
#51
b10 %
b1 $
b1 (
b100 !
b100 &
#52
b11 %
b10 $
b10 (
b101 !
b101 &
#53
b100 %
b11 $
b11 (
b110 !
b110 &
#54
b101 %
b100 $
b100 (
b111 !
b111 &
#55
b110 %
b101 $
b101 (
b1000 !
b1000 &
#56
b111 %
b110 $
b110 (
b1001 !
b1001 &
#57
b1000 %
b111 $
b111 (
b1010 !
b1010 &
#58
b1001 %
b1000 $
b1000 (
b1011 !
b1011 &
#59
b1010 %
b1001 $
b1001 (
b1100 !
b1100 &
#60
b1011 %
b1010 $
b1010 (
b1101 !
b1101 &
#61
b1100 %
b1011 $
b1011 (
b1110 !
b1110 &
#62
b1101 %
b1100 $
b1100 (
b1111 !
b1111 &
#63
b1110 %
b1101 $
b1101 (
b10000 !
b10000 &
#64
b100 "
b1111 %
b1110 $
b1110 (
b10001 !
b10001 &
#65
b0 %
b100 #
b100 '
b10010 !
b10010 &
#66
b1 %
b0 $
b0 (
b100 !
b100 &
#67
b10 %
b1 $
b1 (
b101 !
b101 &
#68
b11 %
b10 $
b10 (
b110 !
b110 &
#69
b100 %
b11 $
b11 (
b111 !
b111 &
#70
b101 %
b100 $
b100 (
b1000 !
b1000 &
#71
b110 %
b101 $
b101 (
b1001 !
b1001 &
#72
b111 %
b110 $
b110 (
b1010 !
b1010 &
#73
b1000 %
b111 $
b111 (
b1011 !
b1011 &
#74
b1001 %
b1000 $
b1000 (
b1100 !
b1100 &
#75
b1010 %
b1001 $
b1001 (
b1101 !
b1101 &
#76
b1011 %
b1010 $
b1010 (
b1110 !
b1110 &
#77
b1100 %
b1011 $
b1011 (
b1111 !
b1111 &
#78
b1101 %
b1100 $
b1100 (
b10000 !
b10000 &
#79
b1110 %
b1101 $
b1101 (
b10001 !
b10001 &
#80
b101 "
b1111 %
b1110 $
b1110 (
b10010 !
b10010 &
#81
b0 %
b101 #
b101 '
b10011 !
b10011 &
#82
b1 %
b0 $
b0 (
b101 !
b101 &
#83
b10 %
b1 $
b1 (
b110 !
b110 &
#84
b11 %
b10 $
b10 (
b111 !
b111 &
#85
b100 %
b11 $
b11 (
b1000 !
b1000 &
#86
b101 %
b100 $
b100 (
b1001 !
b1001 &
#87
b110 %
b101 $
b101 (
b1010 !
b1010 &
#88
b111 %
b110 $
b110 (
b1011 !
b1011 &
#89
b1000 %
b111 $
b111 (
b1100 !
b1100 &
#90
b1001 %
b1000 $
b1000 (
b1101 !
b1101 &
#91
b1010 %
b1001 $
b1001 (
b1110 !
b1110 &
#92
b1011 %
b1010 $
b1010 (
b1111 !
b1111 &
#93
b1100 %
b1011 $
b1011 (
b10000 !
b10000 &
#94
b1101 %
b1100 $
b1100 (
b10001 !
b10001 &
#95
b1110 %
b1101 $
b1101 (
b10010 !
b10010 &
#96
b110 "
b1111 %
b1110 $
b1110 (
b10011 !
b10011 &
#97
b0 %
b110 #
b110 '
b10100 !
b10100 &
#98
b1 %
b0 $
b0 (
b110 !
b110 &
#99
b10 %
b1 $
b1 (
b111 !
b111 &
#100
b11 %
b10 $
b10 (
b1000 !
b1000 &
#101
b100 %
b11 $
b11 (
b1001 !
b1001 &
#102
b101 %
b100 $
b100 (
b1010 !
b1010 &
#103
b110 %
b101 $
b101 (
b1011 !
b1011 &
#104
b111 %
b110 $
b110 (
b1100 !
b1100 &
#105
b1000 %
b111 $
b111 (
b1101 !
b1101 &
#106
b1001 %
b1000 $
b1000 (
b1110 !
b1110 &
#107
b1010 %
b1001 $
b1001 (
b1111 !
b1111 &
#108
b1011 %
b1010 $
b1010 (
b10000 !
b10000 &
#109
b1100 %
b1011 $
b1011 (
b10001 !
b10001 &
#110
b1101 %
b1100 $
b1100 (
b10010 !
b10010 &
#111
b1110 %
b1101 $
b1101 (
b10011 !
b10011 &
#112
b111 "
b1111 %
b1110 $
b1110 (
b10100 !
b10100 &
#113
b0 %
b111 #
b111 '
b10101 !
b10101 &
#114
b1 %
b0 $
b0 (
b111 !
b111 &
#115
b10 %
b1 $
b1 (
b1000 !
b1000 &
#116
b11 %
b10 $
b10 (
b1001 !
b1001 &
#117
b100 %
b11 $
b11 (
b1010 !
b1010 &
#118
b101 %
b100 $
b100 (
b1011 !
b1011 &
#119
b110 %
b101 $
b101 (
b1100 !
b1100 &
#120
b111 %
b110 $
b110 (
b1101 !
b1101 &
#121
b1000 %
b111 $
b111 (
b1110 !
b1110 &
#122
b1001 %
b1000 $
b1000 (
b1111 !
b1111 &
#123
b1010 %
b1001 $
b1001 (
b10000 !
b10000 &
#124
b1011 %
b1010 $
b1010 (
b10001 !
b10001 &
#125
b1100 %
b1011 $
b1011 (
b10010 !
b10010 &
#126
b1101 %
b1100 $
b1100 (
b10011 !
b10011 &
#127
b1110 %
b1101 $
b1101 (
b10100 !
b10100 &
#128
b1000 "
b1111 %
b1110 $
b1110 (
b10101 !
b10101 &
#129
b0 %
b1000 #
b1000 '
b10110 !
b10110 &
#130
b1 %
b0 $
b0 (
b1000 !
b1000 &
#131
b10 %
b1 $
b1 (
b1001 !
b1001 &
#132
b11 %
b10 $
b10 (
b1010 !
b1010 &
#133
b100 %
b11 $
b11 (
b1011 !
b1011 &
#134
b101 %
b100 $
b100 (
b1100 !
b1100 &
#135
b110 %
b101 $
b101 (
b1101 !
b1101 &
#136
b111 %
b110 $
b110 (
b1110 !
b1110 &
#137
b1000 %
b111 $
b111 (
b1111 !
b1111 &
#138
b1001 %
b1000 $
b1000 (
b10000 !
b10000 &
#139
b1010 %
b1001 $
b1001 (
b10001 !
b10001 &
#140
b1011 %
b1010 $
b1010 (
b10010 !
b10010 &
#141
b1100 %
b1011 $
b1011 (
b10011 !
b10011 &
#142
b1101 %
b1100 $
b1100 (
b10100 !
b10100 &
#143
b1110 %
b1101 $
b1101 (
b10101 !
b10101 &
#144
b1001 "
b1111 %
b1110 $
b1110 (
b10110 !
b10110 &
#145
b0 %
b1001 #
b1001 '
b10111 !
b10111 &
#146
b1 %
b0 $
b0 (
b1001 !
b1001 &
#147
b10 %
b1 $
b1 (
b1010 !
b1010 &
#148
b11 %
b10 $
b10 (
b1011 !
b1011 &
#149
b100 %
b11 $
b11 (
b1100 !
b1100 &
#150
b101 %
b100 $
b100 (
b1101 !
b1101 &
#151
b110 %
b101 $
b101 (
b1110 !
b1110 &
#152
b111 %
b110 $
b110 (
b1111 !
b1111 &
#153
b1000 %
b111 $
b111 (
b10000 !
b10000 &
#154
b1001 %
b1000 $
b1000 (
b10001 !
b10001 &
#155
b1010 %
b1001 $
b1001 (
b10010 !
b10010 &
#156
b1011 %
b1010 $
b1010 (
b10011 !
b10011 &
#157
b1100 %
b1011 $
b1011 (
b10100 !
b10100 &
#158
b1101 %
b1100 $
b1100 (
b10101 !
b10101 &
#159
b1110 %
b1101 $
b1101 (
b10110 !
b10110 &
#160
b1010 "
b1111 %
b1110 $
b1110 (
b10111 !
b10111 &
#161
b0 %
b1010 #
b1010 '
b11000 !
b11000 &
#162
b1 %
b0 $
b0 (
b1010 !
b1010 &
#163
b10 %
b1 $
b1 (
b1011 !
b1011 &
#164
b11 %
b10 $
b10 (
b1100 !
b1100 &
#165
b100 %
b11 $
b11 (
b1101 !
b1101 &
#166
b101 %
b100 $
b100 (
b1110 !
b1110 &
#167
b110 %
b101 $
b101 (
b1111 !
b1111 &
#168
b111 %
b110 $
b110 (
b10000 !
b10000 &
#169
b1000 %
b111 $
b111 (
b10001 !
b10001 &
#170
b1001 %
b1000 $
b1000 (
b10010 !
b10010 &
#171
b1010 %
b1001 $
b1001 (
b10011 !
b10011 &
#172
b1011 %
b1010 $
b1010 (
b10100 !
b10100 &
#173
b1100 %
b1011 $
b1011 (
b10101 !
b10101 &
#174
b1101 %
b1100 $
b1100 (
b10110 !
b10110 &
#175
b1110 %
b1101 $
b1101 (
b10111 !
b10111 &
#176
b1011 "
b1111 %
b1110 $
b1110 (
b11000 !
b11000 &
#177
b0 %
b1011 #
b1011 '
b11001 !
b11001 &
#178
b1 %
b0 $
b0 (
b1011 !
b1011 &
#179
b10 %
b1 $
b1 (
b1100 !
b1100 &
#180
b11 %
b10 $
b10 (
b1101 !
b1101 &
#181
b100 %
b11 $
b11 (
b1110 !
b1110 &
#182
b101 %
b100 $
b100 (
b1111 !
b1111 &
#183
b110 %
b101 $
b101 (
b10000 !
b10000 &
#184
b111 %
b110 $
b110 (
b10001 !
b10001 &
#185
b1000 %
b111 $
b111 (
b10010 !
b10010 &
#186
b1001 %
b1000 $
b1000 (
b10011 !
b10011 &
#187
b1010 %
b1001 $
b1001 (
b10100 !
b10100 &
#188
b1011 %
b1010 $
b1010 (
b10101 !
b10101 &
#189
b1100 %
b1011 $
b1011 (
b10110 !
b10110 &
#190
b1101 %
b1100 $
b1100 (
b10111 !
b10111 &
#191
b1110 %
b1101 $
b1101 (
b11000 !
b11000 &
#192
b1100 "
b1111 %
b1110 $
b1110 (
b11001 !
b11001 &
#193
b0 %
b1100 #
b1100 '
b11010 !
b11010 &
#194
b1 %
b0 $
b0 (
b1100 !
b1100 &
#195
b10 %
b1 $
b1 (
b1101 !
b1101 &
#196
b11 %
b10 $
b10 (
b1110 !
b1110 &
#197
b100 %
b11 $
b11 (
b1111 !
b1111 &
#198
b101 %
b100 $
b100 (
b10000 !
b10000 &
#199
b110 %
b101 $
b101 (
b10001 !
b10001 &
#200
b111 %
b110 $
b110 (
b10010 !
b10010 &
#201
b1000 %
b111 $
b111 (
b10011 !
b10011 &
#202
b1001 %
b1000 $
b1000 (
b10100 !
b10100 &
#203
b1010 %
b1001 $
b1001 (
b10101 !
b10101 &
#204
b1011 %
b1010 $
b1010 (
b10110 !
b10110 &
#205
b1100 %
b1011 $
b1011 (
b10111 !
b10111 &
#206
b1101 %
b1100 $
b1100 (
b11000 !
b11000 &
#207
b1110 %
b1101 $
b1101 (
b11001 !
b11001 &
#208
b1101 "
b1111 %
b1110 $
b1110 (
b11010 !
b11010 &
#209
b0 %
b1101 #
b1101 '
b11011 !
b11011 &
#210
b1 %
b0 $
b0 (
b1101 !
b1101 &
#211
b10 %
b1 $
b1 (
b1110 !
b1110 &
#212
b11 %
b10 $
b10 (
b1111 !
b1111 &
#213
b100 %
b11 $
b11 (
b10000 !
b10000 &
#214
b101 %
b100 $
b100 (
b10001 !
b10001 &
#215
b110 %
b101 $
b101 (
b10010 !
b10010 &
#216
b111 %
b110 $
b110 (
b10011 !
b10011 &
#217
b1000 %
b111 $
b111 (
b10100 !
b10100 &
#218
b1001 %
b1000 $
b1000 (
b10101 !
b10101 &
#219
b1010 %
b1001 $
b1001 (
b10110 !
b10110 &
#220
b1011 %
b1010 $
b1010 (
b10111 !
b10111 &
#221
b1100 %
b1011 $
b1011 (
b11000 !
b11000 &
#222
b1101 %
b1100 $
b1100 (
b11001 !
b11001 &
#223
b1110 %
b1101 $
b1101 (
b11010 !
b11010 &
#224
b1110 "
b1111 %
b1110 $
b1110 (
b11011 !
b11011 &
#225
b0 %
b1110 #
b1110 '
b11100 !
b11100 &
#226
b1 %
b0 $
b0 (
b1110 !
b1110 &
#227
b10 %
b1 $
b1 (
b1111 !
b1111 &
#228
b11 %
b10 $
b10 (
b10000 !
b10000 &
#229
b100 %
b11 $
b11 (
b10001 !
b10001 &
#230
b101 %
b100 $
b100 (
b10010 !
b10010 &
#231
b110 %
b101 $
b101 (
b10011 !
b10011 &
#232
b111 %
b110 $
b110 (
b10100 !
b10100 &
#233
b1000 %
b111 $
b111 (
b10101 !
b10101 &
#234
b1001 %
b1000 $
b1000 (
b10110 !
b10110 &
#235
b1010 %
b1001 $
b1001 (
b10111 !
b10111 &
#236
b1011 %
b1010 $
b1010 (
b11000 !
b11000 &
#237
b1100 %
b1011 $
b1011 (
b11001 !
b11001 &
#238
b1101 %
b1100 $
b1100 (
b11010 !
b11010 &
#239
b1110 %
b1101 $
b1101 (
b11011 !
b11011 &
#240
b1111 "
b1111 %
b1110 $
b1110 (
b11100 !
b11100 &
