E5TP1/sum4bit.v
module sum4bit(
    x0, //Sumando 0 (4-bit)
    x1, //Sumando 1 (4-bit)
    o   //Resultado (5-bit)
);

input wire [3:0] x0, x1;
output reg [4:0] o;

initial begin
  o = 0;
end

always @(x0 or x1) begin
  o = x0 + x1;
end


endmodule

E5TP1/src/sum4bit/sum4bit_tb.v
`include "src/sum4bit/sum4bit.v"

module sum4bit_tb;

//Defining test variables
reg [3:0] in0, in1;
reg [4:0] i, j;
wire [4:0] out;

//Connecting the ports
sum4bit sum_udt(
  .x0(in0),
  .x1(in1),
  .o(out)
  );

//Code
initial begin
  $dumpfile("sum4bit.vcd");
  $dumpvars;
end

initial begin
  in0 = 0;
  in1 = 0;
  $display("4-bit adder Testbench");
  $display("In0\t+\tIn1\t=\tOut");
  $monitor("%d\t\t%d\t\t%d", in0, in1, out);
end

always begin
for (i = 0; i<16 ; i = i+1) begin
  for (j=0; j<16; j = j+1) begin
    in0 = i[3:0];
    in1 = j[3:0];
    #1;
  end
end
#20$finish;
end

endmodule

E5TP1/sum4bit.vcd
$date
	Mon Sep  3 22:25:05 2018
$end
$version
	Icarus Verilog
$end
$timescale
	1s
$end
$scope module sum4bit_tb $end
$var wire 5 ! out [4:0] $end
$var reg 5 " i [4:0] $end
$var reg 4 # in0 [3:0] $end
$var reg 4 $ in1 [3:0] $end
$var reg 5 % j [4:0] $end
$scope module sum_udt $end
$var wire 5 & o [4:0] $end
$var wire 4 ' x0 [3:0] $end
$var wire 4 ( x1 [3:0] $end
$upscope $end
$upscope $end
$enddefinitions $end
#0
$dumpvars
b0 (
b0 '
b0 &
b0 %
b0 $
b0 #
b0 "
b0 !
$end
#1
b1 $
b1 (
b1 !
b1 &
b1 %
#2
b10 $
b10 (
b10 !
b10 &
b10 %
#3
b11 $
b11 (
b11 !
b11 &
b11 %
#4
b100 $
b100 (
b100 !
b100 &
b100 %
#5
b101 $
b101 (
b101 !
b101 &
b101 %
#6
b110 $
b110 (
b110 !
b110 &
b110 %
#7
b111 $
b111 (
b111 !
b111 &
b111 %
#8
b1000 $
b1000 (
b1000 !
b1000 &
b1000 %
#9
b1001 $
b1001 (
b1001 !
b1001 &
b1001 %
#10
b1010 $
b1010 (
b1010 !
b1010 &
b1010 %
#11
b1011 $
b1011 (
b1011 !
b1011 &
b1011 %
#12
b1100 $
b1100 (
b1100 !
b1100 &
b1100 %
#13
b1101 $
b1101 (
b1101 !
b1101 &
b1101 %
#14
b1110 $
b1110 (
b1110 !
b1110 &
b1110 %
#15
b1111 $
b1111 (
b1111 !
b1111 &
b1111 %
#16
b0 $
b0 (
b1 #
b1 '
b1 !
b1 &
b1 "
b0 %
#17
b1 $
b1 (
b10 !
b10 &
b1 %
#18
b10 $
b10 (
b11 !
b11 &
b10 %
#19
b11 $
b11 (
b100 !
b100 &
b11 %
#20
b100 $
b100 (
b101 !
b101 &
b100 %
#21
b101 $
b101 (
b110 !
b110 &
b101 %
#22
b110 $
b110 (
b111 !
b111 &
b110 %
#23
b111 $
b111 (
b1000 !
b1000 &
b111 %
#24
b1000 $
b1000 (
b1001 !
b1001 &
b1000 %
#25
b1001 $
b1001 (
b1010 !
b1010 &
b1001 %
#26
b1010 $
b1010 (
b1011 !
b1011 &
b1010 %
#27
b1011 $
b1011 (
b1100 !
b1100 &
b1011 %
#28
b1100 $
b1100 (
b1101 !
b1101 &
b1100 %
#29
b1101 $
b1101 (
b1110 !
b1110 &
b1101 %
#30
b1110 $
b1110 (
b1111 !
b1111 &
b1110 %
#31
b1111 $
b1111 (
b10000 !
b10000 &
b1111 %
#32
b0 $
b0 (
b10 #
b10 '
b10 !
b10 &
b10 "
b0 %
#33
b1 $
b1 (
b11 !
b11 &
b1 %
#34
b10 $
b10 (
b100 !
b100 &
b10 %
#35
b11 $
b11 (
b101 !
b101 &
b11 %
#36
b100 $
b100 (
b110 !
b110 &
b100 %
#37
b101 $
b101 (
b111 !
b111 &
b101 %
#38
b110 $
b110 (
b1000 !
b1000 &
b110 %
#39
b111 $
b111 (
b1001 !
b1001 &
b111 %
#40
b1000 $
b1000 (
b1010 !
b1010 &
b1000 %
#41
b1001 $
b1001 (
b1011 !
b1011 &
b1001 %
#42
b1010 $
b1010 (
b1100 !
b1100 &
b1010 %
#43
b1011 $
b1011 (
b1101 !
b1101 &
b1011 %
#44
b1100 $
b1100 (
b1110 !
b1110 &
b1100 %
#45
b1101 $
b1101 (
b1111 !
b1111 &
b1101 %
#46
b1110 $
b1110 (
b10000 !
b10000 &
b1110 %
#47
b1111 $
b1111 (
b10001 !
b10001 &
b1111 %
#48
b0 $
b0 (
b11 #
b11 '
b11 !
b11 &
b11 "
b0 %
#49
b1 $
b1 (
b100 !
b100 &
b1 %
#50
b10 $
b10 (
b101 !
b101 &
b10 %
#51
b11 $
b11 (
b110 !
b110 &
b11 %
#52
b100 $
b100 (
b111 !
b111 &
b100 %
#53
b101 $
b101 (
b1000 !
b1000 &
b101 %
#54
b110 $
b110 (
b1001 !
b1001 &
b110 %
#55
b111 $
b111 (
b1010 !
b1010 &
b111 %
#56
b1000 $
b1000 (
b1011 !
b1011 &
b1000 %
#57
b1001 $
b1001 (
b1100 !
b1100 &
b1001 %
#58
b1010 $
b1010 (
b1101 !
b1101 &
b1010 %
#59
b1011 $
b1011 (
b1110 !
b1110 &
b1011 %
#60
b1100 $
b1100 (
b1111 !
b1111 &
b1100 %
#61
b1101 $
b1101 (
b10000 !
b10000 &
b1101 %
#62
b1110 $
b1110 (
b10001 !
b10001 &
b1110 %
#63
b1111 $
b1111 (
b10010 !
b10010 &
b1111 %
#64
b0 $
b0 (
b100 #
b100 '
b100 !
b100 &
b100 "
b0 %
#65
b1 $
b1 (
b101 !
b101 &
b1 %
#66
b10 $
b10 (
b110 !
b110 &
b10 %
#67
b11 $
b11 (
b111 !
b111 &
b11 %
#68
b100 $
b100 (
b1000 !
b1000 &
b100 %
#69
b101 $
b101 (
b1001 !
b1001 &
b101 %
#70
b110 $
b110 (
b1010 !
b1010 &
b110 %
#71
b111 $
b111 (
b1011 !
b1011 &
b111 %
#72
b1000 $
b1000 (
b1100 !
b1100 &
b1000 %
#73
b1001 $
b1001 (
b1101 !
b1101 &
b1001 %
#74
b1010 $
b1010 (
b1110 !
b1110 &
b1010 %
#75
b1011 $
b1011 (
b1111 !
b1111 &
b1011 %
#76
b1100 $
b1100 (
b10000 !
b10000 &
b1100 %
#77
b1101 $
b1101 (
b10001 !
b10001 &
b1101 %
#78
b1110 $
b1110 (
b10010 !
b10010 &
b1110 %
#79
b1111 $
b1111 (
b10011 !
b10011 &
b1111 %
#80
b0 $
b0 (
b101 #
b101 '
b101 !
b101 &
b101 "
b0 %
#81
b1 $
b1 (
b110 !
b110 &
b1 %
#82
b10 $
b10 (
b111 !
b111 &
b10 %
#83
b11 $
b11 (
b1000 !
b1000 &
b11 %
#84
b100 $
b100 (
b1001 !
b1001 &
b100 %
#85
b101 $
b101 (
b1010 !
b1010 &
b101 %
#86
b110 $
b110 (
b1011 !
b1011 &
b110 %
#87
b111 $
b111 (
b1100 !
b1100 &
b111 %
#88
b1000 $
b1000 (
b1101 !
b1101 &
b1000 %
#89
b1001 $
b1001 (
b1110 !
b1110 &
b1001 %
#90
b1010 $
b1010 (
b1111 !
b1111 &
b1010 %
#91
b1011 $
b1011 (
b10000 !
b10000 &
b1011 %
#92
b1100 $
b1100 (
b10001 !
b10001 &
b1100 %
#93
b1101 $
b1101 (
b10010 !
b10010 &
b1101 %
#94
b1110 $
b1110 (
b10011 !
b10011 &
b1110 %
#95
b1111 $
b1111 (
b10100 !
b10100 &
b1111 %
#96
b0 $
b0 (
b110 #
b110 '
b110 !
b110 &
b110 "
b0 %
#97
b1 $
b1 (
b111 !
b111 &
b1 %
#98
b10 $
b10 (
b1000 !
b1000 &
b10 %
#99
b11 $
b11 (
b1001 !
b1001 &
b11 %
#100
b100 $
b100 (
b1010 !
b1010 &
b100 %
#101
b101 $
b101 (
b1011 !
b1011 &
b101 %
#102
b110 $
b110 (
b1100 !
b1100 &
b110 %
#103
b111 $
b111 (
b1101 !
b1101 &
b111 %
#104
b1000 $
b1000 (
b1110 !
b1110 &
b1000 %
#105
b1001 $
b1001 (
b1111 !
b1111 &
b1001 %
#106
b1010 $
b1010 (
b10000 !
b10000 &
b1010 %
#107
b1011 $
b1011 (
b10001 !
b10001 &
b1011 %
#108
b1100 $
b1100 (
b10010 !
b10010 &
b1100 %
#109
b1101 $
b1101 (
b10011 !
b10011 &
b1101 %
#110
b1110 $
b1110 (
b10100 !
b10100 &
b1110 %
#111
b1111 $
b1111 (
b10101 !
b10101 &
b1111 %
#112
b0 $
b0 (
b111 #
b111 '
b111 !
b111 &
b111 "
b0 %
#113
b1 $
b1 (
b1000 !
b1000 &
b1 %
#114
b10 $
b10 (
b1001 !
b1001 &
b10 %
#115
b11 $
b11 (
b1010 !
b1010 &
b11 %
#116
b100 $
b100 (
b1011 !
b1011 &
b100 %
#117
b101 $
b101 (
b1100 !
b1100 &
b101 %
#118
b110 $
b110 (
b1101 !
b1101 &
b110 %
#119
b111 $
b111 (
b1110 !
b1110 &
b111 %
#120
b1000 $
b1000 (
b1111 !
b1111 &
b1000 %
#121
b1001 $
b1001 (
b10000 !
b10000 &
b1001 %
#122
b1010 $
b1010 (
b10001 !
b10001 &
b1010 %
#123
b1011 $
b1011 (
b10010 !
b10010 &
b1011 %
#124
b1100 $
b1100 (
b10011 !
b10011 &
b1100 %
#125
b1101 $
b1101 (
b10100 !
b10100 &
b1101 %
#126
b1110 $
b1110 (
b10101 !
b10101 &
b1110 %
#127
b1111 $
b1111 (
b10110 !
b10110 &
b1111 %
#128
b0 $
b0 (
b1000 #
b1000 '
b1000 !
b1000 &
b1000 "
b0 %
#129
b1 $
b1 (
b1001 !
b1001 &
b1 %
#130
b10 $
b10 (
b1010 !
b1010 &
b10 %
#131
b11 $
b11 (
b1011 !
b1011 &
b11 %
#132
b100 $
b100 (
b1100 !
b1100 &
b100 %
#133
b101 $
b101 (
b1101 !
b1101 &
b101 %
#134
b110 $
b110 (
b1110 !
b1110 &
b110 %
#135
b111 $
b111 (
b1111 !
b1111 &
b111 %
#136
b1000 $
b1000 (
b10000 !
b10000 &
b1000 %
#137
b1001 $
b1001 (
b10001 !
b10001 &
b1001 %
#138
b1010 $
b1010 (
b10010 !
b10010 &
b1010 %
#139
b1011 $
b1011 (
b10011 !
b10011 &
b1011 %
#140
b1100 $
b1100 (
b10100 !
b10100 &
b1100 %
#141
b1101 $
b1101 (
b10101 !
b10101 &
b1101 %
#142
b1110 $
b1110 (
b10110 !
b10110 &
b1110 %
#143
b1111 $
b1111 (
b10111 !
b10111 &
b1111 %
#144
b0 $
b0 (
b1001 #
b1001 '
b1001 !
b1001 &
b1001 "
b0 %
#145
b1 $
b1 (
b1010 !
b1010 &
b1 %
#146
b10 $
b10 (
b1011 !
b1011 &
b10 %
#147
b11 $
b11 (
b1100 !
b1100 &
b11 %
#148
b100 $
b100 (
b1101 !
b1101 &
b100 %
#149
b101 $
b101 (
b1110 !
b1110 &
b101 %
#150
b110 $
b110 (
b1111 !
b1111 &
b110 %
#151
b111 $
b111 (
b10000 !
b10000 &
b111 %
#152
b1000 $
b1000 (
b10001 !
b10001 &
b1000 %
#153
b1001 $
b1001 (
b10010 !
b10010 &
b1001 %
#154
b1010 $
b1010 (
b10011 !
b10011 &
b1010 %
#155
b1011 $
b1011 (
b10100 !
b10100 &
b1011 %
#156
b1100 $
b1100 (
b10101 !
b10101 &
b1100 %
#157
b1101 $
b1101 (
b10110 !
b10110 &
b1101 %
#158
b1110 $
b1110 (
b10111 !
b10111 &
b1110 %
#159
b1111 $
b1111 (
b11000 !
b11000 &
b1111 %
#160
b0 $
b0 (
b1010 #
b1010 '
b1010 !
b1010 &
b1010 "
b0 %
#161
b1 $
b1 (
b1011 !
b1011 &
b1 %
#162
b10 $
b10 (
b1100 !
b1100 &
b10 %
#163
b11 $
b11 (
b1101 !
b1101 &
b11 %
#164
b100 $
b100 (
b1110 !
b1110 &
b100 %
#165
b101 $
b101 (
b1111 !
b1111 &
b101 %
#166
b110 $
b110 (
b10000 !
b10000 &
b110 %
#167
b111 $
b111 (
b10001 !
b10001 &
b111 %
#168
b1000 $
b1000 (
b10010 !
b10010 &
b1000 %
#169
b1001 $
b1001 (
b10011 !
b10011 &
b1001 %
#170
b1010 $
b1010 (
b10100 !
b10100 &
b1010 %
#171
b1011 $
b1011 (
b10101 !
b10101 &
b1011 %
#172
b1100 $
b1100 (
b10110 !
b10110 &
b1100 %
#173
b1101 $
b1101 (
b10111 !
b10111 &
b1101 %
#174
b1110 $
b1110 (
b11000 !
b11000 &
b1110 %
#175
b1111 $
b1111 (
b11001 !
b11001 &
b1111 %
#176
b0 $
b0 (
b1011 #
b1011 '
b1011 !
b1011 &
b1011 "
b0 %
#177
b1 $
b1 (
b1100 !
b1100 &
b1 %
#178
b10 $
b10 (
b1101 !
b1101 &
b10 %
#179
b11 $
b11 (
b1110 !
b1110 &
b11 %
#180
b100 $
b100 (
b1111 !
b1111 &
b100 %
#181
b101 $
b101 (
b10000 !
b10000 &
b101 %
#182
b110 $
b110 (
b10001 !
b10001 &
b110 %
#183
b111 $
b111 (
b10010 !
b10010 &
b111 %
#184
b1000 $
b1000 (
b10011 !
b10011 &
b1000 %
#185
b1001 $
b1001 (
b10100 !
b10100 &
b1001 %
#186
b1010 $
b1010 (
b10101 !
b10101 &
b1010 %
#187
b1011 $
b1011 (
b10110 !
b10110 &
b1011 %
#188
b1100 $
b1100 (
b10111 !
b10111 &
b1100 %
#189
b1101 $
b1101 (
b11000 !
b11000 &
b1101 %
#190
b1110 $
b1110 (
b11001 !
b11001 &
b1110 %
#191
b1111 $
b1111 (
b11010 !
b11010 &
b1111 %
#192
b0 $
b0 (
b1100 #
b1100 '
b1100 !
b1100 &
b1100 "
b0 %
#193
b1 $
b1 (
b1101 !
b1101 &
b1 %
#194
b10 $
b10 (
b1110 !
b1110 &
b10 %
#195
b11 $
b11 (
b1111 !
b1111 &
b11 %
#196
b100 $
b100 (
b10000 !
b10000 &
b100 %
#197
b101 $
b101 (
b10001 !
b10001 &
b101 %
#198
b110 $
b110 (
b10010 !
b10010 &
b110 %
#199
b111 $
b111 (
b10011 !
b10011 &
b111 %
#200
b1000 $
b1000 (
b10100 !
b10100 &
b1000 %
#201
b1001 $
b1001 (
b10101 !
b10101 &
b1001 %
#202
b1010 $
b1010 (
b10110 !
b10110 &
b1010 %
#203
b1011 $
b1011 (
b10111 !
b10111 &
b1011 %
#204
b1100 $
b1100 (
b11000 !
b11000 &
b1100 %
#205
b1101 $
b1101 (
b11001 !
b11001 &
b1101 %
#206
b1110 $
b1110 (
b11010 !
b11010 &
b1110 %
#207
b1111 $
b1111 (
b11011 !
b11011 &
b1111 %
#208
b0 $
b0 (
b1101 #
b1101 '
b1101 !
b1101 &
b1101 "
b0 %
#209
b1 $
b1 (
b1110 !
b1110 &
b1 %
#210
b10 $
b10 (
b1111 !
b1111 &
b10 %
#211
b11 $
b11 (
b10000 !
b10000 &
b11 %
#212
b100 $
b100 (
b10001 !
b10001 &
b100 %
#213
b101 $
b101 (
b10010 !
b10010 &
b101 %
#214
b110 $
b110 (
b10011 !
b10011 &
b110 %
#215
b111 $
b111 (
b10100 !
b10100 &
b111 %
#216
b1000 $
b1000 (
b10101 !
b10101 &
b1000 %
#217
b1001 $
b1001 (
b10110 !
b10110 &
b1001 %
#218
b1010 $
b1010 (
b10111 !
b10111 &
b1010 %
#219
b1011 $
b1011 (
b11000 !
b11000 &
b1011 %
#220
b1100 $
b1100 (
b11001 !
b11001 &
b1100 %
#221
b1101 $
b1101 (
b11010 !
b11010 &
b1101 %
#222
b1110 $
b1110 (
b11011 !
b11011 &
b1110 %
#223
b1111 $
b1111 (
b11100 !
b11100 &
b1111 %
#224
b0 $
b0 (
b1110 #
b1110 '
b1110 !
b1110 &
b1110 "
b0 %
#225
b1 $
b1 (
b1111 !
b1111 &
b1 %
#226
b10 $
b10 (
b10000 !
b10000 &
b10 %
#227
b11 $
b11 (
b10001 !
b10001 &
b11 %
#228
b100 $
b100 (
b10010 !
b10010 &
b100 %
#229
b101 $
b101 (
b10011 !
b10011 &
b101 %
#230
b110 $
b110 (
b10100 !
b10100 &
b110 %
#231
b111 $
b111 (
b10101 !
b10101 &
b111 %
#232
b1000 $
b1000 (
b10110 !
b10110 &
b1000 %
#233
b1001 $
b1001 (
b10111 !
b10111 &
b1001 %
#234
b1010 $
b1010 (
b11000 !
b11000 &
b1010 %
#235
b1011 $
b1011 (
b11001 !
b11001 &
b1011 %
#236
b1100 $
b1100 (
b11010 !
b11010 &
b1100 %
#237
b1101 $
b1101 (
b11011 !
b11011 &
b1101 %
#238
b1110 $
b1110 (
b11100 !
b11100 &
b1110 %
#239
b1111 $
b1111 (
b11101 !
b11101 &
b1111 %
#240
b0 $
b0 (
b1111 #
b1111 '
b1111 !
b1111 &
b1111 "
b0 %
#241
b1 $
b1 (
b10000 !
b10000 &
b1 %
#242
b10 $
b10 (
b10001 !
b10001 &
b10 %
#243
b11 $
b11 (
b10010 !
b10010 &
b11 %
#244
b100 $
b100 (
b10011 !
b10011 &
b100 %
#245
b101 $
b101 (
b10100 !
b10100 &
b101 %
#246
b110 $
b110 (
b10101 !
b10101 &
b110 %
#247
b111 $
b111 (
b10110 !
b10110 &
b111 %
#248
b1000 $
b1000 (
b10111 !
b10111 &
b1000 %
#249
b1001 $
b1001 (
b11000 !
b11000 &
b1001 %
#250
b1010 $
b1010 (
b11001 !
b11001 &
b1010 %
#251
b1011 $
b1011 (
b11010 !
b11010 &
b1011 %
#252
b1100 $
b1100 (
b11011 !
b11011 &
b1100 %
#253
b1101 $
b1101 (
b11100 !
b11100 &
b1101 %
#254
b1110 $
b1110 (
b11101 !
b11101 &
b1110 %
#255
b1111 $
b1111 (
b11110 !
b11110 &
b1111 %
#256
b10000 "
b10000 %
