E5TP1/sum4bit.v
module sum4bit(
    x0, //Sumando 0 (4-bit)
    x1, //Sumando 1 (4-bit)
    o   //Resultado (5-bit)
);

input wire [3:0] x0, x1;
output reg [4:0] o;

initial begin
  o = 0;
end

always @(x0 or x1) begin
  o = x0 + x1;
end


endmodule

E5TP1/sum4bit_tb.v
`include "sum4bit.v"

module sum4bit_tb;

//Defining test variables
reg [3:0] in0, in1, i, j;
wire [4:0] out;

//Connecting the ports
sum4bit sum_udt(.x0(in0), .x1(in1), .o(out));

//Code
initial begin
  $dumpfile("sum4bit.vcd");
  $dumpvars;
end

initial begin
  in0 = 0;
  in1 = 0;
  $display("In0\t+\tIn1\t=\tOut");
  $monitor("%d\t%d\t%d", in0, in1, out);
end


always begin
for (i = 0; i<15 ; i = i+1) begin
    #1 in0 = i;
    for (j=0; j<15; j = j+1) begin
      #1in1 = j;
    end
end
#20$finish;
end



endmodule

E5TP1/sum4bit.vcd
$date
	Wed Aug 22 01:04:02 2018
$end
$version
	Icarus Verilog
$end
$timescale
	1s
$end
$scope module sum4bit_tb $end
$var wire 5 ! out [4:0] $end
$var reg 4 " i [3:0] $end
$var reg 4 # in0 [3:0] $end
$var reg 4 $ in1 [3:0] $end
$var reg 4 % j [3:0] $end
$scope module sum_udt $end
$var wire 4 & x0 [3:0] $end
$var wire 4 ' x1 [3:0] $end
$var reg 5 ( o [4:0] $end
$upscope $end
$upscope $end
$enddefinitions $end
#0
$dumpvars
b0 (
b0 '
b0 &
bx %
b0 $
b0 #
b0 "
b0 !
$end
#1
b0 %
#2
b1 %
#3
b1 (
b1 !
b10 %
b1 $
b1 '
#4
b10 (
b10 !
b11 %
b10 $
b10 '
#5
b11 (
b11 !
b100 %
b11 $
b11 '
#6
b100 (
b100 !
b101 %
b100 $
b100 '
#7
b101 (
b101 !
b110 %
b101 $
b101 '
#8
b110 (
b110 !
b111 %
b110 $
b110 '
#9
b111 (
b111 !
b1000 %
b111 $
b111 '
#10
b1000 (
b1000 !
b1001 %
b1000 $
b1000 '
#11
b1001 (
b1001 !
b1010 %
b1001 $
b1001 '
#12
b1010 (
b1010 !
b1011 %
b1010 $
b1010 '
#13
b1011 (
b1011 !
b1100 %
b1011 $
b1011 '
#14
b1100 (
b1100 !
b1101 %
b1100 $
b1100 '
#15
b1101 (
b1101 !
b1110 %
b1101 $
b1101 '
#16
b1110 (
b1110 !
b1 "
b1111 %
b1110 $
b1110 '
#17
b1111 (
b1111 !
b0 %
b1 #
b1 &
#18
b1 (
b1 !
b1 %
b0 $
b0 '
#19
b10 (
b10 !
b10 %
b1 $
b1 '
#20
b11 (
b11 !
b11 %
b10 $
b10 '
#21
b100 (
b100 !
b100 %
b11 $
b11 '
#22
b101 (
b101 !
b101 %
b100 $
b100 '
#23
b110 (
b110 !
b110 %
b101 $
b101 '
#24
b111 (
b111 !
b111 %
b110 $
b110 '
#25
b1000 (
b1000 !
b1000 %
b111 $
b111 '
#26
b1001 (
b1001 !
b1001 %
b1000 $
b1000 '
#27
b1010 (
b1010 !
b1010 %
b1001 $
b1001 '
#28
b1011 (
b1011 !
b1011 %
b1010 $
b1010 '
#29
b1100 (
b1100 !
b1100 %
b1011 $
b1011 '
#30
b1101 (
b1101 !
b1101 %
b1100 $
b1100 '
#31
b1110 (
b1110 !
b1110 %
b1101 $
b1101 '
#32
b1111 (
b1111 !
b10 "
b1111 %
b1110 $
b1110 '
#33
b10000 (
b10000 !
b0 %
b10 #
b10 &
#34
b10 (
b10 !
b1 %
b0 $
b0 '
#35
b11 (
b11 !
b10 %
b1 $
b1 '
#36
b100 (
b100 !
b11 %
b10 $
b10 '
#37
b101 (
b101 !
b100 %
b11 $
b11 '
#38
b110 (
b110 !
b101 %
b100 $
b100 '
#39
b111 (
b111 !
b110 %
b101 $
b101 '
#40
b1000 (
b1000 !
b111 %
b110 $
b110 '
#41
b1001 (
b1001 !
b1000 %
b111 $
b111 '
#42
b1010 (
b1010 !
b1001 %
b1000 $
b1000 '
#43
b1011 (
b1011 !
b1010 %
b1001 $
b1001 '
#44
b1100 (
b1100 !
b1011 %
b1010 $
b1010 '
#45
b1101 (
b1101 !
b1100 %
b1011 $
b1011 '
#46
b1110 (
b1110 !
b1101 %
b1100 $
b1100 '
#47
b1111 (
b1111 !
b1110 %
b1101 $
b1101 '
#48
b10000 (
b10000 !
b11 "
b1111 %
b1110 $
b1110 '
#49
b10001 (
b10001 !
b0 %
b11 #
b11 &
#50
b11 (
b11 !
b1 %
b0 $
b0 '
#51
b100 (
b100 !
b10 %
b1 $
b1 '
#52
b101 (
b101 !
b11 %
b10 $
b10 '
#53
b110 (
b110 !
b100 %
b11 $
b11 '
#54
b111 (
b111 !
b101 %
b100 $
b100 '
#55
b1000 (
b1000 !
b110 %
b101 $
b101 '
#56
b1001 (
b1001 !
b111 %
b110 $
b110 '
#57
b1010 (
b1010 !
b1000 %
b111 $
b111 '
#58
b1011 (
b1011 !
b1001 %
b1000 $
b1000 '
#59
b1100 (
b1100 !
b1010 %
b1001 $
b1001 '
#60
b1101 (
b1101 !
b1011 %
b1010 $
b1010 '
#61
b1110 (
b1110 !
b1100 %
b1011 $
b1011 '
#62
b1111 (
b1111 !
b1101 %
b1100 $
b1100 '
#63
b10000 (
b10000 !
b1110 %
b1101 $
b1101 '
#64
b10001 (
b10001 !
b100 "
b1111 %
b1110 $
b1110 '
#65
b10010 (
b10010 !
b0 %
b100 #
b100 &
#66
b100 (
b100 !
b1 %
b0 $
b0 '
#67
b101 (
b101 !
b10 %
b1 $
b1 '
#68
b110 (
b110 !
b11 %
b10 $
b10 '
#69
b111 (
b111 !
b100 %
b11 $
b11 '
#70
b1000 (
b1000 !
b101 %
b100 $
b100 '
#71
b1001 (
b1001 !
b110 %
b101 $
b101 '
#72
b1010 (
b1010 !
b111 %
b110 $
b110 '
#73
b1011 (
b1011 !
b1000 %
b111 $
b111 '
#74
b1100 (
b1100 !
b1001 %
b1000 $
b1000 '
#75
b1101 (
b1101 !
b1010 %
b1001 $
b1001 '
#76
b1110 (
b1110 !
b1011 %
b1010 $
b1010 '
#77
b1111 (
b1111 !
b1100 %
b1011 $
b1011 '
#78
b10000 (
b10000 !
b1101 %
b1100 $
b1100 '
#79
b10001 (
b10001 !
b1110 %
b1101 $
b1101 '
#80
b10010 (
b10010 !
b101 "
b1111 %
b1110 $
b1110 '
#81
b10011 (
b10011 !
b0 %
b101 #
b101 &
#82
b101 (
b101 !
b1 %
b0 $
b0 '
#83
b110 (
b110 !
b10 %
b1 $
b1 '
#84
b111 (
b111 !
b11 %
b10 $
b10 '
#85
b1000 (
b1000 !
b100 %
b11 $
b11 '
#86
b1001 (
b1001 !
b101 %
b100 $
b100 '
#87
b1010 (
b1010 !
b110 %
b101 $
b101 '
#88
b1011 (
b1011 !
b111 %
b110 $
b110 '
#89
b1100 (
b1100 !
b1000 %
b111 $
b111 '
#90
b1101 (
b1101 !
b1001 %
b1000 $
b1000 '
#91
b1110 (
b1110 !
b1010 %
b1001 $
b1001 '
#92
b1111 (
b1111 !
b1011 %
b1010 $
b1010 '
#93
b10000 (
b10000 !
b1100 %
b1011 $
b1011 '
#94
b10001 (
b10001 !
b1101 %
b1100 $
b1100 '
#95
b10010 (
b10010 !
b1110 %
b1101 $
b1101 '
#96
b10011 (
b10011 !
b110 "
b1111 %
b1110 $
b1110 '
#97
b10100 (
b10100 !
b0 %
b110 #
b110 &
#98
b110 (
b110 !
b1 %
b0 $
b0 '
#99
b111 (
b111 !
b10 %
b1 $
b1 '
#100
b1000 (
b1000 !
b11 %
b10 $
b10 '
#101
b1001 (
b1001 !
b100 %
b11 $
b11 '
#102
b1010 (
b1010 !
b101 %
b100 $
b100 '
#103
b1011 (
b1011 !
b110 %
b101 $
b101 '
#104
b1100 (
b1100 !
b111 %
b110 $
b110 '
#105
b1101 (
b1101 !
b1000 %
b111 $
b111 '
#106
b1110 (
b1110 !
b1001 %
b1000 $
b1000 '
#107
b1111 (
b1111 !
b1010 %
b1001 $
b1001 '
#108
b10000 (
b10000 !
b1011 %
b1010 $
b1010 '
#109
b10001 (
b10001 !
b1100 %
b1011 $
b1011 '
#110
b10010 (
b10010 !
b1101 %
b1100 $
b1100 '
#111
b10011 (
b10011 !
b1110 %
b1101 $
b1101 '
#112
b10100 (
b10100 !
b111 "
b1111 %
b1110 $
b1110 '
#113
b10101 (
b10101 !
b0 %
b111 #
b111 &
#114
b111 (
b111 !
b1 %
b0 $
b0 '
#115
b1000 (
b1000 !
b10 %
b1 $
b1 '
#116
b1001 (
b1001 !
b11 %
b10 $
b10 '
#117
b1010 (
b1010 !
b100 %
b11 $
b11 '
#118
b1011 (
b1011 !
b101 %
b100 $
b100 '
#119
b1100 (
b1100 !
b110 %
b101 $
b101 '
#120
b1101 (
b1101 !
b111 %
b110 $
b110 '
#121
b1110 (
b1110 !
b1000 %
b111 $
b111 '
#122
b1111 (
b1111 !
b1001 %
b1000 $
b1000 '
#123
b10000 (
b10000 !
b1010 %
b1001 $
b1001 '
#124
b10001 (
b10001 !
b1011 %
b1010 $
b1010 '
#125
b10010 (
b10010 !
b1100 %
b1011 $
b1011 '
#126
b10011 (
b10011 !
b1101 %
b1100 $
b1100 '
#127
b10100 (
b10100 !
b1110 %
b1101 $
b1101 '
#128
b10101 (
b10101 !
b1000 "
b1111 %
b1110 $
b1110 '
#129
b10110 (
b10110 !
b0 %
b1000 #
b1000 &
#130
b1000 (
b1000 !
b1 %
b0 $
b0 '
#131
b1001 (
b1001 !
b10 %
b1 $
b1 '
#132
b1010 (
b1010 !
b11 %
b10 $
b10 '
#133
b1011 (
b1011 !
b100 %
b11 $
b11 '
#134
b1100 (
b1100 !
b101 %
b100 $
b100 '
#135
b1101 (
b1101 !
b110 %
b101 $
b101 '
#136
b1110 (
b1110 !
b111 %
b110 $
b110 '
#137
b1111 (
b1111 !
b1000 %
b111 $
b111 '
#138
b10000 (
b10000 !
b1001 %
b1000 $
b1000 '
#139
b10001 (
b10001 !
b1010 %
b1001 $
b1001 '
#140
b10010 (
b10010 !
b1011 %
b1010 $
b1010 '
#141
b10011 (
b10011 !
b1100 %
b1011 $
b1011 '
#142
b10100 (
b10100 !
b1101 %
b1100 $
b1100 '
#143
b10101 (
b10101 !
b1110 %
b1101 $
b1101 '
#144
b10110 (
b10110 !
b1001 "
b1111 %
b1110 $
b1110 '
#145
b10111 (
b10111 !
b0 %
b1001 #
b1001 &
#146
b1001 (
b1001 !
b1 %
b0 $
b0 '
#147
b1010 (
b1010 !
b10 %
b1 $
b1 '
#148
b1011 (
b1011 !
b11 %
b10 $
b10 '
#149
b1100 (
b1100 !
b100 %
b11 $
b11 '
#150
b1101 (
b1101 !
b101 %
b100 $
b100 '
#151
b1110 (
b1110 !
b110 %
b101 $
b101 '
#152
b1111 (
b1111 !
b111 %
b110 $
b110 '
#153
b10000 (
b10000 !
b1000 %
b111 $
b111 '
#154
b10001 (
b10001 !
b1001 %
b1000 $
b1000 '
#155
b10010 (
b10010 !
b1010 %
b1001 $
b1001 '
#156
b10011 (
b10011 !
b1011 %
b1010 $
b1010 '
#157
b10100 (
b10100 !
b1100 %
b1011 $
b1011 '
#158
b10101 (
b10101 !
b1101 %
b1100 $
b1100 '
#159
b10110 (
b10110 !
b1110 %
b1101 $
b1101 '
#160
b10111 (
b10111 !
b1010 "
b1111 %
b1110 $
b1110 '
#161
b11000 (
b11000 !
b0 %
b1010 #
b1010 &
#162
b1010 (
b1010 !
b1 %
b0 $
b0 '
#163
b1011 (
b1011 !
b10 %
b1 $
b1 '
#164
b1100 (
b1100 !
b11 %
b10 $
b10 '
#165
b1101 (
b1101 !
b100 %
b11 $
b11 '
#166
b1110 (
b1110 !
b101 %
b100 $
b100 '
#167
b1111 (
b1111 !
b110 %
b101 $
b101 '
#168
b10000 (
b10000 !
b111 %
b110 $
b110 '
#169
b10001 (
b10001 !
b1000 %
b111 $
b111 '
#170
b10010 (
b10010 !
b1001 %
b1000 $
b1000 '
#171
b10011 (
b10011 !
b1010 %
b1001 $
b1001 '
#172
b10100 (
b10100 !
b1011 %
b1010 $
b1010 '
#173
b10101 (
b10101 !
b1100 %
b1011 $
b1011 '
#174
b10110 (
b10110 !
b1101 %
b1100 $
b1100 '
#175
b10111 (
b10111 !
b1110 %
b1101 $
b1101 '
#176
b11000 (
b11000 !
b1011 "
b1111 %
b1110 $
b1110 '
#177
b11001 (
b11001 !
b0 %
b1011 #
b1011 &
#178
b1011 (
b1011 !
b1 %
b0 $
b0 '
#179
b1100 (
b1100 !
b10 %
b1 $
b1 '
#180
b1101 (
b1101 !
b11 %
b10 $
b10 '
#181
b1110 (
b1110 !
b100 %
b11 $
b11 '
#182
b1111 (
b1111 !
b101 %
b100 $
b100 '
#183
b10000 (
b10000 !
b110 %
b101 $
b101 '
#184
b10001 (
b10001 !
b111 %
b110 $
b110 '
#185
b10010 (
b10010 !
b1000 %
b111 $
b111 '
#186
b10011 (
b10011 !
b1001 %
b1000 $
b1000 '
#187
b10100 (
b10100 !
b1010 %
b1001 $
b1001 '
#188
b10101 (
b10101 !
b1011 %
b1010 $
b1010 '
#189
b10110 (
b10110 !
b1100 %
b1011 $
b1011 '
#190
b10111 (
b10111 !
b1101 %
b1100 $
b1100 '
#191
b11000 (
b11000 !
b1110 %
b1101 $
b1101 '
#192
b11001 (
b11001 !
b1100 "
b1111 %
b1110 $
b1110 '
#193
b11010 (
b11010 !
b0 %
b1100 #
b1100 &
#194
b1100 (
b1100 !
b1 %
b0 $
b0 '
#195
b1101 (
b1101 !
b10 %
b1 $
b1 '
#196
b1110 (
b1110 !
b11 %
b10 $
b10 '
#197
b1111 (
b1111 !
b100 %
b11 $
b11 '
#198
b10000 (
b10000 !
b101 %
b100 $
b100 '
#199
b10001 (
b10001 !
b110 %
b101 $
b101 '
#200
b10010 (
b10010 !
b111 %
b110 $
b110 '
#201
b10011 (
b10011 !
b1000 %
b111 $
b111 '
#202
b10100 (
b10100 !
b1001 %
b1000 $
b1000 '
#203
b10101 (
b10101 !
b1010 %
b1001 $
b1001 '
#204
b10110 (
b10110 !
b1011 %
b1010 $
b1010 '
#205
b10111 (
b10111 !
b1100 %
b1011 $
b1011 '
#206
b11000 (
b11000 !
b1101 %
b1100 $
b1100 '
#207
b11001 (
b11001 !
b1110 %
b1101 $
b1101 '
#208
b11010 (
b11010 !
b1101 "
b1111 %
b1110 $
b1110 '
#209
b11011 (
b11011 !
b0 %
b1101 #
b1101 &
#210
b1101 (
b1101 !
b1 %
b0 $
b0 '
#211
b1110 (
b1110 !
b10 %
b1 $
b1 '
#212
b1111 (
b1111 !
b11 %
b10 $
b10 '
#213
b10000 (
b10000 !
b100 %
b11 $
b11 '
#214
b10001 (
b10001 !
b101 %
b100 $
b100 '
#215
b10010 (
b10010 !
b110 %
b101 $
b101 '
#216
b10011 (
b10011 !
b111 %
b110 $
b110 '
#217
b10100 (
b10100 !
b1000 %
b111 $
b111 '
#218
b10101 (
b10101 !
b1001 %
b1000 $
b1000 '
#219
b10110 (
b10110 !
b1010 %
b1001 $
b1001 '
#220
b10111 (
b10111 !
b1011 %
b1010 $
b1010 '
#221
b11000 (
b11000 !
b1100 %
b1011 $
b1011 '
#222
b11001 (
b11001 !
b1101 %
b1100 $
b1100 '
#223
b11010 (
b11010 !
b1110 %
b1101 $
b1101 '
#224
b11011 (
b11011 !
b1110 "
b1111 %
b1110 $
b1110 '
#225
b11100 (
b11100 !
b0 %
b1110 #
b1110 &
#226
b1110 (
b1110 !
b1 %
b0 $
b0 '
#227
b1111 (
b1111 !
b10 %
b1 $
b1 '
#228
b10000 (
b10000 !
b11 %
b10 $
b10 '
#229
b10001 (
b10001 !
b100 %
b11 $
b11 '
#230
b10010 (
b10010 !
b101 %
b100 $
b100 '
#231
b10011 (
b10011 !
b110 %
b101 $
b101 '
#232
b10100 (
b10100 !
b111 %
b110 $
b110 '
#233
b10101 (
b10101 !
b1000 %
b111 $
b111 '
#234
b10110 (
b10110 !
b1001 %
b1000 $
b1000 '
#235
b10111 (
b10111 !
b1010 %
b1001 $
b1001 '
#236
b11000 (
b11000 !
b1011 %
b1010 $
b1010 '
#237
b11001 (
b11001 !
b1100 %
b1011 $
b1011 '
#238
b11010 (
b11010 !
b1101 %
b1100 $
b1100 '
#239
b11011 (
b11011 !
b1110 %
b1101 $
b1101 '
#240
b11100 (
b11100 !
b1111 "
b1111 %
b1110 $
b1110 '
