E3TP1/encoder.v
module  encoder (
encoder_in, //Entrada de 4 patas
encoder_out //Salida Binaria de 2 patas
);

  //Initialize Input(s).
  input [3:0] encoder_in;

  //Initialize Output(s).
  output [1:0] encoder_out;
  
  //No se si esto hacia falta pero por ahora lo dejo.
  wire [3:0] encoder_in;
  reg [1:0] encoder_out;

  always @ (encoder_in) begin
    encoder_out = 0;
    
    /*
    //Trying with cases. However, it doesn't contemplate value hierarchy.
    case (encoder_in)
      4'b0001: encoder_out = 0;
      4'b0010: encoder_out = 1;
      4'b0100: encoder_out = 2;
      4'b1000: encoder_out = 3;
      default: encoder_out = 0;
    endcase
    */

    //Trying with if satetements. It should be considering value hierarchy.
    //MSB should take priority over the output.
    if (encoder_in & 4'b0001) begin
      encoder_out = 0;
    end
    if (encoder_in & 4'b0010) begin
      encoder_out = 1;
    end
    if (encoder_in & 4'b0100) begin
      encoder_out = 2;
    end
    if (encoder_in & 4'b1000) begin
      encoder_out = 3;
    end

  end


endmodule

E3TP1/encoder_tb.v
`include "encoder.v"

module encoder_tb;

reg [3:0] data_in;
wire [1:0] data_out;

encoder e_0(.encoder_in(data_in), .encoder_out(data_out));

initial begin
    data_in = 4'b0001;
end

always begin
    #1 data_in = 4'b0010;
    #1 data_in = 4'b0100;
    #1 data_in = 4'b1000;
    #1 data_in = 4'b0011;
    #1 data_in = 4'b0101;
    #1 data_in = 4'b1001;
    #1 data_in = 4'b0110;
    #1 data_in = 4'b1010;
    #1 data_in = 4'b1100;
    #10 $finish;
end

initial begin
  $dumpfile("encoder.vcd");
  $dumpvars;
end

initial begin
  $display("Input value\tOutput\tValue");
  $monitor("%b\t\t%b\t%d",data_in, data_out, data_out);
end

endmodule

E3TP1/encoder.vcd
$date
	Wed Aug 29 15:25:36 2018
$end
$version
	Icarus Verilog
$end
$timescale
	1s
$end
$scope module encoder_tb $end
$var wire 2 ! data_out [1:0] $end
$var reg 4 " data_in [3:0] $end
$scope module e_0 $end
$var wire 4 # encoder_in [3:0] $end
$var reg 2 $ encoder_out [1:0] $end
$upscope $end
$upscope $end
$enddefinitions $end
#0
$dumpvars
b0 $
b1 #
b1 "
b0 !
$end
#1
b1 $
b1 !
b10 "
b10 #
#2
b10 $
b10 !
b100 "
b100 #
#3
b11 $
b11 !
b1000 "
b1000 #
#4
b1 $
b1 !
b11 "
b11 #
#5
b10 $
b10 !
b101 "
b101 #
#6
b11 $
b11 !
b1001 "
b1001 #
#7
b10 $
b10 !
b110 "
b110 #
#8
b11 $
b11 !
b1010 "
b1010 #
#9
b11 $
b11 !
b1100 "
b1100 #
